Workbook

Sheet README
A1: HOW TO USE THIS TEMPLATE
A2: Colour rule | B2: BLUE text = you type it. BLACK text = a formula, do not overwrite.
A3: Header rule | B3: GREEN header = input column. NAVY header = derived column.
A4: Sample rows | B4: Every sheet has sample rows so you can see the formulas working. Delete them and paste your own data over the top.
A5: Extending | B5: Formulas are pre-filled and blank-guarded to row 201 (Dim_Fund, Fact_Work), 401 (Fact_Milestone), 60 (Dim_Analyst). For more, select the last formula row and drag down.
A6: Time entry | B6: Cut-offs as real times (04:30), not text. Actual events as full date-times.
A8: DECISIONS BUILT INTO THIS VERSION
A9: EUC adjustment | B9: Fifth product flag. EUC = 1 moves 5 points toward reconciliation, the same direction as ETD. Recon_Pct now ranges 55 to 85, so NAV calculation can fall to 15% of required time on a fund carrying ETD, both OTC types and EUC without PFC. Those funds have almost no room after the pricing gate — check the Feasibility_Flag on them first.
A10: Strategic client | B10: Captured as a Yes/No flag in Dim_Fund column E. The derived Client_Tier column turns it into Strategic or Non-strategic for use as a dashboard label and slicer. Use the YESNO transform if your export holds it as Y/N.
A11: A feed that does not apply | B11: Never leave the cut-off blank — blank reads as 00:00, which gives that fund the largest slack in the book and sorts it to the bottom of the watchlist. Set Has_<feed>_Process to No and put the PRICING cut-off in the time cell. Slack becomes zero, the feed is treated as never binding, and the slack, rank and watchlist columns all show n/a.
A12: A cut-off you do not know | B12: Different problem. Enter a conservative estimate and set Cutoff_Data_Quality to Estimated. Filter those funds out of supplier analysis — an estimated pricing cut-off produces phantom SLA breaches you do not want in a conversation with the pricing team.
A13: Pricing or client cut-off missing | B13: Not a gap, an exclusion. Those two anchor every calculation. Leave the fund out rather than guess.
A14: Custody and TA arrivals — NOT captured | B14: They carry 5–8 hours of slack before the pricing gate, so their lateness is absorbed and never reaches NAV. Chasing email trails for them buys nothing. Their cut-offs stay in Dim_Fund because they still define the slack calculation.
A15: Broker — ETA, not a cut-off | B15: Broker_ETA is the supplier's own estimate, not a contractual deadline. Treat 'on time vs ETA' with care: it says nothing about whether the ETA was reasonable. Once you have actuals, systematic optimism in the ETA is its own finding.
A16: Broker actuals — watchlist only | B16: Capture them only for funds flagged CAPTURE in Dim_Fund. Everything else has too much slack for a late broker to bind.
A17: Pricing — mandatory | B17: Slack of zero by definition, already in your system. Every minute late is a minute on NAV.
A18: Analyst — two fields, two jobs | B18: Dim_Fund.Default_Analyst_ID is the normal owner, used for PLANNED capacity. Fact_Work.Maker_ID is who actually did it, from the maker record, used for ACTUAL capacity. The gap between them is the reassignment rate.
A19: Checker — captured, unbudgeted | B19: The 450 minutes covers MAKER effort only. Check time is real time in someone's day that no capacity figure allows for. Dim_Analyst shows it in its own column and adds it into True_Load_Mins.
A21: SHEETS
A22: Constants | B22: 20.38, 450, the five % adjustments, and the broker watchlist threshold.
A23: Dim_Team | B23: One row per team. Shift start, shifts, capacity.
A24: Dim_Signoff | B24: Three rows. Oversight and Client tails are PLACEHOLDERS — not yet agreed.
A25: Dim_Fund | B25: One row per fund. 19 inputs, 23 derived. v4.5 adds 9 derived columns (BC to BK).
A26: Dim_Analyst | B26: One row per analyst, 3 inputs. Planned load, actual load, check load and reassignment all calculate themselves.
A27: Fact_Milestone | B27: One row per fund per day per feed. Pricing always; Broker only for watchlist funds.
A28: Fact_Work | B28: One row per fund per day. 11 inputs, 18 derived. v4.5 adds 26 Power BI columns (BA to BZ).
A29: Checks | B29: Run after loading. Every check has a target.
A31: BUILD IN PHASES
A32: Phase 1 | B32: Constants + Dim_Team + Dim_Fund + Dim_Analyst. No event data at all. Gives planned load, utilisation, the feasibility flag and the broker watchlist. Start here.
A33: Phase 2 | B33: Add Fact_Milestone (pricing only, to begin with). Gives the whole pricing critical-path view.
A34: Phase 3 | B34: Add Fact_Work. Maker ID comes free from the system record, so actual capacity and reassignment are available immediately — not a later phase.
A36: STILL OPEN
A37: Oversight and client tails | B37: No agreed target. Measure the actual for three months, take the 80th percentile, use that as a working assumption and negotiate from evidence.
A38: Shift assignment for two-shift teams | B38: Not captured. Build on single-shift teams and report the rest as unmeasurable — that is a legitimate output and a better case for capturing it than asking in the abstract.
A39: Check time budget | B39: If checking turns out to be a material share of the day, the 450 needs revisiting or checking needs its own weightage. The Check_Mins_PerDay column tells you whether it is material.
A41: TWO TRAPS WORTH CHECKING
A42: Pricing arrival meaning | B42: Is it when the file landed, or when someone marked it received? The second includes human lag and overstates supplier delay. Matters if you show these numbers to the pricing team.
A43: Delivered_DT meaning | B43: Is it FA completion or post-sign-off delivery? These differ on roughly 30% of funds and mixing them corrupts every breach rate.
A45: STATUS LOG — HOW FACT_WORK IS NOW BUILT
A46: What you paste | B46: Status_Log, long format: one row per status change, with Date, Fund_ID, Status text, Timestamp and the Person name. Paste the whole log — only four statuses are read, everything else is ignored.
A47: The four statuses | B47: "Changed to the status of Calculated", "...Controlled", "...Fund accounting signed off", "...signed off".
A48: Min or Max | B48: Calculated uses the EARLIEST row — first touch. The three end statuses use the LATEST — the version that counted. Max on Calculated would hide reruns: a fund done twice would look like a short job that started late.
A49: NAV_End differs by model | B49: Client sign-off funds have no Controlled status, so NAV_End is Fund accounting signed off. Everything else uses Controlled. Do NOT compare NAV durations across the two — use FA_Total_Mins, which spans Calculated to Fund accounting signed off for every fund.
A50: Check time | B50: Controlled to Fund accounting signed off. Available for non-client funds only, which is roughly half the book — better than none.
A51: Dim_Person | B51: The log holds names, the model needs IDs. Every distinct name must appear here or that fund-day drops out of the capacity view silently. The In_Dim_Analyst column flags names that do not resolve.
A52: Recon start is gone | B52: No system records it, so Implied_Work_Start_DT back-calculates from Calculated minus Recon_Mins. Queue_After_Pricing_Mins then measures how long a fund sat with pricing in hand and nobody free. It assumes work took exactly its budgeted minutes — so a fund that overran its budget is indistinguishable from one that started late. Label these as reconstructed, not observed.
A53: Broker actuals are gone | B53: Fact_Milestone is Pricing only. Broker_ETA still drives the slack and watchlist columns in Dim_Fund, so you can still say which funds have thin broker margin — just not how often the broker missed.
A54: Self_Checked | B54: Same person on Calculated and Controlled. A four-eyes breach, surfaced here as a by-product. Treat it as a control issue in its own right, separate from anything about bottlenecks.
A56: VERSION 3 — WHAT CHANGED
A57: Two dates, not one | B57: Fact_Work now carries NAV_Date (the valuation date, your reporting grain) and Process_Date (when the work happened). Cut-offs anchor to Process_Date, because 17:30 means 17:30 on the day you produce it. Processing_Lag_Days is the gap, and a fund drifting from T+1 to T+2 is a finding nothing else catches.
A58: Names, not IDs | B58: The status log holds names, so the whole model is keyed on Analyst_Name. Dim_Analyst has one row per name exactly as it appears in the log. External approvers such as Client Ops get Active = No — they consume no FA capacity but must be listed or their rows drop out silently.
A59: Planned load moved | B59: It used to sum every fund in an analyst's book as if all ran daily, which badly overstates anyone holding monthly funds. It now comes from Fact_Work rows grouped on Default_Analyst_Name — same denominator as actual, so the two are directly comparable and frequency handles itself.
A60: Frequency is derived | B60: Dim_Fund now shows Runs_Observed and NAV_Frequency_Observed, counted from Fact_Work. A fund whose observed frequency does not match expectation is visible without being an input.
A61: Month-end is the thing to look at | B61: Monthly funds land together on top of the daily book. Average utilisation can read 70% while month-end runs at 150%. Plot utilisation by Process_Date, not an average, or the spike is invisible.
A63: VERSION 4 — PRICING AT TOP LEVEL
A64: What changed | B64: Pricing arrives per TOP (pricing group), not per fund. Fact_Milestone is regrained to one row per TOP per process date — far smaller than fund level, and it matches how the supplier actually delivers.
A65: Dim_TOP | B65: New sheet, one row per pricing group. Fund count, earliest and latest fund cut-off, and the spread between them all derive from Dim_Fund.
A66: The binding cut-off | B66: The supplier sends one file for the whole group, so the deadline it must hit is the EARLIEST fund cut-off in that TOP. A file on time for one fund can be late for another in the same group.
A67: Two different late measures | B67: Fact_Milestone[SLA_Met] measures the TOP against its binding cut-off — the supplier conversation. Fact_Work[Pricing_Late_For_This_Fund] measures the same arrival against each fund's own PSA cut-off — the fund-level service conversation. They will not agree, and both are correct.
A68: Cut-off spread is a finding | B68: Dim_TOP[Cutoff_Spread_Mins] shows how far apart cut-offs are inside one group. A wide spread means either the earliest fund carries a deadline the others do not, or the later funds have slack nobody uses. Review before renegotiating any PSA.
A69: Blast radius | B69: Fact_Milestone[Fund_Days_Impacted] counts how many fund-days each late arrival touched. One late TOP with five funds is five late funds, not one — the concentration measure the fund-level model could not produce.
A71: PER-DAY BINDING CUT-OFF
A72: What changed | B72: Fact_Milestone[Binding_Cutoff_Hr] is now the earliest cut-off among the funds of that TOP that actually ran on that date (found in Fact_Work). Before, it was the earliest across every fund assigned to the TOP, which made a TOP look late on days when its early-cut-off fund did not run.
A73: Funds_In_TOP on Fact_Milestone | B73: Now counts the funds of that TOP that ran that day, not every fund assigned to it. Fund_Days_Impacted uses it, so blast radius is no longer overstated. Column names are unchanged, so Power Query and measures need no edits.
A74: Days with no running funds | B74: If none of a TOP's funds ran on a date, Binding_Cutoff_Hr is blank and the delivery is not scored.
A75: Dim_TOP is a design view | B75: Earliest, Latest and Spread in Dim_TOP stay static, across all assigned funds. They drive the Group Design page, not the SLA.
A77: WHY MINIFS / MAXIFS
A78: What went wrong | B78: Dim_TOP Earliest and Latest, and Fact_Milestone Binding_Cutoff_Hr, used a min-via-max trick with IFERROR over a whole range inside SUMPRODUCT. LibreOffice reads that as an array and gets it right. Excel can evaluate the IFERROR part one row at a time, so every row returned its own fund's cut-off instead of the group's earliest and latest.
A79: The replacement | B79: MINIFS and MAXIFS need no array evaluation. They require Excel 2019 or Microsoft 365. On older Excel they show a name error rather than a wrong number.
A80: Fact_Work helper | B80: Column AN, Fund_Pricing_Cutoff_Hr, holds each fund-day's own pricing cut-off so Fact_Milestone can take the earliest among the funds that ran.
A82: ROW LIMITS — WHOLE-COLUMN FORMULAS
A83: What went wrong | B83: The Fact_Milestone and Dim_TOP formulas read Fact_Work to row 301 and Dim_Fund to row 201. With real volumes the matching rows sit below that, so MINIFS found nothing and returned 0, which made the binding cut-off 00:00 and every delivery look hundreds of minutes late.
A84: The fix | B84: They now read whole columns, so they keep working however many rows you load, and they return blank, not 0, when nothing matches. A cut-off of 0 is treated as a missing input.
A85: Fixed ranges removed | B85: Every formula that totals, looks up or counts now reads whole columns, so none depends on how many rows you load. The only fixed sizes left are Dim_Slot and Dim_Clock (32 half-hour slots by design).
A87: BOTTLENECK ANALYSIS COLUMNS
A88: Where the buffer goes | B88: Planned_Buffer_Mins is the client cut-off minus the fund's PSA cut-off, NAV budget and planned tail. Var_Pricing, Pricing_To_Calc, Var_NAV_Stretch, Var_Control and Var_Approval are how much each stage used or saved against plan. They add up to the breach: Breach = sum of variances minus planned buffer. Bridge_Check tests that to within 2 minutes.
A89: Breach_Class | B89: Lost on arrival: pricing arrived with less headroom than the NAV budget plus tail, so even instant work could not have met the cut-off. Lost after arrival: there was time, and it was used up inside the team or in approval. The test uses the budget, so it is strict and will under-count lost-on-arrival.
A90: Due slots | B90: Due_Slot_Hr buckets each fund-day by the 30-minute slot in which its TOP's pricing was due: the earliest cut-off among that TOP's funds that ran that day, taken from Fact_Milestone (or the static Dim_TOP value when no delivery was logged). Every fund in a TOP shares one slot, because they are all released together when the file arrives. Dim_Slot counts fund-days per slot and flags Peak slots. Fact_Milestone gets the same slot from its binding cut-off.
A91: Clock columns | B91: Arrival_Hr, Start_Hr and End_Hr are time of day in hours. They feed the cumulative flow chart through Dim_Clock.
A92: Business days | B92: Constants!B13 now reads whole columns, so it keeps working above row 301.
A93: Dim_Slot | B93: One row per 30-minute slot by the time a TOP's pricing was DUE, not by a fund's own cut-off and not by when the file arrived. Funds are released in waves when their TOP lands, so their wait belongs to the TOP's slot. Keep the sheet free of notes: they would load as data.
A94: Dim_Clock | B94: Slot END times for the cumulative flow chart. Keep it disconnected from every other table.
A95: Dim_BufferStep | B95: Keep disconnected. The text in column A is matched exactly by the Bridge Mins measure, so do not reword it.
A97: FILLING FORMULAS DOWN TO YOUR LAST ROW
A98: The rule | B98: Formulas that read whole columns already cover every row you load. What does not extend itself is the row of formulas next to your pasted data. After pasting, select the formulas in the last pre-filled row and double-click the fill handle: Excel fills down as far as the data in the adjacent column goes.
A99: Where to do it | B99: Fact_Work (D to AZ, from the input columns A to C), Fact_Milestone (D to K), Dim_Fund (the derived block), Dim_Fund_Staging, and Status_Log columns G and H.
A100: How you will know | B100: The FORMULA COVERAGE block on the Checks sheet counts rows that have data but no formulas. Every line should read 0.
A101: Status_Log lookups | B101: Calculated, Controlled, FA signed off and signed off times, the rerun count, and the maker and checker names now use MINIFS and MAXIFS plus two helper columns (G Key, H Key_Time). They need Excel 2019 or Microsoft 365. A full recalculation on tens of thousands of fund-days can take minutes; doing this pivot in Power Query is the faster long-term route.
A102: Notes moved here | B102: The explanatory notes that sat in data columns of Dim_Analyst, Dim_TOP and Raw_Fund_Import were moved to this sheet, because text in a data column is read as data.
A103: Moved from Dim_Analyst | B103: One row per NAME exactly as it appears in Status_Log. Active = No for external approvers — they consume no FA capacity but must be listed or their rows drop.
A104: Moved from Dim_TOP | B104: One row per pricing group. Earliest, Latest and Spread are a STATIC design view across every fund assigned to the TOP. The daily SLA does not read them: Fact_Milestone[Binding_Cutoff_Hr] is recalculated for each TOP on each date from the funds that actually ran.
A105: Moved from Raw_Fund_Import | B105: PASTE YOUR EXPORT HERE — row 1 headers, row 2 onward data. Column order does not matter. Extra columns are ignored.
A107: VERSION 4.5 — POWER BI PAGES
A108: What changed | B108: Columns added to the right of every existing table so the two report pages (Supplier Concentration Risk, Fund Level) can be built without Power Query logic. No existing column moved or was renamed. All DAX ships as a Tabular Editor C# script (NAV_Bottleneck_Measures_v4_5.csx). PBI_Mapping lists every visual, field and measure.
A109: New sheets | B109: Dim_SupplierType, Dim_WaitGroup, Dim_DetailRow: disconnected row lists for SWITCH measures. Dim_Cause: legend order for Possible_Cause, related to Fact_Work. Keep all four free of notes: they load as data. PBI_Mapping is documentation: do not load it.
A110: Thin slack | B110: Constants!B17, default 0 (zero tolerance). A feed is thin when its slack to the pricing cut-off is at or below it, so a late file reaches NAV directly. The broker watchlist keeps its own threshold in B14.
A111: Wait after pricing — three parts | B111: Wait_After_Pricing_Mins = Queue_Wait_Mins + Own_Recon_Mins + Other_Holdup_Mins. Queue = minutes between pricing arrival and this fund's Calculated when the same maker was WORKING on another fund that day, i.e. inside that fund-day's work window (Work_Start_Num to Work_End_Num: Calculated minus its recon budget, to Calculated). Hold-ups on the funds ahead are not passed down. Own recon = the same maker reconciling THIS fund, up to its Recon_Mins budget, taken from what is left. Other hold-up = the remainder: data not ready, breaks, recon over budget, or work not in the log. Nothing is called idle: the maker usually does both recon and calculation. RECONSTRUCTED, not observed: both queue and own recon use recon budgets, not actual work times, and only work in the status log is visible.
A112: Possible cause | B112: Breached fund-days only, first match wins: Pricing late (this fund's own PSA cut-off), Thin custody slack, Broker-dependent, None of these. Custody, TA and broker arrivals are not captured, so only pricing is a measured cause.
A113: Timeline bars | B113: Bar_Offset_Hr (transparent) + Bar_Wait_Hr + Bar_NAV_Hr + Bar_Control_Hr + Bar_Tail_Hr = delivery time of day. Client sign-off funds have no Controlled step: their NAV bar runs to FA signed off and the control bar is 0.
A114: Fix: missing client cut-off | B114: Fact_Work[Client_Cutoff_DT] used to fall back to midnight when the client cut-off was missing, inventing a breach. It is now blank, and Headroom_After_Pricing_Mins is guarded for it. Checks counts them.
...

Sheet Constants
A1: CONSTANT | B1: VALUE | C1: NOTES
A2: FTE denominator | B2: 20.38 | C2: INPUT — confirmed constant across all funds.
A3: Daily capacity (minutes) | B3: 450 | C3: INPUT — one analyst's day. MAKER EFFORT ONLY. Checking is not inside this number.
A4: Minutes per weightage unit | B4: =B3/B2 -> 22.080471 | C4: FORMULA — 450 / 20.38 = 22.08.
A6: Base reconciliation % | B6: 60 | C6: INPUT — fund with none of the four products.
A7: ETD adjustment | B7: 5 | C7: INPUT
A8: OTC (non-CFD) adjustment | B8: 5 | C8: INPUT
A9: OTC (CFD) adjustment | B9: 10 | C9: INPUT
A10: PFC adjustment | B10: -5 | C10: INPUT — negative, moves the boundary toward NAV calculation.
A11: EUC adjustment | B11: 5 | C11: INPUT — positive, moves the boundary toward reconciliation (same direction as ETD).
A13: Business days in Fact_Work | B13: =IF(COUNT(Fact_Work!$B:$B)=0,1,NETWORKDAYS(MIN(Fact_Work!$B:$B),MAX(Fact_Work!$B:$B))) -> 3 | C13: FORMULA — used to convert total actual minutes into a per-day figure.
A14: Broker slack watchlist threshold (mins) | B14: 90 | C14: INPUT — funds with less broker margin than this are the only ones where a late broker can bind. Capture broker actuals for these funds only.
A15: Peak percentile | B15: 0.75 | C15: INPUT — a time slot counts as Peak when its funds-due-per-day is at or above this percentile of the busy slots.
A16: WARNING | C16: Changing any INPUT moves every fund's target at once, including history. Version-control before editing.
A17: Thin slack threshold (mins) | B17: 0 | C17: INPUT — v4.5. A custody, TA or broker feed is THIN when its slack to the pricing cut-off is at or below this. 0 = zero tolerance: thin only when the feed's cut-off is at or after the pricing cut-off, so any lateness reaches NAV directly. Separate from the broker watchlist threshold in B14.
A18: Shift length (hrs) | B18: 9 | C18: INPUT — v4.5. Hours on desk including breaks, the same for every team. Shift end = Dim_Team shift start + this. Places each maker on the clock for the Team load by hour chart.

Sheet Dim_Team
A1: Team_ID | B1: Team_Name | C1: Shift_Start | D1: Shifts_In_Team | E1: Daily_Capacity_Mins | F1: Shift_Start_Hr | G1: Shift_End_Hr
A2: TM01 | B2: Equity Ops | C2: 0.375 | D2: 1 | E2: 450 | F2: =IF($A2="","",HOUR($C2)+MINUTE($C2)/60) -> 9 | G2: =IF($A2="","",$F2+Constants!$B$18) -> 18
A3: TM02 | B3: Fixed Income Ops | C3: 0.375 | D3: 1 | E3: 450 | F3: =IF($A3="","",HOUR($C3)+MINUTE($C3)/60) -> 9 | G3: =IF($A3="","",$F3+Constants!$B$18) -> 18
A4: TM03 | B4: Multi-Asset Ops | C4: 0.41666667 | D4: 1 | E4: 450 | F4: =IF($A4="","",HOUR($C4)+MINUTE($C4)/60) -> 10 | G4: =IF($A4="","",$F4+Constants!$B$18) -> 19
A5: TM04 | B5: Derivatives Ops | C5: 0.375 | D5: 2 | E5: 450 | F5: =IF($A5="","",HOUR($C5)+MINUTE($C5)/60) -> 9 | G5: =IF($A5="","",$F5+Constants!$B$18) -> 18
F6: =IF($A6="","",HOUR($C6)+MINUTE($C6)/60) | G6: =IF($A6="","",$F6+Constants!$B$18)
F7: =IF($A7="","",HOUR($C7)+MINUTE($C7)/60) | G7: =IF($A7="","",$F7+Constants!$B$18)
F8: =IF($A8="","",HOUR($C8)+MINUTE($C8)/60) | G8: =IF($A8="","",$F8+Constants!$B$18)
F9: =IF($A9="","",HOUR($C9)+MINUTE($C9)/60) | G9: =IF($A9="","",$F9+Constants!$B$18)
F10: =IF($A10="","",HOUR($C10)+MINUTE($C10)/60) | G10: =IF($A10="","",$F10+Constants!$B$18)
F11: =IF($A11="","",HOUR($C11)+MINUTE($C11)/60) | G11: =IF($A11="","",$F11+Constants!$B$18)
F12: =IF($A12="","",HOUR($C12)+MINUTE($C12)/60) | G12: =IF($A12="","",$F12+Constants!$B$18)
F13: =IF($A13="","",HOUR($C13)+MINUTE($C13)/60) | G13: =IF($A13="","",$F13+Constants!$B$18)
F14: =IF($A14="","",HOUR($C14)+MINUTE($C14)/60) | G14: =IF($A14="","",$F14+Constants!$B$18)
F15: =IF($A15="","",HOUR($C15)+MINUTE($C15)/60) | G15: =IF($A15="","",$F15+Constants!$B$18)
F16: =IF($A16="","",HOUR($C16)+MINUTE($C16)/60) | G16: =IF($A16="","",$F16+Constants!$B$18)
F17: =IF($A17="","",HOUR($C17)+MINUTE($C17)/60) | G17: =IF($A17="","",$F17+Constants!$B$18)
... F39: =IF($A39="","",HOUR($C39)+MINUTE($C39)/60) | G39: =IF($A39="","",$F39+Constants!$B$18)

Sheet Dim_Signoff
A1: Signoff_Model | B1: Responsible_Party | C1: Planned_Tail_Mins | D1: Status
A2: FA | B2: FA team — checker only, no external step | C2: 0 | D2: Defined
A3: Oversight | B3: Internal oversight team | C3: 25 | D3: NOT AGREED — placeholder
A4: Client | B4: Client approves | C4: 46 | D4: NOT AGREED — placeholder

Sheet Dim_Fund
A1: Fund_ID | B1: Fund_Name | C1: Client_ID | D1: Client_Name | E1: Strategic_Client | F1: Team_ID | G1: Default_Analyst_Name | H1: Weightage | I1: ETD | J1: OTC_nonCFD | K1: OTC_CFD | L1: PFC | M1: EUC | N1: Has_Custody_Process | O1: Has_TA_Process | P1: Has_Broker_Process | Q1: Custody_Cutoff | R1: TA_Cutoff | S1: Broker_ETA | T1: Pricing_Cutoff | U1: TOP_ID | V1: Client_Cutoff | W1: NAV_Deadline | X1: Signoff_Model | Y1: Cutoff_Data_Quality | Z1: Recon_Pct | AA1: NAV_Pct | AB1: Required_Mins | AC1: Recon_Mins | AD1: NAV_Mins | AE1: Custody_Cutoff_Hr | AF1: TA_Cutoff_Hr | AG1: Broker_ETA_Hr | AH1: Pricing_Cutoff_Hr | AI1: Client_Cutoff_Hr | AJ1: NAV_Deadline_Hr | AK1: Shift_Start_Hr | AL1: Planned_Tail_Mins | AM1: Slack_Custody_Mins | AN1: Slack_TA_Mins | AO1: Slack_Broker_Mins | AP1: Avail_Recon_Mins | AQ1: Avail_NAV_Mins | AR1: Recon_Feasible | AS1: NAV_Feasible | AT1: Feasibility_Flag | AU1: Broker_Watchlist | AV1: Broker_Slack_Rank | AW1: Client_Tier | AX1: Runs_Observed | AY1: NAV_Frequency_Observed | AZ1: TOP_Binding_Cutoff_Hr | BA1: Cutoff_Vs_TOP_Mins | BB1: TOP_Cutoff_Risk | BC1: Client_First_In_TOP | BD1: Broker_Dependent | BE1: Thin_Custody_Slack | BF1: Thin_TA_Slack | BG1: Thin_Broker_Slack | BH1: Custody_Slack_Group | BI1: Slack_Custody_Num | BJ1: Slack_TA_Num | BK1: Slack_Broker_Num
A2: FD-1001 | B2: Sample Fund 1001 | C2: CL01 | D2: Meridian Pensions | E2: Yes | F2: TM01 | G2: Lim Wei Ming | H2: 2.152 | I2: 1 | J2: 0 | K2: 0 | L2: 1 | M2: 0 | N2: Yes | O2: No | P2: No | Q2: 0.20237179 | R2: 0.52066418 | S2: 0.52066418 | T2: 0.52066418 | U2: TOP-EQ1 | V2: 0.69703251 | W2: 0.72185538 | X2: FA | Y2: Estimated | Z2: =IF($A2="","",Constants!$B$6+$I2*Constants!$B$7+$J2*Constants!$B$8+$K2*Constants!$B$9+$L2*Constants!$B$10+$M2*Constants!$B$11) -> 60 | AA2: =IF($A2="","",100-Z2) -> 40 | AB2: =IF($A2="","",ROUND($H2*Constants!$B$4,1)) -> 47.5 | AC2: =IF($A2="","",ROUND(AB2*Z2/100,1)) -> 28.5 | AD2: =IF($A2="","",ROUND(AB2*AA2/100,1)) -> 19 | AE2: =IF($A2="","",HOUR($Q2)+MINUTE($Q2)/60) -> 4.85 | AF2: =IF($A2="","",HOUR($R2)+MINUTE($R2)/60) -> 12.483333 | AG2: =IF($A2="","",HOUR($S2)+MINUTE($S2)/60) -> 12.483333 | AH2: =IF($A2="","",HOUR($T2)+MINUTE($T2)/60) -> 12.483333 | AI2: =IF($A2="","",HOUR($V2)+MINUTE($V2)/60) -> 16.716667 | AJ2: =IF($A2="","",HOUR($W2)+MINUTE($W2)/60) -> 17.316667 | AK2: =IF($A2="","",VLOOKUP($F2,Dim_Team!$A:$F,6,0)) -> 9 | AL2: =IF($A2="","",VLOOKUP($X2,Dim_Signoff!$A:$C,3,0)) -> 0 | AM2: =IF($A2="","",IF($N2="No","n/a",ROUND((AH2-AE2)*60,0))) -> 458 | AN2: =IF($A2="","",IF($O2="No","n/a",ROUND((AH2-AF2)*60,0))) -> n/a | AO2: =IF($A2="","",IF($P2="No","n/a",ROUND((AH2-AG2)*60,0))) -> n/a | AP2: =IF($A2="","",ROUND((AH2-AK2)*60,0)) -> 209 | AQ2: =IF($A2="","",ROUND((AI2-AH2)*60,0)) -> 254 | AR2: =IF($A2="","",IF(AP2>=AC2,"Yes","No")) -> Yes | AS2: =IF($A2="","",IF(AQ2>=AD2+AL2,"Yes","No")) -> Yes | AT2: =IF($A2="","",IF(AND(AR2="Yes",AS2="Yes"),"OK","REVIEW")) -> OK | AU2: =IF($A2="","",IF($P2="No","Not applicable",IF(AO2<Constants!$B$14,"CAPTURE","Not needed"))) -> Not applicable | AV2: =IF($A2="","",IF($P2="No","n/a",RANK(AO2,AO:AO,1))) -> n/a | AW2: =IF($A2="","",IF(UPPER($E2)="YES","Strategic","Non-strategic")) -> Strategic | AX2: =IF($A2="","",COUNTIFS(Fact_Work!$C:$C,$A2)) -> 3 | AY2: =IF($A2="","",IF(AX2=0,"Not seen",IF(AX2>=Constants!$B$13*0.6,"Daily",IF(AX2>=Constants!$B$13*0.12,"Weekly","Monthly or ad hoc")))) -> Daily | AZ2: =IF($A2="","",IFERROR(VLOOKUP($U2,Dim_TOP!$A:$H,8,0),"")) -> 11.65 | BA2: =IF($A2="","",IFERROR(ROUND((AH2-AZ2)*60,0),"")) -> 50 | BB2: =IF($A2="","",IF(BA2="","",IF(BA2<=0,"Sets the deadline","Later than peers by "&BA2&" min"))) -> Later than peers by 50 min | BC2: =IF($A2="","",IF($U2="",0,IF(COUNTIFS($U$2:$U2,$U2,$C$2:$C2,$C2)=1,1,0))) -> 1 | BD2: =IF($A2="","",IF(UPPER($P2)="YES","Yes","No")) -> No | BE2: =IF($A2="","",IF($N2="No","n/a",IF(AM2<=Constants!$B$17,"Yes","No"))) -> No | BF2: =IF($A2="","",IF($O2="No","n/a",IF(AN2<=Constants!$B$17,"Yes","No"))) -> n/a | BG2: =IF($A2="","",IF($P2="No","n/a",IF(AO2<=Constants!$B$17,"Yes","No"))) -> n/a | BH2: =IF($A2="","",IF($N2="No","No custody process",IF(BE2="Yes","Thin custody slack","Ample custody slack"))) -> Ample custody slack | BI2: =IF($A2="","",IF($N2="No","",AM2)) -> 458 | BJ2: =IF($A2="","",IF($O2="No","",AN2)) | BK2: =IF($A2="","",IF($P2="No","",AO2))
A3: FD-1002 | B3: Sample Fund 1002 | C3: CL02 | D3: Northgate Insurance | E3: Yes | F3: TM01 | G3: Siti Noraini | H3: 1.213 | I3: 0 | J3: 0 | K3: 0 | L3: 0 | M3: 1 | N3: Yes | O3: Yes | P3: Yes | Q3: 0.19558832 | R3: 0.15141525 | S3: 0.34989132 | T3: 0.51935645 | U3: TOP-FI1 | V3: 0.68414656 | W3: 0.71053446 | X3: FA | Y3: Confirmed | Z3: =IF($A3="","",Constants!$B$6+$I3*Constants!$B$7+$J3*Constants!$B$8+$K3*Constants!$B$9+$L3*Constants!$B$10+$M3*Constants!$B$11) -> 65 | AA3: =IF($A3="","",100-Z3) -> 35 | AB3: =IF($A3="","",ROUND($H3*Constants!$B$4,1)) -> 26.8 | AC3: =IF($A3="","",ROUND(AB3*Z3/100,1)) -> 17.4 | AD3: =IF($A3="","",ROUND(AB3*AA3/100,1)) -> 9.4 | AE3: =IF($A3="","",HOUR($Q3)+MINUTE($Q3)/60) -> 4.6833333 | AF3: =IF($A3="","",HOUR($R3)+MINUTE($R3)/60) -> 3.6333333 | AG3: =IF($A3="","",HOUR($S3)+MINUTE($S3)/60) -> 8.3833333 | AH3: =IF($A3="","",HOUR($T3)+MINUTE($T3)/60) -> 12.45 | AI3: =IF($A3="","",HOUR($V3)+MINUTE($V3)/60) -> 16.416667 | AJ3: =IF($A3="","",HOUR($W3)+MINUTE($W3)/60) -> 17.05 | AK3: =IF($A3="","",VLOOKUP($F3,Dim_Team!$A:$F,6,0)) -> 9 | AL3: =IF($A3="","",VLOOKUP($X3,Dim_Signoff!$A:$C,3,0)) -> 0 | AM3: =IF($A3="","",IF($N3="No","n/a",ROUND((AH3-AE3)*60,0))) -> 466 | AN3: =IF($A3="","",IF($O3="No","n/a",ROUND((AH3-AF3)*60,0))) -> 529 | AO3: =IF($A3="","",IF($P3="No","n/a",ROUND((AH3-AG3)*60,0))) -> 244 | AP3: =IF($A3="","",ROUND((AH3-AK3)*60,0)) -> 207 | AQ3: =IF($A3="","",ROUND((AI3-AH3)*60,0)) -> 238 | AR3: =IF($A3="","",IF(AP3>=AC3,"Yes","No")) -> Yes | AS3: =IF($A3="","",IF(AQ3>=AD3+AL3,"Yes","No")) -> Yes | AT3: =IF($A3="","",IF(AND(AR3="Yes",AS3="Yes"),"OK","REVIEW")) -> OK | AU3: =IF($A3="","",IF($P3="No","Not applicable",IF(AO3<Constants!$B$14,"CAPTURE","Not needed"))) -> Not needed | AV3: =IF($A3="","",IF($P3="No","n/a",RANK(AO3,AO:AO,1))) -> 5 | AW3: =IF($A3="","",IF(UPPER($E3)="YES","Strategic","Non-strategic")) -> Strategic | AX3: =IF($A3="","",COUNTIFS(Fact_Work!$C:$C,$A3)) -> 3 | AY3: =IF($A3="","",IF(AX3=0,"Not seen",IF(AX3>=Constants!$B$13*0.6,"Daily",IF(AX3>=Constants!$B$13*0.12,"Weekly","Monthly or ad hoc")))) -> Daily | AZ3: =IF($A3="","",IFERROR(VLOOKUP($U3,Dim_TOP!$A:$H,8,0),"")) -> 12.45 | BA3: =IF($A3="","",IFERROR(ROUND((AH3-AZ3)*60,0),"")) -> 0 | BB3: =IF($A3="","",IF(BA3="","",IF(BA3<=0,"Sets the deadline","Later than peers by "&BA3&" min"))) -> Sets the deadline | BC3: =IF($A3="","",IF($U3="",0,IF(COUNTIFS($U$2:$U3,$U3,$C$2:$C3,$C3)=1,1,0))) -> 1 | BD3: =IF($A3="","",IF(UPPER($P3)="YES","Yes","No")) -> Yes | BE3: =IF($A3="","",IF($N3="No","n/a",IF(AM3<=Constants!$B$17,"Yes","No"))) -> No | BF3: =IF($A3="","",IF($O3="No","n/a",IF(AN3<=Constants!$B$17,"Yes","No"))) -> No | BG3: =IF($A3="","",IF($P3="No","n/a",IF(AO3<=Constants!$B$17,"Yes","No"))) -> No | BH3: =IF($A3="","",IF($N3="No","No custody process",IF(BE3="Yes","Thin custody slack","Ample custody slack"))) -> Ample custody slack | BI3: =IF($A3="","",IF($N3="No","",AM3)) -> 466 | BJ3: =IF($A3="","",IF($O3="No","",AN3)) -> 529 | BK3: =IF($A3="","",IF($P3="No","",AO3)) -> 244
A4: FD-1003 | B4: Sample Fund 1003 | C4: CL03 | D4: Halvern Wealth | E4: No | F4: TM02 | G4: Raj Kumar | H4: 2.073 | I4: 0 | J4: 0 | K4: 0 | L4: 0 | M4: 0 | N4: Yes | O4: Yes | P4: Yes | Q4: 0.18913262 | R4: 0.19178209 | S4: 0.31743308 | T4: 0.48878378 | U4: TOP-MA1 | V4: 0.66347521 | W4: 0.69532609 | X4: FA | Y4: Confirmed | Z4: =IF($A4="","",Constants!$B$6+$I4*Constants!$B$7+$J4*Constants!$B$8+$K4*Constants!$B$9+$L4*Constants!$B$10+$M4*Constants!$B$11) -> 60 | AA4: =IF($A4="","",100-Z4) -> 40 | AB4: =IF($A4="","",ROUND($H4*Constants!$B$4,1)) -> 45.8 | AC4: =IF($A4="","",ROUND(AB4*Z4/100,1)) -> 27.5 | AD4: =IF($A4="","",ROUND(AB4*AA4/100,1)) -> 18.3 | AE4: =IF($A4="","",HOUR($Q4)+MINUTE($Q4)/60) -> 4.5333333 | AF4: =IF($A4="","",HOUR($R4)+MINUTE($R4)/60) -> 4.6 | AG4: =IF($A4="","",HOUR($S4)+MINUTE($S4)/60) -> 7.6166667 | AH4: =IF($A4="","",HOUR($T4)+MINUTE($T4)/60) -> 11.716667 | AI4: =IF($A4="","",HOUR($V4)+MINUTE($V4)/60) -> 15.916667 | AJ4: =IF($A4="","",HOUR($W4)+MINUTE($W4)/60) -> 16.683333 | AK4: =IF($A4="","",VLOOKUP($F4,Dim_Team!$A:$F,6,0)) -> 9 | AL4: =IF($A4="","",VLOOKUP($X4,Dim_Signoff!$A:$C,3,0)) -> 0 | AM4: =IF($A4="","",IF($N4="No","n/a",ROUND((AH4-AE4)*60,0))) -> 431 | AN4: =IF($A4="","",IF($O4="No","n/a",ROUND((AH4-AF4)*60,0))) -> 427 | AO4: =IF($A4="","",IF($P4="No","n/a",ROUND((AH4-AG4)*60,0))) -> 246 | AP4: =IF($A4="","",ROUND((AH4-AK4)*60,0)) -> 163 | AQ4: =IF($A4="","",ROUND((AI4-AH4)*60,0)) -> 252 | AR4: =IF($A4="","",IF(AP4>=AC4,"Yes","No")) -> Yes | AS4: =IF($A4="","",IF(AQ4>=AD4+AL4,"Yes","No")) -> Yes | AT4: =IF($A4="","",IF(AND(AR4="Yes",AS4="Yes"),"OK","REVIEW")) -> OK | AU4: =IF($A4="","",IF($P4="No","Not applicable",IF(AO4<Constants!$B$14,"CAPTURE","Not needed"))) -> Not needed | AV4: =IF($A4="","",IF($P4="No","n/a",RANK(AO4,AO:AO,1))) -> 6 | AW4: =IF($A4="","",IF(UPPER($E4)="YES","Strategic","Non-strategic")) -> Non-strategic | AX4: =IF($A4="","",COUNTIFS(Fact_Work!$C:$C,$A4)) -> 3 | AY4: =IF($A4="","",IF(AX4=0,"Not seen",IF(AX4>=Constants!$B$13*0.6,"Daily",IF(AX4>=Constants!$B$13*0.12,"Weekly","Monthly or ad hoc")))) -> Daily | AZ4: =IF($A4="","",IFERROR(VLOOKUP($U4,Dim_TOP!$A:$H,8,0),"")) -> 11.716667 | BA4: =IF($A4="","",IFERROR(ROUND((AH4-AZ4)*60,0),"")) -> 0 | BB4: =IF($A4="","",IF(BA4="","",IF(BA4<=0,"Sets the deadline","Later than peers by "&BA4&" min"))) -> Sets the deadline | BC4: =IF($A4="","",IF($U4="",0,IF(COUNTIFS($U$2:$U4,$U4,$C$2:$C4,$C4)=1,1,0))) -> 1 | BD4: =IF($A4="","",IF(UPPER($P4)="YES","Yes","No")) -> Yes | BE4: =IF($A4="","",IF($N4="No","n/a",IF(AM4<=Constants!$B$17,"Yes","No"))) -> No | BF4: =IF($A4="","",IF($O4="No","n/a",IF(AN4<=Constants!$B$17,"Yes","No"))) -> No | BG4: =IF($A4="","",IF($P4="No","n/a",IF(AO4<=Constants!$B$17,"Yes","No"))) -> No | BH4: =IF($A4="","",IF($N4="No","No custody process",IF(BE4="Yes","Thin custody slack","Ample custody slack"))) -> Ample custody slack | BI4: =IF($A4="","",IF($N4="No","",AM4)) -> 431 | BJ4: =IF($A4="","",IF($O4="No","",AN4)) -> 427 | BK4: =IF($A4="","",IF($P4="No","",AO4)) -> 246
A5: FD-1004 | B5: Sample Fund 1004 | C5: CL01 | D5: Meridian Pensions | E5: Yes | F5: TM03 | G5: Chen Xiao | H5: 2.099 | I5: 0 | J5: 0 | K5: 0 | L5: 0 | M5: 0 | N5: Yes | O5: Yes | P5: Yes | Q5: 0.18626602 | R5: 0.16115303 | S5: 0.31727212 | T5: 0.52841758 | U5: TOP-ALT | V5: 0.7071355 | W5: 0.73348044 | X5: Oversight | Y5: Confirmed | Z5: =IF($A5="","",Constants!$B$6+$I5*Constants!$B$7+$J5*Constants!$B$8+$K5*Constants!$B$9+$L5*Constants!$B$10+$M5*Constants!$B$11) -> 60 | AA5: =IF($A5="","",100-Z5) -> 40 | AB5: =IF($A5="","",ROUND($H5*Constants!$B$4,1)) -> 46.3 | AC5: =IF($A5="","",ROUND(AB5*Z5/100,1)) -> 27.8 | AD5: =IF($A5="","",ROUND(AB5*AA5/100,1)) -> 18.5 | AE5: =IF($A5="","",HOUR($Q5)+MINUTE($Q5)/60) -> 4.4666667 | AF5: =IF($A5="","",HOUR($R5)+MINUTE($R5)/60) -> 3.8666667 | AG5: =IF($A5="","",HOUR($S5)+MINUTE($S5)/60) -> 7.6 | AH5: =IF($A5="","",HOUR($T5)+MINUTE($T5)/60) -> 12.666667 | AI5: =IF($A5="","",HOUR($V5)+MINUTE($V5)/60) -> 16.966667 | AJ5: =IF($A5="","",HOUR($W5)+MINUTE($W5)/60) -> 17.6 | AK5: =IF($A5="","",VLOOKUP($F5,Dim_Team!$A:$F,6,0)) -> 10 | AL5: =IF($A5="","",VLOOKUP($X5,Dim_Signoff!$A:$C,3,0)) -> 25 | AM5: =IF($A5="","",IF($N5="No","n/a",ROUND((AH5-AE5)*60,0))) -> 492 | AN5: =IF($A5="","",IF($O5="No","n/a",ROUND((AH5-AF5)*60,0))) -> 528 | AO5: =IF($A5="","",IF($P5="No","n/a",ROUND((AH5-AG5)*60,0))) -> 304 | AP5: =IF($A5="","",ROUND((AH5-AK5)*60,0)) -> 160 | AQ5: =IF($A5="","",ROUND((AI5-AH5)*60,0)) -> 258 | AR5: =IF($A5="","",IF(AP5>=AC5,"Yes","No")) -> Yes | AS5: =IF($A5="","",IF(AQ5>=AD5+AL5,"Yes","No")) -> Yes | AT5: =IF($A5="","",IF(AND(AR5="Yes",AS5="Yes"),"OK","REVIEW")) -> OK | AU5: =IF($A5="","",IF($P5="No","Not applicable",IF(AO5<Constants!$B$14,"CAPTURE","Not needed"))) -> Not needed | AV5: =IF($A5="","",IF($P5="No","n/a",RANK(AO5,AO:AO,1))) -> 8 | AW5: =IF($A5="","",IF(UPPER($E5)="YES","Strategic","Non-strategic")) -> Strategic | AX5: =IF($A5="","",COUNTIFS(Fact_Work!$C:$C,$A5)) -> 3 | AY5: =IF($A5="","",IF(AX5=0,"Not seen",IF(AX5>=Constants!$B$13*0.6,"Daily",IF(AX5>=Constants!$B$13*0.12,"Weekly","Monthly or ad hoc")))) -> Daily | AZ5: =IF($A5="","",IFERROR(VLOOKUP($U5,Dim_TOP!$A:$H,8,0),"")) -> 11.633333 | BA5: =IF($A5="","",IFERROR(ROUND((AH5-AZ5)*60,0),"")) -> 62 | BB5: =IF($A5="","",IF(BA5="","",IF(BA5<=0,"Sets the deadline","Later than peers by "&BA5&" min"))) -> Later than peers by 62 min | BC5: =IF($A5="","",IF($U5="",0,IF(COUNTIFS($U$2:$U5,$U5,$C$2:$C5,$C5)=1,1,0))) -> 1 | BD5: =IF($A5="","",IF(UPPER($P5)="YES","Yes","No")) -> Yes | BE5: =IF($A5="","",IF($N5="No","n/a",IF(AM5<=Constants!$B$17,"Yes","No"))) -> No | BF5: =IF($A5="","",IF($O5="No","n/a",IF(AN5<=Constants!$B$17,"Yes","No"))) -> No | BG5: =IF($A5="","",IF($P5="No","n/a",IF(AO5<=Constants!$B$17,"Yes","No"))) -> No | BH5: =IF($A5="","",IF($N5="No","No custody process",IF(BE5="Yes","Thin custody slack","Ample custody slack"))) -> Ample custody slack | BI5: =IF($A5="","",IF($N5="No","",AM5)) -> 492 | BJ5: =IF($A5="","",IF($O5="No","",AN5)) -> 528 | BK5: =IF($A5="","",IF($P5="No","",AO5)) -> 304
A6: FD-1005 | B6: Sample Fund 1005 | C6: CL02 | D6: Northgate Insurance | E6: Yes | F6: TM03 | G6: Aisha Rahman | H6: 1.597 | I6: 0 | J6: 0 | K6: 0 | L6: 0 | M6: 1 | N6: Yes | O6: No | P6: Yes | Q6: 0.19102841 | R6: 0.54287619 | S6: 0.2938606 | T6: 0.54287619 | U6: TOP-EQ1 | V6: 0.68369544 | W6: 0.7172464 | X6: Client | Y6: Confirmed | Z6: =IF($A6="","",Constants!$B$6+$I6*Constants!$B$7+$J6*Constants!$B$8+$K6*Constants!$B$9+$L6*Constants!$B$10+$M6*Constants!$B$11) -> 65 | AA6: =IF($A6="","",100-Z6) -> 35 | AB6: =IF($A6="","",ROUND($H6*Constants!$B$4,1)) -> 35.3 | AC6: =IF($A6="","",ROUND(AB6*Z6/100,1)) -> 22.9 | AD6: =IF($A6="","",ROUND(AB6*AA6/100,1)) -> 12.4 | AE6: =IF($A6="","",HOUR($Q6)+MINUTE($Q6)/60) -> 4.5833333 | AF6: =IF($A6="","",HOUR($R6)+MINUTE($R6)/60) -> 13.016667 | AG6: =IF($A6="","",HOUR($S6)+MINUTE($S6)/60) -> 7.05 | AH6: =IF($A6="","",HOUR($T6)+MINUTE($T6)/60) -> 13.016667 | AI6: =IF($A6="","",HOUR($V6)+MINUTE($V6)/60) -> 16.4 | AJ6: =IF($A6="","",HOUR($W6)+MINUTE($W6)/60) -> 17.2 | AK6: =IF($A6="","",VLOOKUP($F6,Dim_Team!$A:$F,6,0)) -> 10 | AL6: =IF($A6="","",VLOOKUP($X6,Dim_Signoff!$A:$C,3,0)) -> 46 | AM6: =IF($A6="","",IF($N6="No","n/a",ROUND((AH6-AE6)*60,0))) -> 506 | AN6: =IF($A6="","",IF($O6="No","n/a",ROUND((AH6-AF6)*60,0))) -> n/a | AO6: =IF($A6="","",IF($P6="No","n/a",ROUND((AH6-AG6)*60,0))) -> 358 | AP6: =IF($A6="","",ROUND((AH6-AK6)*60,0)) -> 181 | AQ6: =IF($A6="","",ROUND((AI6-AH6)*60,0)) -> 203 | AR6: =IF($A6="","",IF(AP6>=AC6,"Yes","No")) -> Yes | AS6: =IF($A6="","",IF(AQ6>=AD6+AL6,"Yes","No")) -> Yes | AT6: =IF($A6="","",IF(AND(AR6="Yes",AS6="Yes"),"OK","REVIEW")) -> OK | AU6: =IF($A6="","",IF($P6="No","Not applicable",IF(AO6<Constants!$B$14,"CAPTURE","Not needed"))) -> Not needed | AV6: =IF($A6="","",IF($P6="No","n/a",RANK(AO6,AO:AO,1))) -> 10 | AW6: =IF($A6="","",IF(UPPER($E6)="YES","Strategic","Non-strategic")) -> Strategic | AX6: =IF($A6="","",COUNTIFS(Fact_Work!$C:$C,$A6)) -> 3 | AY6: =IF($A6="","",IF(AX6=0,"Not seen",IF(AX6>=Constants!$B$13*0.6,"Daily",IF(AX6>=Constants!$B$13*0.12,"Weekly","Monthly or ad hoc")))) -> Daily | AZ6: =IF($A6="","",IFERROR(VLOOKUP($U6,Dim_TOP!$A:$H,8,0),"")) -> 11.65 | BA6: =IF($A6="","",IFERROR(ROUND((AH6-AZ6)*60,0),"")) -> 82 | BB6: =IF($A6="","",IF(BA6="","",IF(BA6<=0,"Sets the deadline","Later than peers by "&BA6&" min"))) -> Later than peers by 82 min | BC6: =IF($A6="","",IF($U6="",0,IF(COUNTIFS($U$2:$U6,$U6,$C$2:$C6,$C6)=1,1,0))) -> 1 | BD6: =IF($A6="","",IF(UPPER($P6)="YES","Yes","No")) -> Yes | BE6: =IF($A6="","",IF($N6="No","n/a",IF(AM6<=Constants!$B$17,"Yes","No"))) -> No | BF6: =IF($A6="","",IF($O6="No","n/a",IF(AN6<=Constants!$B$17,"Yes","No"))) -> n/a | BG6: =IF($A6="","",IF($P6="No","n/a",IF(AO6<=Constants!$B$17,"Yes","No"))) -> No | BH6: =IF($A6="","",IF($N6="No","No custody process",IF(BE6="Yes","Thin custody slack","Ample custody slack"))) -> Ample custody slack | BI6: =IF($A6="","",IF($N6="No","",AM6)) -> 506 | BJ6: =IF($A6="","",IF($O6="No","",AN6)) | BK6: =IF($A6="","",IF($P6="No","",AO6)) -> 358
A7: FD-1006 | B7: Sample Fund 1006 | C7: CL03 | D7: Halvern Wealth | E7: No | F7: TM04 | G7: Daniel Tan | H7: 1.147 | I7: 1 | J7: 0 | K7: 0 | L7: 1 | M7: 0 | N7: Yes | O7: Yes | P7: Yes | Q7: 0.1969941 | R7: 0.16218888 | S7: 0.49486561 | T7: 0.55317194 | U7: TOP-FI1 | V7: 0.73934149 | W7: 0.76631603 | X7: FA | Y7: Confirmed | Z7: =IF($A7="","",Constants!$B$6+$I7*Constants!$B$7+$J7*Constants!$B$8+$K7*Constants!$B$9+$L7*Constants!$B$10+$M7*Constants!$B$11) -> 60 | AA7: =IF($A7="","",100-Z7) -> 40 | AB7: =IF($A7="","",ROUND($H7*Constants!$B$4,1)) -> 25.3 | AC7: =IF($A7="","",ROUND(AB7*Z7/100,1)) -> 15.2 | AD7: =IF($A7="","",ROUND(AB7*AA7/100,1)) -> 10.1 | AE7: =IF($A7="","",HOUR($Q7)+MINUTE($Q7)/60) -> 4.7166667 | AF7: =IF($A7="","",HOUR($R7)+MINUTE($R7)/60) -> 3.8833333 | AG7: =IF($A7="","",HOUR($S7)+MINUTE($S7)/60) -> 11.866667 | AH7: =IF($A7="","",HOUR($T7)+MINUTE($T7)/60) -> 13.266667 | AI7: =IF($A7="","",HOUR($V7)+MINUTE($V7)/60) -> 17.733333 | AJ7: =IF($A7="","",HOUR($W7)+MINUTE($W7)/60) -> 18.383333 | AK7: =IF($A7="","",VLOOKUP($F7,Dim_Team!$A:$F,6,0)) -> 9 | AL7: =IF($A7="","",VLOOKUP($X7,Dim_Signoff!$A:$C,3,0)) -> 0 | AM7: =IF($A7="","",IF($N7="No","n/a",ROUND((AH7-AE7)*60,0))) -> 513 | AN7: =IF($A7="","",IF($O7="No","n/a",ROUND((AH7-AF7)*60,0))) -> 563 | AO7: =IF($A7="","",IF($P7="No","n/a",ROUND((AH7-AG7)*60,0))) -> 84 | AP7: =IF($A7="","",ROUND((AH7-AK7)*60,0)) -> 256 | AQ7: =IF($A7="","",ROUND((AI7-AH7)*60,0)) -> 268 | AR7: =IF($A7="","",IF(AP7>=AC7,"Yes","No")) -> Yes | AS7: =IF($A7="","",IF(AQ7>=AD7+AL7,"Yes","No")) -> Yes | AT7: =IF($A7="","",IF(AND(AR7="Yes",AS7="Yes"),"OK","REVIEW")) -> OK | AU7: =IF($A7="","",IF($P7="No","Not applicable",IF(AO7<Constants!$B$14,"CAPTURE","Not needed"))) -> CAPTURE | AV7: =IF($A7="","",IF($P7="No","n/a",RANK(AO7,AO:AO,1))) -> 2 | AW7: =IF($A7="","",IF(UPPER($E7)="YES","Strategic","Non-strategic")) -> Non-strategic | AX7: =IF($A7="","",COUNTIFS(Fact_Work!$C:$C,$A7)) -> 3 | AY7: =IF($A7="","",IF(AX7=0,"Not seen",IF(AX7>=Constants!$B$13*0.6,"Daily",IF(AX7>=Constants!$B$13*0.12,"Weekly","Monthly or ad hoc")))) -> Daily | AZ7: =IF($A7="","",IFERROR(VLOOKUP($U7,Dim_TOP!$A:$H,8,0),"")) -> 12.45 | BA7: =IF($A7="","",IFERROR(ROUND((AH7-AZ7)*60,0),"")) -> 49 | BB7: =IF($A7="","",IF(BA7="","",IF(BA7<=0,"Sets the deadline","Later than peers by "&BA7&" min"))) -> Later than peers by 49 min | BC7: =IF($A7="","",IF($U7="",0,IF(COUNTIFS($U$2:$U7,$U7,$C$2:$C7,$C7)=1,1,0))) -> 1 | BD7: =IF($A7="","",IF(UPPER($P7)="YES","Yes","No")) -> Yes | BE7: =IF($A7="","",IF($N7="No","n/a",IF(AM7<=Constants!$B$17,"Yes","No"))) -> No | BF7: =IF($A7="","",IF($O7="No","n/a",IF(AN7<=Constants!$B$17,"Yes","No"))) -> No | BG7: =IF($A7="","",IF($P7="No","n/a",IF(AO7<=Constants!$B$17,"Yes","No"))) -> No | BH7: =IF($A7="","",IF($N7="No","No custody process",IF(BE7="Yes","Thin custody slack","Ample custody slack"))) -> Ample custody slack | BI7: =IF($A7="","",IF($N7="No","",AM7)) -> 513 | BJ7: =IF($A7="","",IF($O7="No","",AN7)) -> 563 | BK7: =IF($A7="","",IF($P7="No","",AO7)) -> 84
A8: FD-1007 | B8: Sample Fund 1007 | C8: CL01 | D8: Meridian Pensions | E8: Yes | F8: TM01 | G8: Lim Wei Ming | H8: 1.347 | I8: 0 | J8: 1 | K8: 1 | L8: 1 | M8: 0 | N8: Yes | O8: Yes | P8: No | Q8: 0.14851954 | R8: 0.19505622 | S8: 0.54673606 | T8: 0.54673606 | U8: TOP-MA1 | V8: 0.72372753 | W8: 0.76242641 | X8: FA | Y8: Confirmed | Z8: =IF($A8="","",Constants!$B$6+$I8*Constants!$B$7+$J8*Constants!$B$8+$K8*Constants!$B$9+$L8*Constants!$B$10+$M8*Constants!$B$11) -> 70 | AA8: =IF($A8="","",100-Z8) -> 30 | AB8: =IF($A8="","",ROUND($H8*Constants!$B$4,1)) -> 29.7 | AC8: =IF($A8="","",ROUND(AB8*Z8/100,1)) -> 20.8 | AD8: =IF($A8="","",ROUND(AB8*AA8/100,1)) -> 8.9 | AE8: =IF($A8="","",HOUR($Q8)+MINUTE($Q8)/60) -> 3.55 | AF8: =IF($A8="","",HOUR($R8)+MINUTE($R8)/60) -> 4.6666667 | AG8: =IF($A8="","",HOUR($S8)+MINUTE($S8)/60) -> 13.116667 | AH8: =IF($A8="","",HOUR($T8)+MINUTE($T8)/60) -> 13.116667 | AI8: =IF($A8="","",HOUR($V8)+MINUTE($V8)/60) -> 17.366667 | AJ8: =IF($A8="","",HOUR($W8)+MINUTE($W8)/60) -> 18.283333 | AK8: =IF($A8="","",VLOOKUP($F8,Dim_Team!$A:$F,6,0)) -> 9 | AL8: =IF($A8="","",VLOOKUP($X8,Dim_Signoff!$A:$C,3,0)) -> 0 | AM8: =IF($A8="","",IF($N8="No","n/a",ROUND((AH8-AE8)*60,0))) -> 574 | AN8: =IF($A8="","",IF($O8="No","n/a",ROUND((AH8-AF8)*60,0))) -> 507 | AO8: =IF($A8="","",IF($P8="No","n/a",ROUND((AH8-AG8)*60,0))) -> n/a | AP8: =IF($A8="","",ROUND((AH8-AK8)*60,0)) -> 247 | AQ8: =IF($A8="","",ROUND((AI8-AH8)*60,0)) -> 255 | AR8: =IF($A8="","",IF(AP8>=AC8,"Yes","No")) -> Yes | AS8: =IF($A8="","",IF(AQ8>=AD8+AL8,"Yes","No")) -> Yes | AT8: =IF($A8="","",IF(AND(AR8="Yes",AS8="Yes"),"OK","REVIEW")) -> OK | AU8: =IF($A8="","",IF($P8="No","Not applicable",IF(AO8<Constants!$B$14,"CAPTURE","Not needed"))) -> Not applicable | AV8: =IF($A8="","",IF($P8="No","n/a",RANK(AO8,AO:AO,1))) -> n/a | AW8: =IF($A8="","",IF(UPPER($E8)="YES","Strategic","Non-strategic")) -> Strategic | AX8: =IF($A8="","",COUNTIFS(Fact_Work!$C:$C,$A8)) -> 3 | AY8: =IF($A8="","",IF(AX8=0,"Not seen",IF(AX8>=Constants!$B$13*0.6,"Daily",IF(AX8>=Constants!$B$13*0.12,"Weekly","Monthly or ad hoc")))) -> Daily | AZ8: =IF($A8="","",IFERROR(VLOOKUP($U8,Dim_TOP!$A:$H,8,0),"")) -> 11.716667 | BA8: =IF($A8="","",IFERROR(ROUND((AH8-AZ8)*60,0),"")) -> 84 | BB8: =IF($A8="","",IF(BA8="","",IF(BA8<=0,"Sets the deadline","Later than peers by "&BA8&" min"))) -> Later than peers by 84 min | BC8: =IF($A8="","",IF($U8="",0,IF(COUNTIFS($U$2:$U8,$U8,$C$2:$C8,$C8)=1,1,0))) -> 1 | BD8: =IF($A8="","",IF(UPPER($P8)="YES","Yes","No")) -> No | BE8: =IF($A8="","",IF($N8="No","n/a",IF(AM8<=Constants!$B$17,"Yes","No"))) -> No | BF8: =IF($A8="","",IF($O8="No","n/a",IF(AN8<=Constants!$B$17,"Yes","No"))) -> No | BG8: =IF($A8="","",IF($P8="No","n/a",IF(AO8<=Constants!$B$17,"Yes","No"))) -> n/a | BH8: =IF($A8="","",IF($N8="No","No custody process",IF(BE8="Yes","Thin custody slack","Ample custody slack"))) -> Ample custody slack | BI8: =IF($A8="","",IF($N8="No","",AM8)) -> 574 | BJ8: =IF($A8="","",IF($O8="No","",AN8)) -> 507 | BK8: =IF($A8="","",IF($P8="No","",AO8))
A9: FD-1008 | B9: Sample Fund 1008 | C9: CL02 | D9: Northgate Insurance | E9: Yes | F9: TM01 | G9: Siti Noraini | H9: 1.769 | I9: 0 | J9: 0 | K9: 1 | L9: 0 | M9: 1 | N9: Yes | O9: Yes | P9: Yes | Q9: 0.1874934 | R9: 0.16795178 | S9: 0.33133422 | T9: 0.49271241 | U9: TOP-ALT | V9: 0.67259672 | W9: 0.69955729 | X9: FA | Y9: Estimated | Z9: =IF($A9="","",Constants!$B$6+$I9*Constants!$B$7+$J9*Constants!$B$8+$K9*Constants!$B$9+$L9*Constants!$B$10+$M9*Constants!$B$11) -> 75 | AA9: =IF($A9="","",100-Z9) -> 25 | AB9: =IF($A9="","",ROUND($H9*Constants!$B$4,1)) -> 39.1 | AC9: =IF($A9="","",ROUND(AB9*Z9/100,1)) -> 29.3 | AD9: =IF($A9="","",ROUND(AB9*AA9/100,1)) -> 9.8 | AE9: =IF($A9="","",HOUR($Q9)+MINUTE($Q9)/60) -> 4.4833333 | AF9: =IF($A9="","",HOUR($R9)+MINUTE($R9)/60) -> 4.0166667 | AG9: =IF($A9="","",HOUR($S9)+MINUTE($S9)/60) -> 7.95 | AH9: =IF($A9="","",HOUR($T9)+MINUTE($T9)/60) -> 11.816667 | AI9: =IF($A9="","",HOUR($V9)+MINUTE($V9)/60) -> 16.133333 | AJ9: =IF($A9="","",HOUR($W9)+MINUTE($W9)/60) -> 16.783333 | AK9: =IF($A9="","",VLOOKUP($F9,Dim_Team!$A:$F,6,0)) -> 9 | AL9: =IF($A9="","",VLOOKUP($X9,Dim_Signoff!$A:$C,3,0)) -> 0 | AM9: =IF($A9="","",IF($N9="No","n/a",ROUND((AH9-AE9)*60,0))) -> 440 | AN9: =IF($A9="","",IF($O9="No","n/a",ROUND((AH9-AF9)*60,0))) -> 468 | AO9: =IF($A9="","",IF($P9="No","n/a",ROUND((AH9-AG9)*60,0))) -> 232 | AP9: =IF($A9="","",ROUND((AH9-AK9)*60,0)) -> 169 | AQ9: =IF($A9="","",ROUND((AI9-AH9)*60,0)) -> 259 | AR9: =IF($A9="","",IF(AP9>=AC9,"Yes","No")) -> Yes | AS9: =IF($A9="","",IF(AQ9>=AD9+AL9,"Yes","No")) -> Yes | AT9: =IF($A9="","",IF(AND(AR9="Yes",AS9="Yes"),"OK","REVIEW")) -> OK | AU9: =IF($A9="","",IF($P9="No","Not applicable",IF(AO9<Constants!$B$14,"CAPTURE","Not needed"))) -> Not needed | AV9: =IF($A9="","",IF($P9="No","n/a",RANK(AO9,AO:AO,1))) -> 4 | AW9: =IF($A9="","",IF(UPPER($E9)="YES","Strategic","Non-strategic")) -> Strategic | AX9: =IF($A9="","",COUNTIFS(Fact_Work!$C:$C,$A9)) -> 1 | AY9: =IF($A9="","",IF(AX9=0,"Not seen",IF(AX9>=Constants!$B$13*0.6,"Daily",IF(AX9>=Constants!$B$13*0.12,"Weekly","Monthly or ad hoc")))) -> Weekly | AZ9: =IF($A9="","",IFERROR(VLOOKUP($U9,Dim_TOP!$A:$H,8,0),"")) -> 11.633333 | BA9: =IF($A9="","",IFERROR(ROUND((AH9-AZ9)*60,0),"")) -> 11 | BB9: =IF($A9="","",IF(BA9="","",IF(BA9<=0,"Sets the deadline","Later than peers by "&BA9&" min"))) -> Later than peers by 11 min | BC9: =IF($A9="","",IF($U9="",0,IF(COUNTIFS($U$2:$U9,$U9,$C$2:$C9,$C9)=1,1,0))) -> 1 | BD9: =IF($A9="","",IF(UPPER($P9)="YES","Yes","No")) -> Yes | BE9: =IF($A9="","",IF($N9="No","n/a",IF(AM9<=Constants!$B$17,"Yes","No"))) -> No | BF9: =IF($A9="","",IF($O9="No","n/a",IF(AN9<=Constants!$B$17,"Yes","No"))) -> No | BG9: =IF($A9="","",IF($P9="No","n/a",IF(AO9<=Constants!$B$17,"Yes","No"))) -> No | BH9: =IF($A9="","",IF($N9="No","No custody process",IF(BE9="Yes","Thin custody slack","Ample custody slack"))) -> Ample custody slack | BI9: =IF($A9="","",IF($N9="No","",AM9)) -> 440 | BJ9: =IF($A9="","",IF($O9="No","",AN9)) -> 468 | BK9: =IF($A9="","",IF($P9="No","",AO9)) -> 232
A10: FD-1009 | B10: Sample Fund 1009 | C10: CL03 | D10: Halvern Wealth | E10: No | F10: TM02 | G10: Raj Kumar | H10: 1.487 | I10: 0 | J10: 1 | K10: 0 | L10: 0 | M10: 0 | N10: Yes | O10: No | P10: Yes | Q10: 0.17932946 | R10: 0.48564405 | S10: 0.30941221 | T10: 0.48564405 | U10: TOP-EQ1 | V10: 0.63247362 | W10: 0.66810583 | X10: Oversight | Y10: Confirmed | Z10: =IF($A10="","",Constants!$B$6+$I10*Constants!$B$7+$J10*Constants!$B$8+$K10*Constants!$B$9+$L10*Constants!$B$10+$M10*Constants!$B$11) -> 65 | AA10: =IF($A10="","",100-Z10) -> 35 | AB10: =IF($A10="","",ROUND($H10*Constants!$B$4,1)) -> 32.8 | AC10: =IF($A10="","",ROUND(AB10*Z10/100,1)) -> 21.3 | AD10: =IF($A10="","",ROUND(AB10*AA10/100,1)) -> 11.5 | AE10: =IF($A10="","",HOUR($Q10)+MINUTE($Q10)/60) -> 4.3 | AF10: =IF($A10="","",HOUR($R10)+MINUTE($R10)/60) -> 11.65 | AG10: =IF($A10="","",HOUR($S10)+MINUTE($S10)/60) -> 7.4166667 | AH10: =IF($A10="","",HOUR($T10)+MINUTE($T10)/60) -> 11.65 | AI10: =IF($A10="","",HOUR($V10)+MINUTE($V10)/60) -> 15.166667 | AJ10: =IF($A10="","",HOUR($W10)+MINUTE($W10)/60) -> 16.033333 | AK10: =IF($A10="","",VLOOKUP($F10,Dim_Team!$A:$F,6,0)) -> 9 | AL10: =IF($A10="","",VLOOKUP($X10,Dim_Signoff!$A:$C,3,0)) -> 25 | AM10: =IF($A10="","",IF($N10="No","n/a",ROUND((AH10-AE10)*60,0))) -> 441 | AN10: =IF($A10="","",IF($O10="No","n/a",ROUND((AH10-AF10)*60,0))) -> n/a | AO10: =IF($A10="","",IF($P10="No","n/a",ROUND((AH10-AG10)*60,0))) -> 254 | AP10: =IF($A10="","",ROUND((AH10-AK10)*60,0)) -> 159 | AQ10: =IF($A10="","",ROUND((AI10-AH10)*60,0)) -> 211 | AR10: =IF($A10="","",IF(AP10>=AC10,"Yes","No")) -> Yes | AS10: =IF($A10="","",IF(AQ10>=AD10+AL10,"Yes","No")) -> Yes | AT10: =IF($A10="","",IF(AND(AR10="Yes",AS10="Yes"),"OK","REVIEW")) -> OK | AU10: =IF($A10="","",IF($P10="No","Not applicable",IF(AO10<Constants!$B$14,"CAPTURE","Not needed"))) -> Not needed | AV10: =IF($A10="","",IF($P10="No","n/a",RANK(AO10,AO:AO,1))) -> 7 | AW10: =IF($A10="","",IF(UPPER($E10)="YES","Strategic","Non-strategic")) -> Non-strategic | AX10: =IF($A10="","",COUNTIFS(Fact_Work!$C:$C,$A10)) -> 1 | AY10: =IF($A10="","",IF(AX10=0,"Not seen",IF(AX10>=Constants!$B$13*0.6,"Daily",IF(AX10>=Constants!$B$13*0.12,"Weekly","Monthly or ad hoc")))) -> Weekly | AZ10: =IF($A10="","",IFERROR(VLOOKUP($U10,Dim_TOP!$A:$H,8,0),"")) -> 11.65 | BA10: =IF($A10="","",IFERROR(ROUND((AH10-AZ10)*60,0),"")) -> 0 | BB10: =IF($A10="","",IF(BA10="","",IF(BA10<=0,"Sets the deadline","Later than peers by "&BA10&" min"))) -> Sets the deadline | BC10: =IF($A10="","",IF($U10="",0,IF(COUNTIFS($U$2:$U10,$U10,$C$2:$C10,$C10)=1,1,0))) -> 1 | BD10: =IF($A10="","",IF(UPPER($P10)="YES","Yes","No")) -> Yes | BE10: =IF($A10="","",IF($N10="No","n/a",IF(AM10<=Constants!$B$17,"Yes","No"))) -> No | BF10: =IF($A10="","",IF($O10="No","n/a",IF(AN10<=Constants!$B$17,"Yes","No"))) -> n/a | BG10: =IF($A10="","",IF($P10="No","n/a",IF(AO10<=Constants!$B$17,"Yes","No"))) -> No | BH10: =IF($A10="","",IF($N10="No","No custody process",IF(BE10="Yes","Thin custody slack","Ample custody slack"))) -> Ample custody slack | BI10: =IF($A10="","",IF($N10="No","",AM10)) -> 441 | BJ10: =IF($A10="","",IF($O10="No","",AN10)) | BK10: =IF($A10="","",IF($P10="No","",AO10)) -> 254
A11: FD-1010 | B11: Sample Fund 1010 | C11: CL01 | D11: Meridian Pensions | E11: Yes | F11: TM03 | G11: Chen Xiao | H11: 1.091 | I11: 0 | J11: 0 | K11: 0 | L11: 0 | M11: 0 | N11: Yes | O11: Yes | P11: Yes | Q11: 0.165311 | R11: 0.153869 | S11: 0.35369601 | T11: 0.57737416 | U11: TOP-FI1 | V11: 0.73003046 | W11: 0.76278839 | X11: Client | Y11: Confirmed | Z11: =IF($A11="","",Constants!$B$6+$I11*Constants!$B$7+$J11*Constants!$B$8+$K11*Constants!$B$9+$L11*Constants!$B$10+$M11*Constants!$B$11) -> 60 | AA11: =IF($A11="","",100-Z11) -> 40 | AB11: =IF($A11="","",ROUND($H11*Constants!$B$4,1)) -> 24.1 | AC11: =IF($A11="","",ROUND(AB11*Z11/100,1)) -> 14.5 | AD11: =IF($A11="","",ROUND(AB11*AA11/100,1)) -> 9.6 | AE11: =IF($A11="","",HOUR($Q11)+MINUTE($Q11)/60) -> 3.9666667 | AF11: =IF($A11="","",HOUR($R11)+MINUTE($R11)/60) -> 3.6833333 | AG11: =IF($A11="","",HOUR($S11)+MINUTE($S11)/60) -> 8.4833333 | AH11: =IF($A11="","",HOUR($T11)+MINUTE($T11)/60) -> 13.85 | AI11: =IF($A11="","",HOUR($V11)+MINUTE($V11)/60) -> 17.516667 | AJ11: =IF($A11="","",HOUR($W11)+MINUTE($W11)/60) -> 18.3 | AK11: =IF($A11="","",VLOOKUP($F11,Dim_Team!$A:$F,6,0)) -> 10 | AL11: =IF($A11="","",VLOOKUP($X11,Dim_Signoff!$A:$C,3,0)) -> 46 | AM11: =IF($A11="","",IF($N11="No","n/a",ROUND((AH11-AE11)*60,0))) -> 593 | AN11: =IF($A11="","",IF($O11="No","n/a",ROUND((AH11-AF11)*60,0))) -> 610 | AO11: =IF($A11="","",IF($P11="No","n/a",ROUND((AH11-AG11)*60,0))) -> 322 | AP11: =IF($A11="","",ROUND((AH11-AK11)*60,0)) -> 231 | AQ11: =IF($A11="","",ROUND((AI11-AH11)*60,0)) -> 220 | AR11: =IF($A11="","",IF(AP11>=AC11,"Yes","No")) -> Yes | AS11: =IF($A11="","",IF(AQ11>=AD11+AL11,"Yes","No")) -> Yes | AT11: =IF($A11="","",IF(AND(AR11="Yes",AS11="Yes"),"OK","REVIEW")) -> OK | AU11: =IF($A11="","",IF($P11="No","Not applicable",IF(AO11<Constants!$B$14,"CAPTURE","Not needed"))) -> Not needed | AV11: =IF($A11="","",IF($P11="No","n/a",RANK(AO11,AO:AO,1))) -> 9 | AW11: =IF($A11="","",IF(UPPER($E11)="YES","Strategic","Non-strategic")) -> Strategic | AX11: =IF($A11="","",COUNTIFS(Fact_Work!$C:$C,$A11)) -> 1 | AY11: =IF($A11="","",IF(AX11=0,"Not seen",IF(AX11>=Constants!$B$13*0.6,"Daily",IF(AX11>=Constants!$B$13*0.12,"Weekly","Monthly or ad hoc")))) -> Weekly | AZ11: =IF($A11="","",IFERROR(VLOOKUP($U11,Dim_TOP!$A:$H,8,0),"")) -> 12.45 | BA11: =IF($A11="","",IFERROR(ROUND((AH11-AZ11)*60,0),"")) -> 84 | BB11: =IF($A11="","",IF(BA11="","",IF(BA11<=0,"Sets the deadline","Later than peers by "&BA11&" min"))) -> Later than peers by 84 min | BC11: =IF($A11="","",IF($U11="",0,IF(COUNTIFS($U$2:$U11,$U11,$C$2:$C11,$C11)=1,1,0))) -> 1 | BD11: =IF($A11="","",IF(UPPER($P11)="YES","Yes","No")) -> Yes | BE11: =IF($A11="","",IF($N11="No","n/a",IF(AM11<=Constants!$B$17,"Yes","No"))) -> No | BF11: =IF($A11="","",IF($O11="No","n/a",IF(AN11<=Constants!$B$17,"Yes","No"))) -> No | BG11: =IF($A11="","",IF($P11="No","n/a",IF(AO11<=Constants!$B$17,"Yes","No"))) -> No | BH11: =IF($A11="","",IF($N11="No","No custody process",IF(BE11="Yes","Thin custody slack","Ample custody slack"))) -> Ample custody slack | BI11: =IF($A11="","",IF($N11="No","",AM11)) -> 593 | BJ11: =IF($A11="","",IF($O11="No","",AN11)) -> 610 | BK11: =IF($A11="","",IF($P11="No","",AO11)) -> 322
A12: FD-1011 | B12: Sample Fund 1011 | C12: CL02 | D12: Northgate Insurance | E12: Yes | F12: TM03 | G12: Aisha Rahman | H12: 1.958 | I12: 1 | J12: 0 | K12: 1 | L12: 0 | M12: 1 | N12: Yes | O12: Yes | P12: Yes | Q12: 0.15596948 | R12: 0.2063501 | S12: 0.48735716 | T12: 0.50974706 | U12: TOP-MA1 | V12: 0.69843804 | W12: 0.73560451 | X12: FA | Y12: Confirmed | Z12: =IF($A12="","",Constants!$B$6+$I12*Constants!$B$7+$J12*Constants!$B$8+$K12*Constants!$B$9+$L12*Constants!$B$10+$M12*Constants!$B$11) -> 80 | AA12: =IF($A12="","",100-Z12) -> 20 | AB12: =IF($A12="","",ROUND($H12*Constants!$B$4,1)) -> 43.2 | AC12: =IF($A12="","",ROUND(AB12*Z12/100,1)) -> 34.6 | AD12: =IF($A12="","",ROUND(AB12*AA12/100,1)) -> 8.6 | AE12: =IF($A12="","",HOUR($Q12)+MINUTE($Q12)/60) -> 3.7333333 | AF12: =IF($A12="","",HOUR($R12)+MINUTE($R12)/60) -> 4.95 | AG12: =IF($A12="","",HOUR($S12)+MINUTE($S12)/60) -> 11.683333 | AH12: =IF($A12="","",HOUR($T12)+MINUTE($T12)/60) -> 12.233333 | AI12: =IF($A12="","",HOUR($V12)+MINUTE($V12)/60) -> 16.75 | AJ12: =IF($A12="","",HOUR($W12)+MINUTE($W12)/60) -> 17.65 | AK12: =IF($A12="","",VLOOKUP($F12,Dim_Team!$A:$F,6,0)) -> 10 | AL12: =IF($A12="","",VLOOKUP($X12,Dim_Signoff!$A:$C,3,0)) -> 0 | AM12: =IF($A12="","",IF($N12="No","n/a",ROUND((AH12-AE12)*60,0))) -> 510 | AN12: =IF($A12="","",IF($O12="No","n/a",ROUND((AH12-AF12)*60,0))) -> 437 | AO12: =IF($A12="","",IF($P12="No","n/a",ROUND((AH12-AG12)*60,0))) -> 33 | AP12: =IF($A12="","",ROUND((AH12-AK12)*60,0)) -> 134 | AQ12: =IF($A12="","",ROUND((AI12-AH12)*60,0)) -> 271 | AR12: =IF($A12="","",IF(AP12>=AC12,"Yes","No")) -> Yes | AS12: =IF($A12="","",IF(AQ12>=AD12+AL12,"Yes","No")) -> Yes | AT12: =IF($A12="","",IF(AND(AR12="Yes",AS12="Yes"),"OK","REVIEW")) -> OK | AU12: =IF($A12="","",IF($P12="No","Not applicable",IF(AO12<Constants!$B$14,"CAPTURE","Not needed"))) -> CAPTURE | AV12: =IF($A12="","",IF($P12="No","n/a",RANK(AO12,AO:AO,1))) -> 1 | AW12: =IF($A12="","",IF(UPPER($E12)="YES","Strategic","Non-strategic")) -> Strategic | AX12: =IF($A12="","",COUNTIFS(Fact_Work!$C:$C,$A12)) -> 1 | AY12: =IF($A12="","",IF(AX12=0,"Not seen",IF(AX12>=Constants!$B$13*0.6,"Daily",IF(AX12>=Constants!$B$13*0.12,"Weekly","Monthly or ad hoc")))) -> Weekly | AZ12: =IF($A12="","",IFERROR(VLOOKUP($U12,Dim_TOP!$A:$H,8,0),"")) -> 11.716667 | BA12: =IF($A12="","",IFERROR(ROUND((AH12-AZ12)*60,0),"")) -> 31 | BB12: =IF($A12="","",IF(BA12="","",IF(BA12<=0,"Sets the deadline","Later than peers by "&BA12&" min"))) -> Later than peers by 31 min | BC12: =IF($A12="","",IF($U12="",0,IF(COUNTIFS($U$2:$U12,$U12,$C$2:$C12,$C12)=1,1,0))) -> 1 | BD12: =IF($A12="","",IF(UPPER($P12)="YES","Yes","No")) -> Yes | BE12: =IF($A12="","",IF($N12="No","n/a",IF(AM12<=Constants!$B$17,"Yes","No"))) -> No | BF12: =IF($A12="","",IF($O12="No","n/a",IF(AN12<=Constants!$B$17,"Yes","No"))) -> No | BG12: =IF($A12="","",IF($P12="No","n/a",IF(AO12<=Constants!$B$17,"Yes","No"))) -> No | BH12: =IF($A12="","",IF($N12="No","No custody process",IF(BE12="Yes","Thin custody slack","Ample custody slack"))) -> Ample custody slack | BI12: =IF($A12="","",IF($N12="No","",AM12)) -> 510 | BJ12: =IF($A12="","",IF($O12="No","",AN12)) -> 437 | BK12: =IF($A12="","",IF($P12="No","",AO12)) -> 33
A13: FD-1012 | B13: Sample Fund 1012 | C13: CL03 | D13: Halvern Wealth | E13: No | F13: TM04 | G13: Daniel Tan | H13: 2.148 | I13: 0 | J13: 0 | K13: 0 | L13: 0 | M13: 0 | N13: Yes | O13: Yes | P13: Yes | Q13: 0.15463777 | R13: 0.22714675 | S13: 0.3283202 | T13: 0.48497524 | U13: TOP-ALT | V13: 0.62696405 | W13: 0.66154727 | X13: FA | Y13: Confirmed | Z13: =IF($A13="","",Constants!$B$6+$I13*Constants!$B$7+$J13*Constants!$B$8+$K13*Constants!$B$9+$L13*Constants!$B$10+$M13*Constants!$B$11) -> 60 | AA13: =IF($A13="","",100-Z13) -> 40 | AB13: =IF($A13="","",ROUND($H13*Constants!$B$4,1)) -> 47.4 | AC13: =IF($A13="","",ROUND(AB13*Z13/100,1)) -> 28.4 | AD13: =IF($A13="","",ROUND(AB13*AA13/100,1)) -> 19 | AE13: =IF($A13="","",HOUR($Q13)+MINUTE($Q13)/60) -> 3.7 | AF13: =IF($A13="","",HOUR($R13)+MINUTE($R13)/60) -> 5.45 | AG13: =IF($A13="","",HOUR($S13)+MINUTE($S13)/60) -> 7.8666667 | AH13: =IF($A13="","",HOUR($T13)+MINUTE($T13)/60) -> 11.633333 | AI13: =IF($A13="","",HOUR($V13)+MINUTE($V13)/60) -> 15.033333 | AJ13: =IF($A13="","",HOUR($W13)+MINUTE($W13)/60) -> 15.866667 | AK13: =IF($A13="","",VLOOKUP($F13,Dim_Team!$A:$F,6,0)) -> 9 | AL13: =IF($A13="","",VLOOKUP($X13,Dim_Signoff!$A:$C,3,0)) -> 0 | AM13: =IF($A13="","",IF($N13="No","n/a",ROUND((AH13-AE13)*60,0))) -> 476 | AN13: =IF($A13="","",IF($O13="No","n/a",ROUND((AH13-AF13)*60,0))) -> 371 | AO13: =IF($A13="","",IF($P13="No","n/a",ROUND((AH13-AG13)*60,0))) -> 226 | AP13: =IF($A13="","",ROUND((AH13-AK13)*60,0)) -> 158 | AQ13: =IF($A13="","",ROUND((AI13-AH13)*60,0)) -> 204 | AR13: =IF($A13="","",IF(AP13>=AC13,"Yes","No")) -> Yes | AS13: =IF($A13="","",IF(AQ13>=AD13+AL13,"Yes","No")) -> Yes | AT13: =IF($A13="","",IF(AND(AR13="Yes",AS13="Yes"),"OK","REVIEW")) -> OK | AU13: =IF($A13="","",IF($P13="No","Not applicable",IF(AO13<Constants!$B$14,"CAPTURE","Not needed"))) -> Not needed | AV13: =IF($A13="","",IF($P13="No","n/a",RANK(AO13,AO:AO,1))) -> 3 | AW13: =IF($A13="","",IF(UPPER($E13)="YES","Strategic","Non-strategic")) -> Non-strategic | AX13: =IF($A13="","",COUNTIFS(Fact_Work!$C:$C,$A13)) -> 1 | AY13: =IF($A13="","",IF(AX13=0,"Not seen",IF(AX13>=Constants!$B$13*0.6,"Daily",IF(AX13>=Constants!$B$13*0.12,"Weekly","Monthly or ad hoc")))) -> Weekly | AZ13: =IF($A13="","",IFERROR(VLOOKUP($U13,Dim_TOP!$A:$H,8,0),"")) -> 11.633333 | BA13: =IF($A13="","",IFERROR(ROUND((AH13-AZ13)*60,0),"")) -> 0 | BB13: =IF($A13="","",IF(BA13="","",IF(BA13<=0,"Sets the deadline","Later than peers by "&BA13&" min"))) -> Sets the deadline | BC13: =IF($A13="","",IF($U13="",0,IF(COUNTIFS($U$2:$U13,$U13,$C$2:$C13,$C13)=1,1,0))) -> 1 | BD13: =IF($A13="","",IF(UPPER($P13)="YES","Yes","No")) -> Yes | BE13: =IF($A13="","",IF($N13="No","n/a",IF(AM13<=Constants!$B$17,"Yes","No"))) -> No | BF13: =IF($A13="","",IF($O13="No","n/a",IF(AN13<=Constants!$B$17,"Yes","No"))) -> No | BG13: =IF($A13="","",IF($P13="No","n/a",IF(AO13<=Constants!$B$17,"Yes","No"))) -> No | BH13: =IF($A13="","",IF($N13="No","No custody process",IF(BE13="Yes","Thin custody slack","Ample custody slack"))) -> Ample custody slack | BI13: =IF($A13="","",IF($N13="No","",AM13)) -> 476 | BJ13: =IF($A13="","",IF($O13="No","",AN13)) -> 371 | BK13: =IF($A13="","",IF($P13="No","",AO13)) -> 226
Z14: =IF($A14="","",Constants!$B$6+$I14*Constants!$B$7+$J14*Constants!$B$8+$K14*Constants!$B$9+$L14*Constants!$B$10+$M14*Constants!$B$11) | AA14: =IF($A14="","",100-Z14) | AB14: =IF($A14="","",ROUND($H14*Constants!$B$4,1)) | AC14: =IF($A14="","",ROUND(AB14*Z14/100,1)) | AD14: =IF($A14="","",ROUND(AB14*AA14/100,1)) | AE14: =IF($A14="","",HOUR($Q14)+MINUTE($Q14)/60) | AF14: =IF($A14="","",HOUR($R14)+MINUTE($R14)/60) | AG14: =IF($A14="","",HOUR($S14)+MINUTE($S14)/60) | AH14: =IF($A14="","",HOUR($T14)+MINUTE($T14)/60) | AI14: =IF($A14="","",HOUR($V14)+MINUTE($V14)/60) | AJ14: =IF($A14="","",HOUR($W14)+MINUTE($W14)/60) | AK14: =IF($A14="","",VLOOKUP($F14,Dim_Team!$A:$F,6,0)) | AL14: =IF($A14="","",VLOOKUP($X14,Dim_Signoff!$A:$C,3,0)) | AM14: =IF($A14="","",IF($N14="No","n/a",ROUND((AH14-AE14)*60,0))) | AN14: =IF($A14="","",IF($O14="No","n/a",ROUND((AH14-AF14)*60,0))) | AO14: =IF($A14="","",IF($P14="No","n/a",ROUND((AH14-AG14)*60,0))) | AP14: =IF($A14="","",ROUND((AH14-AK14)*60,0)) | AQ14: =IF($A14="","",ROUND((AI14-AH14)*60,0)) | AR14: =IF($A14="","",IF(AP14>=AC14,"Yes","No")) | AS14: =IF($A14="","",IF(AQ14>=AD14+AL14,"Yes","No")) | AT14: =IF($A14="","",IF(AND(AR14="Yes",AS14="Yes"),"OK","REVIEW")) | AU14: =IF($A14="","",IF($P14="No","Not applicable",IF(AO14<Constants!$B$14,"CAPTURE","Not needed"))) | AV14: =IF($A14="","",IF($P14="No","n/a",RANK(AO14,AO:AO,1))) | AW14: =IF($A14="","",IF(UPPER($E14)="YES","Strategic","Non-strategic")) | AX14: =IF($A14="","",COUNTIFS(Fact_Work!$C:$C,$A14)) | AY14: =IF($A14="","",IF(AX14=0,"Not seen",IF(AX14>=Constants!$B$13*0.6,"Daily",IF(AX14>=Constants!$B$13*0.12,"Weekly","Monthly or ad hoc")))) | AZ14: =IF($A14="","",IFERROR(VLOOKUP($U14,Dim_TOP!$A:$H,8,0),"")) | BA14: =IF($A14="","",IFERROR(ROUND((AH14-AZ14)*60,0),"")) | BB14: =IF($A14="","",IF(BA14="","",IF(BA14<=0,"Sets the deadline","Later than peers by "&BA14&" min"))) | BC14: =IF($A14="","",IF($U14="",0,IF(COUNTIFS($U$2:$U14,$U14,$C$2:$C14,$C14)=1,1,0))) | BD14: =IF($A14="","",IF(UPPER($P14)="YES","Yes","No")) | BE14: =IF($A14="","",IF($N14="No","n/a",IF(AM14<=Constants!$B$17,"Yes","No"))) | BF14: =IF($A14="","",IF($O14="No","n/a",IF(AN14<=Constants!$B$17,"Yes","No"))) | BG14: =IF($A14="","",IF($P14="No","n/a",IF(AO14<=Constants!$B$17,"Yes","No"))) | BH14: =IF($A14="","",IF($N14="No","No custody process",IF(BE14="Yes","Thin custody slack","Ample custody slack"))) | BI14: =IF($A14="","",IF($N14="No","",AM14)) | BJ14: =IF($A14="","",IF($O14="No","",AN14)) | BK14: =IF($A14="","",IF($P14="No","",AO14))
Z15: =IF($A15="","",Constants!$B$6+$I15*Constants!$B$7+$J15*Constants!$B$8+$K15*Constants!$B$9+$L15*Constants!$B$10+$M15*Constants!$B$11) | AA15: =IF($A15="","",100-Z15) | AB15: =IF($A15="","",ROUND($H15*Constants!$B$4,1)) | AC15: =IF($A15="","",ROUND(AB15*Z15/100,1)) | AD15: =IF($A15="","",ROUND(AB15*AA15/100,1)) | AE15: =IF($A15="","",HOUR($Q15)+MINUTE($Q15)/60) | AF15: =IF($A15="","",HOUR($R15)+MINUTE($R15)/60) | AG15: =IF($A15="","",HOUR($S15)+MINUTE($S15)/60) | AH15: =IF($A15="","",HOUR($T15)+MINUTE($T15)/60) | AI15: =IF($A15="","",HOUR($V15)+MINUTE($V15)/60) | AJ15: =IF($A15="","",HOUR($W15)+MINUTE($W15)/60) | AK15: =IF($A15="","",VLOOKUP($F15,Dim_Team!$A:$F,6,0)) | AL15: =IF($A15="","",VLOOKUP($X15,Dim_Signoff!$A:$C,3,0)) | AM15: =IF($A15="","",IF($N15="No","n/a",ROUND((AH15-AE15)*60,0))) | AN15: =IF($A15="","",IF($O15="No","n/a",ROUND((AH15-AF15)*60,0))) | AO15: =IF($A15="","",IF($P15="No","n/a",ROUND((AH15-AG15)*60,0))) | AP15: =IF($A15="","",ROUND((AH15-AK15)*60,0)) | AQ15: =IF($A15="","",ROUND((AI15-AH15)*60,0)) | AR15: =IF($A15="","",IF(AP15>=AC15,"Yes","No")) | AS15: =IF($A15="","",IF(AQ15>=AD15+AL15,"Yes","No")) | AT15: =IF($A15="","",IF(AND(AR15="Yes",AS15="Yes"),"OK","REVIEW")) | AU15: =IF($A15="","",IF($P15="No","Not applicable",IF(AO15<Constants!$B$14,"CAPTURE","Not needed"))) | AV15: =IF($A15="","",IF($P15="No","n/a",RANK(AO15,AO:AO,1))) | AW15: =IF($A15="","",IF(UPPER($E15)="YES","Strategic","Non-strategic")) | AX15: =IF($A15="","",COUNTIFS(Fact_Work!$C:$C,$A15)) | AY15: =IF($A15="","",IF(AX15=0,"Not seen",IF(AX15>=Constants!$B$13*0.6,"Daily",IF(AX15>=Constants!$B$13*0.12,"Weekly","Monthly or ad hoc")))) | AZ15: =IF($A15="","",IFERROR(VLOOKUP($U15,Dim_TOP!$A:$H,8,0),"")) | BA15: =IF($A15="","",IFERROR(ROUND((AH15-AZ15)*60,0),"")) | BB15: =IF($A15="","",IF(BA15="","",IF(BA15<=0,"Sets the deadline","Later than peers by "&BA15&" min"))) | BC15: =IF($A15="","",IF($U15="",0,IF(COUNTIFS($U$2:$U15,$U15,$C$2:$C15,$C15)=1,1,0))) | BD15: =IF($A15="","",IF(UPPER($P15)="YES","Yes","No")) | BE15: =IF($A15="","",IF($N15="No","n/a",IF(AM15<=Constants!$B$17,"Yes","No"))) | BF15: =IF($A15="","",IF($O15="No","n/a",IF(AN15<=Constants!$B$17,"Yes","No"))) | BG15: =IF($A15="","",IF($P15="No","n/a",IF(AO15<=Constants!$B$17,"Yes","No"))) | BH15: =IF($A15="","",IF($N15="No","No custody process",IF(BE15="Yes","Thin custody slack","Ample custody slack"))) | BI15: =IF($A15="","",IF($N15="No","",AM15)) | BJ15: =IF($A15="","",IF($O15="No","",AN15)) | BK15: =IF($A15="","",IF($P15="No","",AO15))
Z16: =IF($A16="","",Constants!$B$6+$I16*Constants!$B$7+$J16*Constants!$B$8+$K16*Constants!$B$9+$L16*Constants!$B$10+$M16*Constants!$B$11) | AA16: =IF($A16="","",100-Z16) | AB16: =IF($A16="","",ROUND($H16*Constants!$B$4,1)) | AC16: =IF($A16="","",ROUND(AB16*Z16/100,1)) | AD16: =IF($A16="","",ROUND(AB16*AA16/100,1)) | AE16: =IF($A16="","",HOUR($Q16)+MINUTE($Q16)/60) | AF16: =IF($A16="","",HOUR($R16)+MINUTE($R16)/60) | AG16: =IF($A16="","",HOUR($S16)+MINUTE($S16)/60) | AH16: =IF($A16="","",HOUR($T16)+MINUTE($T16)/60) | AI16: =IF($A16="","",HOUR($V16)+MINUTE($V16)/60) | AJ16: =IF($A16="","",HOUR($W16)+MINUTE($W16)/60) | AK16: =IF($A16="","",VLOOKUP($F16,Dim_Team!$A:$F,6,0)) | AL16: =IF($A16="","",VLOOKUP($X16,Dim_Signoff!$A:$C,3,0)) | AM16: =IF($A16="","",IF($N16="No","n/a",ROUND((AH16-AE16)*60,0))) | AN16: =IF($A16="","",IF($O16="No","n/a",ROUND((AH16-AF16)*60,0))) | AO16: =IF($A16="","",IF($P16="No","n/a",ROUND((AH16-AG16)*60,0))) | AP16: =IF($A16="","",ROUND((AH16-AK16)*60,0)) | AQ16: =IF($A16="","",ROUND((AI16-AH16)*60,0)) | AR16: =IF($A16="","",IF(AP16>=AC16,"Yes","No")) | AS16: =IF($A16="","",IF(AQ16>=AD16+AL16,"Yes","No")) | AT16: =IF($A16="","",IF(AND(AR16="Yes",AS16="Yes"),"OK","REVIEW")) | AU16: =IF($A16="","",IF($P16="No","Not applicable",IF(AO16<Constants!$B$14,"CAPTURE","Not needed"))) | AV16: =IF($A16="","",IF($P16="No","n/a",RANK(AO16,AO:AO,1))) | AW16: =IF($A16="","",IF(UPPER($E16)="YES","Strategic","Non-strategic")) | AX16: =IF($A16="","",COUNTIFS(Fact_Work!$C:$C,$A16)) | AY16: =IF($A16="","",IF(AX16=0,"Not seen",IF(AX16>=Constants!$B$13*0.6,"Daily",IF(AX16>=Constants!$B$13*0.12,"Weekly","Monthly or ad hoc")))) | AZ16: =IF($A16="","",IFERROR(VLOOKUP($U16,Dim_TOP!$A:$H,8,0),"")) | BA16: =IF($A16="","",IFERROR(ROUND((AH16-AZ16)*60,0),"")) | BB16: =IF($A16="","",IF(BA16="","",IF(BA16<=0,"Sets the deadline","Later than peers by "&BA16&" min"))) | BC16: =IF($A16="","",IF($U16="",0,IF(COUNTIFS($U$2:$U16,$U16,$C$2:$C16,$C16)=1,1,0))) | BD16: =IF($A16="","",IF(UPPER($P16)="YES","Yes","No")) | BE16: =IF($A16="","",IF($N16="No","n/a",IF(AM16<=Constants!$B$17,"Yes","No"))) | BF16: =IF($A16="","",IF($O16="No","n/a",IF(AN16<=Constants!$B$17,"Yes","No"))) | BG16: =IF($A16="","",IF($P16="No","n/a",IF(AO16<=Constants!$B$17,"Yes","No"))) | BH16: =IF($A16="","",IF($N16="No","No custody process",IF(BE16="Yes","Thin custody slack","Ample custody slack"))) | BI16: =IF($A16="","",IF($N16="No","",AM16)) | BJ16: =IF($A16="","",IF($O16="No","",AN16)) | BK16: =IF($A16="","",IF($P16="No","",AO16))
Z17: =IF($A17="","",Constants!$B$6+$I17*Constants!$B$7+$J17*Constants!$B$8+$K17*Constants!$B$9+$L17*Constants!$B$10+$M17*Constants!$B$11) | AA17: =IF($A17="","",100-Z17) | AB17: =IF($A17="","",ROUND($H17*Constants!$B$4,1)) | AC17: =IF($A17="","",ROUND(AB17*Z17/100,1)) | AD17: =IF($A17="","",ROUND(AB17*AA17/100,1)) | AE17: =IF($A17="","",HOUR($Q17)+MINUTE($Q17)/60) | AF17: =IF($A17="","",HOUR($R17)+MINUTE($R17)/60) | AG17: =IF($A17="","",HOUR($S17)+MINUTE($S17)/60) | AH17: =IF($A17="","",HOUR($T17)+MINUTE($T17)/60) | AI17: =IF($A17="","",HOUR($V17)+MINUTE($V17)/60) | AJ17: =IF($A17="","",HOUR($W17)+MINUTE($W17)/60) | AK17: =IF($A17="","",VLOOKUP($F17,Dim_Team!$A:$F,6,0)) | AL17: =IF($A17="","",VLOOKUP($X17,Dim_Signoff!$A:$C,3,0)) | AM17: =IF($A17="","",IF($N17="No","n/a",ROUND((AH17-AE17)*60,0))) | AN17: =IF($A17="","",IF($O17="No","n/a",ROUND((AH17-AF17)*60,0))) | AO17: =IF($A17="","",IF($P17="No","n/a",ROUND((AH17-AG17)*60,0))) | AP17: =IF($A17="","",ROUND((AH17-AK17)*60,0)) | AQ17: =IF($A17="","",ROUND((AI17-AH17)*60,0)) | AR17: =IF($A17="","",IF(AP17>=AC17,"Yes","No")) | AS17: =IF($A17="","",IF(AQ17>=AD17+AL17,"Yes","No")) | AT17: =IF($A17="","",IF(AND(AR17="Yes",AS17="Yes"),"OK","REVIEW")) | AU17: =IF($A17="","",IF($P17="No","Not applicable",IF(AO17<Constants!$B$14,"CAPTURE","Not needed"))) | AV17: =IF($A17="","",IF($P17="No","n/a",RANK(AO17,AO:AO,1))) | AW17: =IF($A17="","",IF(UPPER($E17)="YES","Strategic","Non-strategic")) | AX17: =IF($A17="","",COUNTIFS(Fact_Work!$C:$C,$A17)) | AY17: =IF($A17="","",IF(AX17=0,"Not seen",IF(AX17>=Constants!$B$13*0.6,"Daily",IF(AX17>=Constants!$B$13*0.12,"Weekly","Monthly or ad hoc")))) | AZ17: =IF($A17="","",IFERROR(VLOOKUP($U17,Dim_TOP!$A:$H,8,0),"")) | BA17: =IF($A17="","",IFERROR(ROUND((AH17-AZ17)*60,0),"")) | BB17: =IF($A17="","",IF(BA17="","",IF(BA17<=0,"Sets the deadline","Later than peers by "&BA17&" min"))) | BC17: =IF($A17="","",IF($U17="",0,IF(COUNTIFS($U$2:$U17,$U17,$C$2:$C17,$C17)=1,1,0))) | BD17: =IF($A17="","",IF(UPPER($P17)="YES","Yes","No")) | BE17: =IF($A17="","",IF($N17="No","n/a",IF(AM17<=Constants!$B$17,"Yes","No"))) | BF17: =IF($A17="","",IF($O17="No","n/a",IF(AN17<=Constants!$B$17,"Yes","No"))) | BG17: =IF($A17="","",IF($P17="No","n/a",IF(AO17<=Constants!$B$17,"Yes","No"))) | BH17: =IF($A17="","",IF($N17="No","No custody process",IF(BE17="Yes","Thin custody slack","Ample custody slack"))) | BI17: =IF($A17="","",IF($N17="No","",AM17)) | BJ17: =IF($A17="","",IF($O17="No","",AN17)) | BK17: =IF($A17="","",IF($P17="No","",AO17))
Z18: =IF($A18="","",Constants!$B$6+$I18*Constants!$B$7+$J18*Constants!$B$8+$K18*Constants!$B$9+$L18*Constants!$B$10+$M18*Constants!$B$11) | AA18: =IF($A18="","",100-Z18) | AB18: =IF($A18="","",ROUND($H18*Constants!$B$4,1)) | AC18: =IF($A18="","",ROUND(AB18*Z18/100,1)) | AD18: =IF($A18="","",ROUND(AB18*AA18/100,1)) | AE18: =IF($A18="","",HOUR($Q18)+MINUTE($Q18)/60) | AF18: =IF($A18="","",HOUR($R18)+MINUTE($R18)/60) | AG18: =IF($A18="","",HOUR($S18)+MINUTE($S18)/60) | AH18: =IF($A18="","",HOUR($T18)+MINUTE($T18)/60) | AI18: =IF($A18="","",HOUR($V18)+MINUTE($V18)/60) | AJ18: =IF($A18="","",HOUR($W18)+MINUTE($W18)/60) | AK18: =IF($A18="","",VLOOKUP($F18,Dim_Team!$A:$F,6,0)) | AL18: =IF($A18="","",VLOOKUP($X18,Dim_Signoff!$A:$C,3,0)) | AM18: =IF($A18="","",IF($N18="No","n/a",ROUND((AH18-AE18)*60,0))) | AN18: =IF($A18="","",IF($O18="No","n/a",ROUND((AH18-AF18)*60,0))) | AO18: =IF($A18="","",IF($P18="No","n/a",ROUND((AH18-AG18)*60,0))) | AP18: =IF($A18="","",ROUND((AH18-AK18)*60,0)) | AQ18: =IF($A18="","",ROUND((AI18-AH18)*60,0)) | AR18: =IF($A18="","",IF(AP18>=AC18,"Yes","No")) | AS18: =IF($A18="","",IF(AQ18>=AD18+AL18,"Yes","No")) | AT18: =IF($A18="","",IF(AND(AR18="Yes",AS18="Yes"),"OK","REVIEW")) | AU18: =IF($A18="","",IF($P18="No","Not applicable",IF(AO18<Constants!$B$14,"CAPTURE","Not needed"))) | AV18: =IF($A18="","",IF($P18="No","n/a",RANK(AO18,AO:AO,1))) | AW18: =IF($A18="","",IF(UPPER($E18)="YES","Strategic","Non-strategic")) | AX18: =IF($A18="","",COUNTIFS(Fact_Work!$C:$C,$A18)) | AY18: =IF($A18="","",IF(AX18=0,"Not seen",IF(AX18>=Constants!$B$13*0.6,"Daily",IF(AX18>=Constants!$B$13*0.12,"Weekly","Monthly or ad hoc")))) | AZ18: =IF($A18="","",IFERROR(VLOOKUP($U18,Dim_TOP!$A:$H,8,0),"")) | BA18: =IF($A18="","",IFERROR(ROUND((AH18-AZ18)*60,0),"")) | BB18: =IF($A18="","",IF(BA18="","",IF(BA18<=0,"Sets the deadline","Later than peers by "&BA18&" min"))) | BC18: =IF($A18="","",IF($U18="",0,IF(COUNTIFS($U$2:$U18,$U18,$C$2:$C18,$C18)=1,1,0))) | BD18: =IF($A18="","",IF(UPPER($P18)="YES","Yes","No")) | BE18: =IF($A18="","",IF($N18="No","n/a",IF(AM18<=Constants!$B$17,"Yes","No"))) | BF18: =IF($A18="","",IF($O18="No","n/a",IF(AN18<=Constants!$B$17,"Yes","No"))) | BG18: =IF($A18="","",IF($P18="No","n/a",IF(AO18<=Constants!$B$17,"Yes","No"))) | BH18: =IF($A18="","",IF($N18="No","No custody process",IF(BE18="Yes","Thin custody slack","Ample custody slack"))) | BI18: =IF($A18="","",IF($N18="No","",AM18)) | BJ18: =IF($A18="","",IF($O18="No","",AN18)) | BK18: =IF($A18="","",IF($P18="No","",AO18))
Z19: =IF($A19="","",Constants!$B$6+$I19*Constants!$B$7+$J19*Constants!$B$8+$K19*Constants!$B$9+$L19*Constants!$B$10+$M19*Constants!$B$11) | AA19: =IF($A19="","",100-Z19) | AB19: =IF($A19="","",ROUND($H19*Constants!$B$4,1)) | AC19: =IF($A19="","",ROUND(AB19*Z19/100,1)) | AD19: =IF($A19="","",ROUND(AB19*AA19/100,1)) | AE19: =IF($A19="","",HOUR($Q19)+MINUTE($Q19)/60) | AF19: =IF($A19="","",HOUR($R19)+MINUTE($R19)/60) | AG19: =IF($A19="","",HOUR($S19)+MINUTE($S19)/60) | AH19: =IF($A19="","",HOUR($T19)+MINUTE($T19)/60) | AI19: =IF($A19="","",HOUR($V19)+MINUTE($V19)/60) | AJ19: =IF($A19="","",HOUR($W19)+MINUTE($W19)/60) | AK19: =IF($A19="","",VLOOKUP($F19,Dim_Team!$A:$F,6,0)) | AL19: =IF($A19="","",VLOOKUP($X19,Dim_Signoff!$A:$C,3,0)) | AM19: =IF($A19="","",IF($N19="No","n/a",ROUND((AH19-AE19)*60,0))) | AN19: =IF($A19="","",IF($O19="No","n/a",ROUND((AH19-AF19)*60,0))) | AO19: =IF($A19="","",IF($P19="No","n/a",ROUND((AH19-AG19)*60,0))) | AP19: =IF($A19="","",ROUND((AH19-AK19)*60,0)) | AQ19: =IF($A19="","",ROUND((AI19-AH19)*60,0)) | AR19: =IF($A19="","",IF(AP19>=AC19,"Yes","No")) | AS19: =IF($A19="","",IF(AQ19>=AD19+AL19,"Yes","No")) | AT19: =IF($A19="","",IF(AND(AR19="Yes",AS19="Yes"),"OK","REVIEW")) | AU19: =IF($A19="","",IF($P19="No","Not applicable",IF(AO19<Constants!$B$14,"CAPTURE","Not needed"))) | AV19: =IF($A19="","",IF($P19="No","n/a",RANK(AO19,AO:AO,1))) | AW19: =IF($A19="","",IF(UPPER($E19)="YES","Strategic","Non-strategic")) | AX19: =IF($A19="","",COUNTIFS(Fact_Work!$C:$C,$A19)) | AY19: =IF($A19="","",IF(AX19=0,"Not seen",IF(AX19>=Constants!$B$13*0.6,"Daily",IF(AX19>=Constants!$B$13*0.12,"Weekly","Monthly or ad hoc")))) | AZ19: =IF($A19="","",IFERROR(VLOOKUP($U19,Dim_TOP!$A:$H,8,0),"")) | BA19: =IF($A19="","",IFERROR(ROUND((AH19-AZ19)*60,0),"")) | BB19: =IF($A19="","",IF(BA19="","",IF(BA19<=0,"Sets the deadline","Later than peers by "&BA19&" min"))) | BC19: =IF($A19="","",IF($U19="",0,IF(COUNTIFS($U$2:$U19,$U19,$C$2:$C19,$C19)=1,1,0))) | BD19: =IF($A19="","",IF(UPPER($P19)="YES","Yes","No")) | BE19: =IF($A19="","",IF($N19="No","n/a",IF(AM19<=Constants!$B$17,"Yes","No"))) | BF19: =IF($A19="","",IF($O19="No","n/a",IF(AN19<=Constants!$B$17,"Yes","No"))) | BG19: =IF($A19="","",IF($P19="No","n/a",IF(AO19<=Constants!$B$17,"Yes","No"))) | BH19: =IF($A19="","",IF($N19="No","No custody process",IF(BE19="Yes","Thin custody slack","Ample custody slack"))) | BI19: =IF($A19="","",IF($N19="No","",AM19)) | BJ19: =IF($A19="","",IF($O19="No","",AN19)) | BK19: =IF($A19="","",IF($P19="No","",AO19))
Z20: =IF($A20="","",Constants!$B$6+$I20*Constants!$B$7+$J20*Constants!$B$8+$K20*Constants!$B$9+$L20*Constants!$B$10+$M20*Constants!$B$11) | AA20: =IF($A20="","",100-Z20) | AB20: =IF($A20="","",ROUND($H20*Constants!$B$4,1)) | AC20: =IF($A20="","",ROUND(AB20*Z20/100,1)) | AD20: =IF($A20="","",ROUND(AB20*AA20/100,1)) | AE20: =IF($A20="","",HOUR($Q20)+MINUTE($Q20)/60) | AF20: =IF($A20="","",HOUR($R20)+MINUTE($R20)/60) | AG20: =IF($A20="","",HOUR($S20)+MINUTE($S20)/60) | AH20: =IF($A20="","",HOUR($T20)+MINUTE($T20)/60) | AI20: =IF($A20="","",HOUR($V20)+MINUTE($V20)/60) | AJ20: =IF($A20="","",HOUR($W20)+MINUTE($W20)/60) | AK20: =IF($A20="","",VLOOKUP($F20,Dim_Team!$A:$F,6,0)) | AL20: =IF($A20="","",VLOOKUP($X20,Dim_Signoff!$A:$C,3,0)) | AM20: =IF($A20="","",IF($N20="No","n/a",ROUND((AH20-AE20)*60,0))) | AN20: =IF($A20="","",IF($O20="No","n/a",ROUND((AH20-AF20)*60,0))) | AO20: =IF($A20="","",IF($P20="No","n/a",ROUND((AH20-AG20)*60,0))) | AP20: =IF($A20="","",ROUND((AH20-AK20)*60,0)) | AQ20: =IF($A20="","",ROUND((AI20-AH20)*60,0)) | AR20: =IF($A20="","",IF(AP20>=AC20,"Yes","No")) | AS20: =IF($A20="","",IF(AQ20>=AD20+AL20,"Yes","No")) | AT20: =IF($A20="","",IF(AND(AR20="Yes",AS20="Yes"),"OK","REVIEW")) | AU20: =IF($A20="","",IF($P20="No","Not applicable",IF(AO20<Constants!$B$14,"CAPTURE","Not needed"))) | AV20: =IF($A20="","",IF($P20="No","n/a",RANK(AO20,AO:AO,1))) | AW20: =IF($A20="","",IF(UPPER($E20)="YES","Strategic","Non-strategic")) | AX20: =IF($A20="","",COUNTIFS(Fact_Work!$C:$C,$A20)) | AY20: =IF($A20="","",IF(AX20=0,"Not seen",IF(AX20>=Constants!$B$13*0.6,"Daily",IF(AX20>=Constants!$B$13*0.12,"Weekly","Monthly or ad hoc")))) | AZ20: =IF($A20="","",IFERROR(VLOOKUP($U20,Dim_TOP!$A:$H,8,0),"")) | BA20: =IF($A20="","",IFERROR(ROUND((AH20-AZ20)*60,0),"")) | BB20: =IF($A20="","",IF(BA20="","",IF(BA20<=0,"Sets the deadline","Later than peers by "&BA20&" min"))) | BC20: =IF($A20="","",IF($U20="",0,IF(COUNTIFS($U$2:$U20,$U20,$C$2:$C20,$C20)=1,1,0))) | BD20: =IF($A20="","",IF(UPPER($P20)="YES","Yes","No")) | BE20: =IF($A20="","",IF($N20="No","n/a",IF(AM20<=Constants!$B$17,"Yes","No"))) | BF20: =IF($A20="","",IF($O20="No","n/a",IF(AN20<=Constants!$B$17,"Yes","No"))) | BG20: =IF($A20="","",IF($P20="No","n/a",IF(AO20<=Constants!$B$17,"Yes","No"))) | BH20: =IF($A20="","",IF($N20="No","No custody process",IF(BE20="Yes","Thin custody slack","Ample custody slack"))) | BI20: =IF($A20="","",IF($N20="No","",AM20)) | BJ20: =IF($A20="","",IF($O20="No","",AN20)) | BK20: =IF($A20="","",IF($P20="No","",AO20))
Z21: =IF($A21="","",Constants!$B$6+$I21*Constants!$B$7+$J21*Constants!$B$8+$K21*Constants!$B$9+$L21*Constants!$B$10+$M21*Constants!$B$11) | AA21: =IF($A21="","",100-Z21) | AB21: =IF($A21="","",ROUND($H21*Constants!$B$4,1)) | AC21: =IF($A21="","",ROUND(AB21*Z21/100,1)) | AD21: =IF($A21="","",ROUND(AB21*AA21/100,1)) | AE21: =IF($A21="","",HOUR($Q21)+MINUTE($Q21)/60) | AF21: =IF($A21="","",HOUR($R21)+MINUTE($R21)/60) | AG21: =IF($A21="","",HOUR($S21)+MINUTE($S21)/60) | AH21: =IF($A21="","",HOUR($T21)+MINUTE($T21)/60) | AI21: =IF($A21="","",HOUR($V21)+MINUTE($V21)/60) | AJ21: =IF($A21="","",HOUR($W21)+MINUTE($W21)/60) | AK21: =IF($A21="","",VLOOKUP($F21,Dim_Team!$A:$F,6,0)) | AL21: =IF($A21="","",VLOOKUP($X21,Dim_Signoff!$A:$C,3,0)) | AM21: =IF($A21="","",IF($N21="No","n/a",ROUND((AH21-AE21)*60,0))) | AN21: =IF($A21="","",IF($O21="No","n/a",ROUND((AH21-AF21)*60,0))) | AO21: =IF($A21="","",IF($P21="No","n/a",ROUND((AH21-AG21)*60,0))) | AP21: =IF($A21="","",ROUND((AH21-AK21)*60,0)) | AQ21: =IF($A21="","",ROUND((AI21-AH21)*60,0)) | AR21: =IF($A21="","",IF(AP21>=AC21,"Yes","No")) | AS21: =IF($A21="","",IF(AQ21>=AD21+AL21,"Yes","No")) | AT21: =IF($A21="","",IF(AND(AR21="Yes",AS21="Yes"),"OK","REVIEW")) | AU21: =IF($A21="","",IF($P21="No","Not applicable",IF(AO21<Constants!$B$14,"CAPTURE","Not needed"))) | AV21: =IF($A21="","",IF($P21="No","n/a",RANK(AO21,AO:AO,1))) | AW21: =IF($A21="","",IF(UPPER($E21)="YES","Strategic","Non-strategic")) | AX21: =IF($A21="","",COUNTIFS(Fact_Work!$C:$C,$A21)) | AY21: =IF($A21="","",IF(AX21=0,"Not seen",IF(AX21>=Constants!$B$13*0.6,"Daily",IF(AX21>=Constants!$B$13*0.12,"Weekly","Monthly or ad hoc")))) | AZ21: =IF($A21="","",IFERROR(VLOOKUP($U21,Dim_TOP!$A:$H,8,0),"")) | BA21: =IF($A21="","",IFERROR(ROUND((AH21-AZ21)*60,0),"")) | BB21: =IF($A21="","",IF(BA21="","",IF(BA21<=0,"Sets the deadline","Later than peers by "&BA21&" min"))) | BC21: =IF($A21="","",IF($U21="",0,IF(COUNTIFS($U$2:$U21,$U21,$C$2:$C21,$C21)=1,1,0))) | BD21: =IF($A21="","",IF(UPPER($P21)="YES","Yes","No")) | BE21: =IF($A21="","",IF($N21="No","n/a",IF(AM21<=Constants!$B$17,"Yes","No"))) | BF21: =IF($A21="","",IF($O21="No","n/a",IF(AN21<=Constants!$B$17,"Yes","No"))) | BG21: =IF($A21="","",IF($P21="No","n/a",IF(AO21<=Constants!$B$17,"Yes","No"))) | BH21: =IF($A21="","",IF($N21="No","No custody process",IF(BE21="Yes","Thin custody slack","Ample custody slack"))) | BI21: =IF($A21="","",IF($N21="No","",AM21)) | BJ21: =IF($A21="","",IF($O21="No","",AN21)) | BK21: =IF($A21="","",IF($P21="No","",AO21))
Z22: =IF($A22="","",Constants!$B$6+$I22*Constants!$B$7+$J22*Constants!$B$8+$K22*Constants!$B$9+$L22*Constants!$B$10+$M22*Constants!$B$11) | AA22: =IF($A22="","",100-Z22) | AB22: =IF($A22="","",ROUND($H22*Constants!$B$4,1)) | AC22: =IF($A22="","",ROUND(AB22*Z22/100,1)) | AD22: =IF($A22="","",ROUND(AB22*AA22/100,1)) | AE22: =IF($A22="","",HOUR($Q22)+MINUTE($Q22)/60) | AF22: =IF($A22="","",HOUR($R22)+MINUTE($R22)/60) | AG22: =IF($A22="","",HOUR($S22)+MINUTE($S22)/60) | AH22: =IF($A22="","",HOUR($T22)+MINUTE($T22)/60) | AI22: =IF($A22="","",HOUR($V22)+MINUTE($V22)/60) | AJ22: =IF($A22="","",HOUR($W22)+MINUTE($W22)/60) | AK22: =IF($A22="","",VLOOKUP($F22,Dim_Team!$A:$F,6,0)) | AL22: =IF($A22="","",VLOOKUP($X22,Dim_Signoff!$A:$C,3,0)) | AM22: =IF($A22="","",IF($N22="No","n/a",ROUND((AH22-AE22)*60,0))) | AN22: =IF($A22="","",IF($O22="No","n/a",ROUND((AH22-AF22)*60,0))) | AO22: =IF($A22="","",IF($P22="No","n/a",ROUND((AH22-AG22)*60,0))) | AP22: =IF($A22="","",ROUND((AH22-AK22)*60,0)) | AQ22: =IF($A22="","",ROUND((AI22-AH22)*60,0)) | AR22: =IF($A22="","",IF(AP22>=AC22,"Yes","No")) | AS22: =IF($A22="","",IF(AQ22>=AD22+AL22,"Yes","No")) | AT22: =IF($A22="","",IF(AND(AR22="Yes",AS22="Yes"),"OK","REVIEW")) | AU22: =IF($A22="","",IF($P22="No","Not applicable",IF(AO22<Constants!$B$14,"CAPTURE","Not needed"))) | AV22: =IF($A22="","",IF($P22="No","n/a",RANK(AO22,AO:AO,1))) | AW22: =IF($A22="","",IF(UPPER($E22)="YES","Strategic","Non-strategic")) | AX22: =IF($A22="","",COUNTIFS(Fact_Work!$C:$C,$A22)) | AY22: =IF($A22="","",IF(AX22=0,"Not seen",IF(AX22>=Constants!$B$13*0.6,"Daily",IF(AX22>=Constants!$B$13*0.12,"Weekly","Monthly or ad hoc")))) | AZ22: =IF($A22="","",IFERROR(VLOOKUP($U22,Dim_TOP!$A:$H,8,0),"")) | BA22: =IF($A22="","",IFERROR(ROUND((AH22-AZ22)*60,0),"")) | BB22: =IF($A22="","",IF(BA22="","",IF(BA22<=0,"Sets the deadline","Later than peers by "&BA22&" min"))) | BC22: =IF($A22="","",IF($U22="",0,IF(COUNTIFS($U$2:$U22,$U22,$C$2:$C22,$C22)=1,1,0))) | BD22: =IF($A22="","",IF(UPPER($P22)="YES","Yes","No")) | BE22: =IF($A22="","",IF($N22="No","n/a",IF(AM22<=Constants!$B$17,"Yes","No"))) | BF22: =IF($A22="","",IF($O22="No","n/a",IF(AN22<=Constants!$B$17,"Yes","No"))) | BG22: =IF($A22="","",IF($P22="No","n/a",IF(AO22<=Constants!$B$17,"Yes","No"))) | BH22: =IF($A22="","",IF($N22="No","No custody process",IF(BE22="Yes","Thin custody slack","Ample custody slack"))) | BI22: =IF($A22="","",IF($N22="No","",AM22)) | BJ22: =IF($A22="","",IF($O22="No","",AN22)) | BK22: =IF($A22="","",IF($P22="No","",AO22))
Z23: =IF($A23="","",Constants!$B$6+$I23*Constants!$B$7+$J23*Constants!$B$8+$K23*Constants!$B$9+$L23*Constants!$B$10+$M23*Constants!$B$11) | AA23: =IF($A23="","",100-Z23) | AB23: =IF($A23="","",ROUND($H23*Constants!$B$4,1)) | AC23: =IF($A23="","",ROUND(AB23*Z23/100,1)) | AD23: =IF($A23="","",ROUND(AB23*AA23/100,1)) | AE23: =IF($A23="","",HOUR($Q23)+MINUTE($Q23)/60) | AF23: =IF($A23="","",HOUR($R23)+MINUTE($R23)/60) | AG23: =IF($A23="","",HOUR($S23)+MINUTE($S23)/60) | AH23: =IF($A23="","",HOUR($T23)+MINUTE($T23)/60) | AI23: =IF($A23="","",HOUR($V23)+MINUTE($V23)/60) | AJ23: =IF($A23="","",HOUR($W23)+MINUTE($W23)/60) | AK23: =IF($A23="","",VLOOKUP($F23,Dim_Team!$A:$F,6,0)) | AL23: =IF($A23="","",VLOOKUP($X23,Dim_Signoff!$A:$C,3,0)) | AM23: =IF($A23="","",IF($N23="No","n/a",ROUND((AH23-AE23)*60,0))) | AN23: =IF($A23="","",IF($O23="No","n/a",ROUND((AH23-AF23)*60,0))) | AO23: =IF($A23="","",IF($P23="No","n/a",ROUND((AH23-AG23)*60,0))) | AP23: =IF($A23="","",ROUND((AH23-AK23)*60,0)) | AQ23: =IF($A23="","",ROUND((AI23-AH23)*60,0)) | AR23: =IF($A23="","",IF(AP23>=AC23,"Yes","No")) | AS23: =IF($A23="","",IF(AQ23>=AD23+AL23,"Yes","No")) | AT23: =IF($A23="","",IF(AND(AR23="Yes",AS23="Yes"),"OK","REVIEW")) | AU23: =IF($A23="","",IF($P23="No","Not applicable",IF(AO23<Constants!$B$14,"CAPTURE","Not needed"))) | AV23: =IF($A23="","",IF($P23="No","n/a",RANK(AO23,AO:AO,1))) | AW23: =IF($A23="","",IF(UPPER($E23)="YES","Strategic","Non-strategic")) | AX23: =IF($A23="","",COUNTIFS(Fact_Work!$C:$C,$A23)) | AY23: =IF($A23="","",IF(AX23=0,"Not seen",IF(AX23>=Constants!$B$13*0.6,"Daily",IF(AX23>=Constants!$B$13*0.12,"Weekly","Monthly or ad hoc")))) | AZ23: =IF($A23="","",IFERROR(VLOOKUP($U23,Dim_TOP!$A:$H,8,0),"")) | BA23: =IF($A23="","",IFERROR(ROUND((AH23-AZ23)*60,0),"")) | BB23: =IF($A23="","",IF(BA23="","",IF(BA23<=0,"Sets the deadline","Later than peers by "&BA23&" min"))) | BC23: =IF($A23="","",IF($U23="",0,IF(COUNTIFS($U$2:$U23,$U23,$C$2:$C23,$C23)=1,1,0))) | BD23: =IF($A23="","",IF(UPPER($P23)="YES","Yes","No")) | BE23: =IF($A23="","",IF($N23="No","n/a",IF(AM23<=Constants!$B$17,"Yes","No"))) | BF23: =IF($A23="","",IF($O23="No","n/a",IF(AN23<=Constants!$B$17,"Yes","No"))) | BG23: =IF($A23="","",IF($P23="No","n/a",IF(AO23<=Constants!$B$17,"Yes","No"))) | BH23: =IF($A23="","",IF($N23="No","No custody process",IF(BE23="Yes","Thin custody slack","Ample custody slack"))) | BI23: =IF($A23="","",IF($N23="No","",AM23)) | BJ23: =IF($A23="","",IF($O23="No","",AN23)) | BK23: =IF($A23="","",IF($P23="No","",AO23))
Z24: =IF($A24="","",Constants!$B$6+$I24*Constants!$B$7+$J24*Constants!$B$8+$K24*Constants!$B$9+$L24*Constants!$B$10+$M24*Constants!$B$11) | AA24: =IF($A24="","",100-Z24) | AB24: =IF($A24="","",ROUND($H24*Constants!$B$4,1)) | AC24: =IF($A24="","",ROUND(AB24*Z24/100,1)) | AD24: =IF($A24="","",ROUND(AB24*AA24/100,1)) | AE24: =IF($A24="","",HOUR($Q24)+MINUTE($Q24)/60) | AF24: =IF($A24="","",HOUR($R24)+MINUTE($R24)/60) | AG24: =IF($A24="","",HOUR($S24)+MINUTE($S24)/60) | AH24: =IF($A24="","",HOUR($T24)+MINUTE($T24)/60) | AI24: =IF($A24="","",HOUR($V24)+MINUTE($V24)/60) | AJ24: =IF($A24="","",HOUR($W24)+MINUTE($W24)/60) | AK24: =IF($A24="","",VLOOKUP($F24,Dim_Team!$A:$F,6,0)) | AL24: =IF($A24="","",VLOOKUP($X24,Dim_Signoff!$A:$C,3,0)) | AM24: =IF($A24="","",IF($N24="No","n/a",ROUND((AH24-AE24)*60,0))) | AN24: =IF($A24="","",IF($O24="No","n/a",ROUND((AH24-AF24)*60,0))) | AO24: =IF($A24="","",IF($P24="No","n/a",ROUND((AH24-AG24)*60,0))) | AP24: =IF($A24="","",ROUND((AH24-AK24)*60,0)) | AQ24: =IF($A24="","",ROUND((AI24-AH24)*60,0)) | AR24: =IF($A24="","",IF(AP24>=AC24,"Yes","No")) | AS24: =IF($A24="","",IF(AQ24>=AD24+AL24,"Yes","No")) | AT24: =IF($A24="","",IF(AND(AR24="Yes",AS24="Yes"),"OK","REVIEW")) | AU24: =IF($A24="","",IF($P24="No","Not applicable",IF(AO24<Constants!$B$14,"CAPTURE","Not needed"))) | AV24: =IF($A24="","",IF($P24="No","n/a",RANK(AO24,AO:AO,1))) | AW24: =IF($A24="","",IF(UPPER($E24)="YES","Strategic","Non-strategic")) | AX24: =IF($A24="","",COUNTIFS(Fact_Work!$C:$C,$A24)) | AY24: =IF($A24="","",IF(AX24=0,"Not seen",IF(AX24>=Constants!$B$13*0.6,"Daily",IF(AX24>=Constants!$B$13*0.12,"Weekly","Monthly or ad hoc")))) | AZ24: =IF($A24="","",IFERROR(VLOOKUP($U24,Dim_TOP!$A:$H,8,0),"")) | BA24: =IF($A24="","",IFERROR(ROUND((AH24-AZ24)*60,0),"")) | BB24: =IF($A24="","",IF(BA24="","",IF(BA24<=0,"Sets the deadline","Later than peers by "&BA24&" min"))) | BC24: =IF($A24="","",IF($U24="",0,IF(COUNTIFS($U$2:$U24,$U24,$C$2:$C24,$C24)=1,1,0))) | BD24: =IF($A24="","",IF(UPPER($P24)="YES","Yes","No")) | BE24: =IF($A24="","",IF($N24="No","n/a",IF(AM24<=Constants!$B$17,"Yes","No"))) | BF24: =IF($A24="","",IF($O24="No","n/a",IF(AN24<=Constants!$B$17,"Yes","No"))) | BG24: =IF($A24="","",IF($P24="No","n/a",IF(AO24<=Constants!$B$17,"Yes","No"))) | BH24: =IF($A24="","",IF($N24="No","No custody process",IF(BE24="Yes","Thin custody slack","Ample custody slack"))) | BI24: =IF($A24="","",IF($N24="No","",AM24)) | BJ24: =IF($A24="","",IF($O24="No","",AN24)) | BK24: =IF($A24="","",IF($P24="No","",AO24))
Z25: =IF($A25="","",Constants!$B$6+$I25*Constants!$B$7+$J25*Constants!$B$8+$K25*Constants!$B$9+$L25*Constants!$B$10+$M25*Constants!$B$11) | AA25: =IF($A25="","",100-Z25) | AB25: =IF($A25="","",ROUND($H25*Constants!$B$4,1)) | AC25: =IF($A25="","",ROUND(AB25*Z25/100,1)) | AD25: =IF($A25="","",ROUND(AB25*AA25/100,1)) | AE25: =IF($A25="","",HOUR($Q25)+MINUTE($Q25)/60) | AF25: =IF($A25="","",HOUR($R25)+MINUTE($R25)/60) | AG25: =IF($A25="","",HOUR($S25)+MINUTE($S25)/60) | AH25: =IF($A25="","",HOUR($T25)+MINUTE($T25)/60) | AI25: =IF($A25="","",HOUR($V25)+MINUTE($V25)/60) | AJ25: =IF($A25="","",HOUR($W25)+MINUTE($W25)/60) | AK25: =IF($A25="","",VLOOKUP($F25,Dim_Team!$A:$F,6,0)) | AL25: =IF($A25="","",VLOOKUP($X25,Dim_Signoff!$A:$C,3,0)) | AM25: =IF($A25="","",IF($N25="No","n/a",ROUND((AH25-AE25)*60,0))) | AN25: =IF($A25="","",IF($O25="No","n/a",ROUND((AH25-AF25)*60,0))) | AO25: =IF($A25="","",IF($P25="No","n/a",ROUND((AH25-AG25)*60,0))) | AP25: =IF($A25="","",ROUND((AH25-AK25)*60,0)) | AQ25: =IF($A25="","",ROUND((AI25-AH25)*60,0)) | AR25: =IF($A25="","",IF(AP25>=AC25,"Yes","No")) | AS25: =IF($A25="","",IF(AQ25>=AD25+AL25,"Yes","No")) | AT25: =IF($A25="","",IF(AND(AR25="Yes",AS25="Yes"),"OK","REVIEW")) | AU25: =IF($A25="","",IF($P25="No","Not applicable",IF(AO25<Constants!$B$14,"CAPTURE","Not needed"))) | AV25: =IF($A25="","",IF($P25="No","n/a",RANK(AO25,AO:AO,1))) | AW25: =IF($A25="","",IF(UPPER($E25)="YES","Strategic","Non-strategic")) | AX25: =IF($A25="","",COUNTIFS(Fact_Work!$C:$C,$A25)) | AY25: =IF($A25="","",IF(AX25=0,"Not seen",IF(AX25>=Constants!$B$13*0.6,"Daily",IF(AX25>=Constants!$B$13*0.12,"Weekly","Monthly or ad hoc")))) | AZ25: =IF($A25="","",IFERROR(VLOOKUP($U25,Dim_TOP!$A:$H,8,0),"")) | BA25: =IF($A25="","",IFERROR(ROUND((AH25-AZ25)*60,0),"")) | BB25: =IF($A25="","",IF(BA25="","",IF(BA25<=0,"Sets the deadline","Later than peers by "&BA25&" min"))) | BC25: =IF($A25="","",IF($U25="",0,IF(COUNTIFS($U$2:$U25,$U25,$C$2:$C25,$C25)=1,1,0))) | BD25: =IF($A25="","",IF(UPPER($P25)="YES","Yes","No")) | BE25: =IF($A25="","",IF($N25="No","n/a",IF(AM25<=Constants!$B$17,"Yes","No"))) | BF25: =IF($A25="","",IF($O25="No","n/a",IF(AN25<=Constants!$B$17,"Yes","No"))) | BG25: =IF($A25="","",IF($P25="No","n/a",IF(AO25<=Constants!$B$17,"Yes","No"))) | BH25: =IF($A25="","",IF($N25="No","No custody process",IF(BE25="Yes","Thin custody slack","Ample custody slack"))) | BI25: =IF($A25="","",IF($N25="No","",AM25)) | BJ25: =IF($A25="","",IF($O25="No","",AN25)) | BK25: =IF($A25="","",IF($P25="No","",AO25))
... Z201: =IF($A201="","",Constants!$B$6+$I201*Constants!$B$7+$J201*Constants!$B$8+$K201*Constants!$B$9+$L201*Constants!$B$10+$M201*Constants!$B$11) | AA201: =IF($A201="","",100-Z201) | AB201: =IF($A201="","",ROUND($H201*Constants!$B$4,1)) | AC201: =IF($A201="","",ROUND(AB201*Z201/100,1)) | AD201: =IF($A201="","",ROUND(AB201*AA201/100,1)) | AE201: =IF($A201="","",HOUR($Q201)+MINUTE($Q201)/60) | AF201: =IF($A201="","",HOUR($R201)+MINUTE($R201)/60) | AG201: =IF($A201="","",HOUR($S201)+MINUTE($S201)/60) | AH201: =IF($A201="","",HOUR($T201)+MINUTE($T201)/60) | AI201: =IF($A201="","",HOUR($V201)+MINUTE($V201)/60) | AJ201: =IF($A201="","",HOUR($W201)+MINUTE($W201)/60) | AK201: =IF($A201="","",VLOOKUP($F201,Dim_Team!$A:$F,6,0)) | AL201: =IF($A201="","",VLOOKUP($X201,Dim_Signoff!$A:$C,3,0)) | AM201: =IF($A201="","",IF($N201="No","n/a",ROUND((AH201-AE201)*60,0))) | AN201: =IF($A201="","",IF($O201="No","n/a",ROUND((AH201-AF201)*60,0))) | AO201: =IF($A201="","",IF($P201="No","n/a",ROUND((AH201-AG201)*60,0))) | AP201: =IF($A201="","",ROUND((AH201-AK201)*60,0)) | AQ201: =IF($A201="","",ROUND((AI201-AH201)*60,0)) | AR201: =IF($A201="","",IF(AP201>=AC201,"Yes","No")) | AS201: =IF($A201="","",IF(AQ201>=AD201+AL201,"Yes","No")) | AT201: =IF($A201="","",IF(AND(AR201="Yes",AS201="Yes"),"OK","REVIEW")) | AU201: =IF($A201="","",IF($P201="No","Not applicable",IF(AO201<Constants!$B$14,"CAPTURE","Not needed"))) | AV201: =IF($A201="","",IF($P201="No","n/a",RANK(AO201,AO:AO,1))) | AW201: =IF($A201="","",IF(UPPER($E201)="YES","Strategic","Non-strategic")) | AX201: =IF($A201="","",COUNTIFS(Fact_Work!$C:$C,$A201)) | AY201: =IF($A201="","",IF(AX201=0,"Not seen",IF(AX201>=Constants!$B$13*0.6,"Daily",IF(AX201>=Constants!$B$13*0.12,"Weekly","Monthly or ad hoc")))) | AZ201: =IF($A201="","",IFERROR(VLOOKUP($U201,Dim_TOP!$A:$H,8,0),"")) | BA201: =IF($A201="","",IFERROR(ROUND((AH201-AZ201)*60,0),"")) | BB201: =IF($A201="","",IF(BA201="","",IF(BA201<=0,"Sets the deadline","Later than peers by "&BA201&" min"))) | BC201: =IF($A201="","",IF($U201="",0,IF(COUNTIFS($U$2:$U201,$U201,$C$2:$C201,$C201)=1,1,0))) | BD201: =IF($A201="","",IF(UPPER($P201)="YES","Yes","No")) | BE201: =IF($A201="","",IF($N201="No","n/a",IF(AM201<=Constants!$B$17,"Yes","No"))) | BF201: =IF($A201="","",IF($O201="No","n/a",IF(AN201<=Constants!$B$17,"Yes","No"))) | BG201: =IF($A201="","",IF($P201="No","n/a",IF(AO201<=Constants!$B$17,"Yes","No"))) | BH201: =IF($A201="","",IF($N201="No","No custody process",IF(BE201="Yes","Thin custody slack","Ample custody slack"))) | BI201: =IF($A201="","",IF($N201="No","",AM201)) | BJ201: =IF($A201="","",IF($O201="No","",AN201)) | BK201: =IF($A201="","",IF($P201="No","",AO201))

Sheet Dim_TOP
A1: TOP_ID | B1: TOP_Name | C1: Pricing_Supplier | D1: Funds_In_TOP | E1: Earliest_Cutoff_Hr | F1: Latest_Cutoff_Hr | G1: Cutoff_Spread_Mins | H1: Binding_Cutoff_Hr | I1: Blast_Radius_Flag | J1: Clients_In_TOP | K1: Share_Of_Funds | L1: TOP_Days_Scored | M1: TOP_Days_Late | N1: Late_Hours_Total | O1: Breached_Fund_Days_When_Late
A2: TOP-EQ1 | B2: Equity pricing group | C2: Internal Pricing Team | D2: =IF($A2="","",COUNTIF(Dim_Fund!$U:$U,$A2)) -> 3 | E2: =IF($A2="","",IF($D2=0,"",_xlfn.MINIFS(Dim_Fund!$AH:$AH,Dim_Fund!$U:$U,$A2,Dim_Fund!$AH:$AH,">0"))) -> 11.65 | F2: =IF($A2="","",IF($D2=0,"",_xlfn.MAXIFS(Dim_Fund!$AH:$AH,Dim_Fund!$U:$U,$A2,Dim_Fund!$AH:$AH,">0"))) -> 13.016667 | G2: =IF($A2="","",IF($D2=0,"",ROUND(($F2-$E2)*60,0))) -> 82 | H2: =IF($A2="","",$E2) -> 11.65 | I2: =IF($A2="","",IF($D2>=4,"HIGH — "&$D2&" funds share this feed",IF($D2>=2,"Medium — "&$D2&" funds","Single fund"))) -> Medium — 3 funds | J2: =IF($A2="","",COUNTIFS(Dim_Fund!$U:$U,$A2,Dim_Fund!$BC:$BC,1)) -> 3 | K2: =IF($A2="","",IF(COUNTA(Dim_Fund!$A:$A)<=1,"",$D2/(COUNTA(Dim_Fund!$A:$A)-1))) -> 0.25 | L2: =IF($A2="","",COUNTIFS(Fact_Milestone!$B:$B,$A2,Fact_Milestone!$I:$I,"?*")) -> 3 | M2: =IF($A2="","",COUNTIFS(Fact_Milestone!$B:$B,$A2,Fact_Milestone!$I:$I,"No")) -> 0 | N2: =IF($A2="","",ROUND(SUMIFS(Fact_Milestone!$L:$L,Fact_Milestone!$B:$B,$A2)/60,2)) -> 0 | O2: =IF($A2="","",COUNTIFS(Fact_Work!$AL:$AL,$A2,Fact_Work!$AI:$AI,"Yes",Fact_Work!$BB:$BB,"No")) -> 0
A3: TOP-FI1 | B3: Fixed income pricing group | C3: Internal Pricing Team | D3: =IF($A3="","",COUNTIF(Dim_Fund!$U:$U,$A3)) -> 3 | E3: =IF($A3="","",IF($D3=0,"",_xlfn.MINIFS(Dim_Fund!$AH:$AH,Dim_Fund!$U:$U,$A3,Dim_Fund!$AH:$AH,">0"))) -> 12.45 | F3: =IF($A3="","",IF($D3=0,"",_xlfn.MAXIFS(Dim_Fund!$AH:$AH,Dim_Fund!$U:$U,$A3,Dim_Fund!$AH:$AH,">0"))) -> 13.85 | G3: =IF($A3="","",IF($D3=0,"",ROUND(($F3-$E3)*60,0))) -> 84 | H3: =IF($A3="","",$E3) -> 12.45 | I3: =IF($A3="","",IF($D3>=4,"HIGH — "&$D3&" funds share this feed",IF($D3>=2,"Medium — "&$D3&" funds","Single fund"))) -> Medium — 3 funds | J3: =IF($A3="","",COUNTIFS(Dim_Fund!$U:$U,$A3,Dim_Fund!$BC:$BC,1)) -> 3 | K3: =IF($A3="","",IF(COUNTA(Dim_Fund!$A:$A)<=1,"",$D3/(COUNTA(Dim_Fund!$A:$A)-1))) -> 0.25 | L3: =IF($A3="","",COUNTIFS(Fact_Milestone!$B:$B,$A3,Fact_Milestone!$I:$I,"?*")) -> 3 | M3: =IF($A3="","",COUNTIFS(Fact_Milestone!$B:$B,$A3,Fact_Milestone!$I:$I,"No")) -> 0 | N3: =IF($A3="","",ROUND(SUMIFS(Fact_Milestone!$L:$L,Fact_Milestone!$B:$B,$A3)/60,2)) -> 0 | O3: =IF($A3="","",COUNTIFS(Fact_Work!$AL:$AL,$A3,Fact_Work!$AI:$AI,"Yes",Fact_Work!$BB:$BB,"No")) -> 0
A4: TOP-MA1 | B4: Multi-asset pricing group | C4: Internal Pricing Team | D4: =IF($A4="","",COUNTIF(Dim_Fund!$U:$U,$A4)) -> 3 | E4: =IF($A4="","",IF($D4=0,"",_xlfn.MINIFS(Dim_Fund!$AH:$AH,Dim_Fund!$U:$U,$A4,Dim_Fund!$AH:$AH,">0"))) -> 11.716667 | F4: =IF($A4="","",IF($D4=0,"",_xlfn.MAXIFS(Dim_Fund!$AH:$AH,Dim_Fund!$U:$U,$A4,Dim_Fund!$AH:$AH,">0"))) -> 13.116667 | G4: =IF($A4="","",IF($D4=0,"",ROUND(($F4-$E4)*60,0))) -> 84 | H4: =IF($A4="","",$E4) -> 11.716667 | I4: =IF($A4="","",IF($D4>=4,"HIGH — "&$D4&" funds share this feed",IF($D4>=2,"Medium — "&$D4&" funds","Single fund"))) -> Medium — 3 funds | J4: =IF($A4="","",COUNTIFS(Dim_Fund!$U:$U,$A4,Dim_Fund!$BC:$BC,1)) -> 3 | K4: =IF($A4="","",IF(COUNTA(Dim_Fund!$A:$A)<=1,"",$D4/(COUNTA(Dim_Fund!$A:$A)-1))) -> 0.25 | L4: =IF($A4="","",COUNTIFS(Fact_Milestone!$B:$B,$A4,Fact_Milestone!$I:$I,"?*")) -> 3 | M4: =IF($A4="","",COUNTIFS(Fact_Milestone!$B:$B,$A4,Fact_Milestone!$I:$I,"No")) -> 1 | N4: =IF($A4="","",ROUND(SUMIFS(Fact_Milestone!$L:$L,Fact_Milestone!$B:$B,$A4)/60,2)) -> 0.25 | O4: =IF($A4="","",COUNTIFS(Fact_Work!$AL:$AL,$A4,Fact_Work!$AI:$AI,"Yes",Fact_Work!$BB:$BB,"No")) -> 0
A5: TOP-ALT | B5: Alternatives pricing group | C5: Internal Pricing Team | D5: =IF($A5="","",COUNTIF(Dim_Fund!$U:$U,$A5)) -> 3 | E5: =IF($A5="","",IF($D5=0,"",_xlfn.MINIFS(Dim_Fund!$AH:$AH,Dim_Fund!$U:$U,$A5,Dim_Fund!$AH:$AH,">0"))) -> 11.633333 | F5: =IF($A5="","",IF($D5=0,"",_xlfn.MAXIFS(Dim_Fund!$AH:$AH,Dim_Fund!$U:$U,$A5,Dim_Fund!$AH:$AH,">0"))) -> 12.666667 | G5: =IF($A5="","",IF($D5=0,"",ROUND(($F5-$E5)*60,0))) -> 62 | H5: =IF($A5="","",$E5) -> 11.633333 | I5: =IF($A5="","",IF($D5>=4,"HIGH — "&$D5&" funds share this feed",IF($D5>=2,"Medium — "&$D5&" funds","Single fund"))) -> Medium — 3 funds | J5: =IF($A5="","",COUNTIFS(Dim_Fund!$U:$U,$A5,Dim_Fund!$BC:$BC,1)) -> 3 | K5: =IF($A5="","",IF(COUNTA(Dim_Fund!$A:$A)<=1,"",$D5/(COUNTA(Dim_Fund!$A:$A)-1))) -> 0.25 | L5: =IF($A5="","",COUNTIFS(Fact_Milestone!$B:$B,$A5,Fact_Milestone!$I:$I,"?*")) -> 3 | M5: =IF($A5="","",COUNTIFS(Fact_Milestone!$B:$B,$A5,Fact_Milestone!$I:$I,"No")) -> 1 | N5: =IF($A5="","",ROUND(SUMIFS(Fact_Milestone!$L:$L,Fact_Milestone!$B:$B,$A5)/60,2)) -> 0.92 | O5: =IF($A5="","",COUNTIFS(Fact_Work!$AL:$AL,$A5,Fact_Work!$AI:$AI,"Yes",Fact_Work!$BB:$BB,"No")) -> 1
D6: =IF($A6="","",COUNTIF(Dim_Fund!$U:$U,$A6)) | E6: =IF($A6="","",IF($D6=0,"",_xlfn.MINIFS(Dim_Fund!$AH:$AH,Dim_Fund!$U:$U,$A6,Dim_Fund!$AH:$AH,">0"))) | F6: =IF($A6="","",IF($D6=0,"",_xlfn.MAXIFS(Dim_Fund!$AH:$AH,Dim_Fund!$U:$U,$A6,Dim_Fund!$AH:$AH,">0"))) | G6: =IF($A6="","",IF($D6=0,"",ROUND(($F6-$E6)*60,0))) | H6: =IF($A6="","",$E6) | I6: =IF($A6="","",IF($D6>=4,"HIGH — "&$D6&" funds share this feed",IF($D6>=2,"Medium — "&$D6&" funds","Single fund"))) | J6: =IF($A6="","",COUNTIFS(Dim_Fund!$U:$U,$A6,Dim_Fund!$BC:$BC,1)) | K6: =IF($A6="","",IF(COUNTA(Dim_Fund!$A:$A)<=1,"",$D6/(COUNTA(Dim_Fund!$A:$A)-1))) | L6: =IF($A6="","",COUNTIFS(Fact_Milestone!$B:$B,$A6,Fact_Milestone!$I:$I,"?*")) | M6: =IF($A6="","",COUNTIFS(Fact_Milestone!$B:$B,$A6,Fact_Milestone!$I:$I,"No")) | N6: =IF($A6="","",ROUND(SUMIFS(Fact_Milestone!$L:$L,Fact_Milestone!$B:$B,$A6)/60,2)) | O6: =IF($A6="","",COUNTIFS(Fact_Work!$AL:$AL,$A6,Fact_Work!$AI:$AI,"Yes",Fact_Work!$BB:$BB,"No"))
D7: =IF($A7="","",COUNTIF(Dim_Fund!$U:$U,$A7)) | E7: =IF($A7="","",IF($D7=0,"",_xlfn.MINIFS(Dim_Fund!$AH:$AH,Dim_Fund!$U:$U,$A7,Dim_Fund!$AH:$AH,">0"))) | F7: =IF($A7="","",IF($D7=0,"",_xlfn.MAXIFS(Dim_Fund!$AH:$AH,Dim_Fund!$U:$U,$A7,Dim_Fund!$AH:$AH,">0"))) | G7: =IF($A7="","",IF($D7=0,"",ROUND(($F7-$E7)*60,0))) | H7: =IF($A7="","",$E7) | I7: =IF($A7="","",IF($D7>=4,"HIGH — "&$D7&" funds share this feed",IF($D7>=2,"Medium — "&$D7&" funds","Single fund"))) | J7: =IF($A7="","",COUNTIFS(Dim_Fund!$U:$U,$A7,Dim_Fund!$BC:$BC,1)) | K7: =IF($A7="","",IF(COUNTA(Dim_Fund!$A:$A)<=1,"",$D7/(COUNTA(Dim_Fund!$A:$A)-1))) | L7: =IF($A7="","",COUNTIFS(Fact_Milestone!$B:$B,$A7,Fact_Milestone!$I:$I,"?*")) | M7: =IF($A7="","",COUNTIFS(Fact_Milestone!$B:$B,$A7,Fact_Milestone!$I:$I,"No")) | N7: =IF($A7="","",ROUND(SUMIFS(Fact_Milestone!$L:$L,Fact_Milestone!$B:$B,$A7)/60,2)) | O7: =IF($A7="","",COUNTIFS(Fact_Work!$AL:$AL,$A7,Fact_Work!$AI:$AI,"Yes",Fact_Work!$BB:$BB,"No"))
D8: =IF($A8="","",COUNTIF(Dim_Fund!$U:$U,$A8)) | E8: =IF($A8="","",IF($D8=0,"",_xlfn.MINIFS(Dim_Fund!$AH:$AH,Dim_Fund!$U:$U,$A8,Dim_Fund!$AH:$AH,">0"))) | F8: =IF($A8="","",IF($D8=0,"",_xlfn.MAXIFS(Dim_Fund!$AH:$AH,Dim_Fund!$U:$U,$A8,Dim_Fund!$AH:$AH,">0"))) | G8: =IF($A8="","",IF($D8=0,"",ROUND(($F8-$E8)*60,0))) | H8: =IF($A8="","",$E8) | I8: =IF($A8="","",IF($D8>=4,"HIGH — "&$D8&" funds share this feed",IF($D8>=2,"Medium — "&$D8&" funds","Single fund"))) | J8: =IF($A8="","",COUNTIFS(Dim_Fund!$U:$U,$A8,Dim_Fund!$BC:$BC,1)) | K8: =IF($A8="","",IF(COUNTA(Dim_Fund!$A:$A)<=1,"",$D8/(COUNTA(Dim_Fund!$A:$A)-1))) | L8: =IF($A8="","",COUNTIFS(Fact_Milestone!$B:$B,$A8,Fact_Milestone!$I:$I,"?*")) | M8: =IF($A8="","",COUNTIFS(Fact_Milestone!$B:$B,$A8,Fact_Milestone!$I:$I,"No")) | N8: =IF($A8="","",ROUND(SUMIFS(Fact_Milestone!$L:$L,Fact_Milestone!$B:$B,$A8)/60,2)) | O8: =IF($A8="","",COUNTIFS(Fact_Work!$AL:$AL,$A8,Fact_Work!$AI:$AI,"Yes",Fact_Work!$BB:$BB,"No"))
D9: =IF($A9="","",COUNTIF(Dim_Fund!$U:$U,$A9)) | E9: =IF($A9="","",IF($D9=0,"",_xlfn.MINIFS(Dim_Fund!$AH:$AH,Dim_Fund!$U:$U,$A9,Dim_Fund!$AH:$AH,">0"))) | F9: =IF($A9="","",IF($D9=0,"",_xlfn.MAXIFS(Dim_Fund!$AH:$AH,Dim_Fund!$U:$U,$A9,Dim_Fund!$AH:$AH,">0"))) | G9: =IF($A9="","",IF($D9=0,"",ROUND(($F9-$E9)*60,0))) | H9: =IF($A9="","",$E9) | I9: =IF($A9="","",IF($D9>=4,"HIGH — "&$D9&" funds share this feed",IF($D9>=2,"Medium — "&$D9&" funds","Single fund"))) | J9: =IF($A9="","",COUNTIFS(Dim_Fund!$U:$U,$A9,Dim_Fund!$BC:$BC,1)) | K9: =IF($A9="","",IF(COUNTA(Dim_Fund!$A:$A)<=1,"",$D9/(COUNTA(Dim_Fund!$A:$A)-1))) | L9: =IF($A9="","",COUNTIFS(Fact_Milestone!$B:$B,$A9,Fact_Milestone!$I:$I,"?*")) | M9: =IF($A9="","",COUNTIFS(Fact_Milestone!$B:$B,$A9,Fact_Milestone!$I:$I,"No")) | N9: =IF($A9="","",ROUND(SUMIFS(Fact_Milestone!$L:$L,Fact_Milestone!$B:$B,$A9)/60,2)) | O9: =IF($A9="","",COUNTIFS(Fact_Work!$AL:$AL,$A9,Fact_Work!$AI:$AI,"Yes",Fact_Work!$BB:$BB,"No"))
D10: =IF($A10="","",COUNTIF(Dim_Fund!$U:$U,$A10)) | E10: =IF($A10="","",IF($D10=0,"",_xlfn.MINIFS(Dim_Fund!$AH:$AH,Dim_Fund!$U:$U,$A10,Dim_Fund!$AH:$AH,">0"))) | F10: =IF($A10="","",IF($D10=0,"",_xlfn.MAXIFS(Dim_Fund!$AH:$AH,Dim_Fund!$U:$U,$A10,Dim_Fund!$AH:$AH,">0"))) | G10: =IF($A10="","",IF($D10=0,"",ROUND(($F10-$E10)*60,0))) | H10: =IF($A10="","",$E10) | I10: =IF($A10="","",IF($D10>=4,"HIGH — "&$D10&" funds share this feed",IF($D10>=2,"Medium — "&$D10&" funds","Single fund"))) | J10: =IF($A10="","",COUNTIFS(Dim_Fund!$U:$U,$A10,Dim_Fund!$BC:$BC,1)) | K10: =IF($A10="","",IF(COUNTA(Dim_Fund!$A:$A)<=1,"",$D10/(COUNTA(Dim_Fund!$A:$A)-1))) | L10: =IF($A10="","",COUNTIFS(Fact_Milestone!$B:$B,$A10,Fact_Milestone!$I:$I,"?*")) | M10: =IF($A10="","",COUNTIFS(Fact_Milestone!$B:$B,$A10,Fact_Milestone!$I:$I,"No")) | N10: =IF($A10="","",ROUND(SUMIFS(Fact_Milestone!$L:$L,Fact_Milestone!$B:$B,$A10)/60,2)) | O10: =IF($A10="","",COUNTIFS(Fact_Work!$AL:$AL,$A10,Fact_Work!$AI:$AI,"Yes",Fact_Work!$BB:$BB,"No"))
D11: =IF($A11="","",COUNTIF(Dim_Fund!$U:$U,$A11)) | E11: =IF($A11="","",IF($D11=0,"",_xlfn.MINIFS(Dim_Fund!$AH:$AH,Dim_Fund!$U:$U,$A11,Dim_Fund!$AH:$AH,">0"))) | F11: =IF($A11="","",IF($D11=0,"",_xlfn.MAXIFS(Dim_Fund!$AH:$AH,Dim_Fund!$U:$U,$A11,Dim_Fund!$AH:$AH,">0"))) | G11: =IF($A11="","",IF($D11=0,"",ROUND(($F11-$E11)*60,0))) | H11: =IF($A11="","",$E11) | I11: =IF($A11="","",IF($D11>=4,"HIGH — "&$D11&" funds share this feed",IF($D11>=2,"Medium — "&$D11&" funds","Single fund"))) | J11: =IF($A11="","",COUNTIFS(Dim_Fund!$U:$U,$A11,Dim_Fund!$BC:$BC,1)) | K11: =IF($A11="","",IF(COUNTA(Dim_Fund!$A:$A)<=1,"",$D11/(COUNTA(Dim_Fund!$A:$A)-1))) | L11: =IF($A11="","",COUNTIFS(Fact_Milestone!$B:$B,$A11,Fact_Milestone!$I:$I,"?*")) | M11: =IF($A11="","",COUNTIFS(Fact_Milestone!$B:$B,$A11,Fact_Milestone!$I:$I,"No")) | N11: =IF($A11="","",ROUND(SUMIFS(Fact_Milestone!$L:$L,Fact_Milestone!$B:$B,$A11)/60,2)) | O11: =IF($A11="","",COUNTIFS(Fact_Work!$AL:$AL,$A11,Fact_Work!$AI:$AI,"Yes",Fact_Work!$BB:$BB,"No"))
D12: =IF($A12="","",COUNTIF(Dim_Fund!$U:$U,$A12)) | E12: =IF($A12="","",IF($D12=0,"",_xlfn.MINIFS(Dim_Fund!$AH:$AH,Dim_Fund!$U:$U,$A12,Dim_Fund!$AH:$AH,">0"))) | F12: =IF($A12="","",IF($D12=0,"",_xlfn.MAXIFS(Dim_Fund!$AH:$AH,Dim_Fund!$U:$U,$A12,Dim_Fund!$AH:$AH,">0"))) | G12: =IF($A12="","",IF($D12=0,"",ROUND(($F12-$E12)*60,0))) | H12: =IF($A12="","",$E12) | I12: =IF($A12="","",IF($D12>=4,"HIGH — "&$D12&" funds share this feed",IF($D12>=2,"Medium — "&$D12&" funds","Single fund"))) | J12: =IF($A12="","",COUNTIFS(Dim_Fund!$U:$U,$A12,Dim_Fund!$BC:$BC,1)) | K12: =IF($A12="","",IF(COUNTA(Dim_Fund!$A:$A)<=1,"",$D12/(COUNTA(Dim_Fund!$A:$A)-1))) | L12: =IF($A12="","",COUNTIFS(Fact_Milestone!$B:$B,$A12,Fact_Milestone!$I:$I,"?*")) | M12: =IF($A12="","",COUNTIFS(Fact_Milestone!$B:$B,$A12,Fact_Milestone!$I:$I,"No")) | N12: =IF($A12="","",ROUND(SUMIFS(Fact_Milestone!$L:$L,Fact_Milestone!$B:$B,$A12)/60,2)) | O12: =IF($A12="","",COUNTIFS(Fact_Work!$AL:$AL,$A12,Fact_Work!$AI:$AI,"Yes",Fact_Work!$BB:$BB,"No"))
D13: =IF($A13="","",COUNTIF(Dim_Fund!$U:$U,$A13)) | E13: =IF($A13="","",IF($D13=0,"",_xlfn.MINIFS(Dim_Fund!$AH:$AH,Dim_Fund!$U:$U,$A13,Dim_Fund!$AH:$AH,">0"))) | F13: =IF($A13="","",IF($D13=0,"",_xlfn.MAXIFS(Dim_Fund!$AH:$AH,Dim_Fund!$U:$U,$A13,Dim_Fund!$AH:$AH,">0"))) | G13: =IF($A13="","",IF($D13=0,"",ROUND(($F13-$E13)*60,0))) | H13: =IF($A13="","",$E13) | I13: =IF($A13="","",IF($D13>=4,"HIGH — "&$D13&" funds share this feed",IF($D13>=2,"Medium — "&$D13&" funds","Single fund"))) | J13: =IF($A13="","",COUNTIFS(Dim_Fund!$U:$U,$A13,Dim_Fund!$BC:$BC,1)) | K13: =IF($A13="","",IF(COUNTA(Dim_Fund!$A:$A)<=1,"",$D13/(COUNTA(Dim_Fund!$A:$A)-1))) | L13: =IF($A13="","",COUNTIFS(Fact_Milestone!$B:$B,$A13,Fact_Milestone!$I:$I,"?*")) | M13: =IF($A13="","",COUNTIFS(Fact_Milestone!$B:$B,$A13,Fact_Milestone!$I:$I,"No")) | N13: =IF($A13="","",ROUND(SUMIFS(Fact_Milestone!$L:$L,Fact_Milestone!$B:$B,$A13)/60,2)) | O13: =IF($A13="","",COUNTIFS(Fact_Work!$AL:$AL,$A13,Fact_Work!$AI:$AI,"Yes",Fact_Work!$BB:$BB,"No"))
D14: =IF($A14="","",COUNTIF(Dim_Fund!$U:$U,$A14)) | E14: =IF($A14="","",IF($D14=0,"",_xlfn.MINIFS(Dim_Fund!$AH:$AH,Dim_Fund!$U:$U,$A14,Dim_Fund!$AH:$AH,">0"))) | F14: =IF($A14="","",IF($D14=0,"",_xlfn.MAXIFS(Dim_Fund!$AH:$AH,Dim_Fund!$U:$U,$A14,Dim_Fund!$AH:$AH,">0"))) | G14: =IF($A14="","",IF($D14=0,"",ROUND(($F14-$E14)*60,0))) | H14: =IF($A14="","",$E14) | I14: =IF($A14="","",IF($D14>=4,"HIGH — "&$D14&" funds share this feed",IF($D14>=2,"Medium — "&$D14&" funds","Single fund"))) | J14: =IF($A14="","",COUNTIFS(Dim_Fund!$U:$U,$A14,Dim_Fund!$BC:$BC,1)) | K14: =IF($A14="","",IF(COUNTA(Dim_Fund!$A:$A)<=1,"",$D14/(COUNTA(Dim_Fund!$A:$A)-1))) | L14: =IF($A14="","",COUNTIFS(Fact_Milestone!$B:$B,$A14,Fact_Milestone!$I:$I,"?*")) | M14: =IF($A14="","",COUNTIFS(Fact_Milestone!$B:$B,$A14,Fact_Milestone!$I:$I,"No")) | N14: =IF($A14="","",ROUND(SUMIFS(Fact_Milestone!$L:$L,Fact_Milestone!$B:$B,$A14)/60,2)) | O14: =IF($A14="","",COUNTIFS(Fact_Work!$AL:$AL,$A14,Fact_Work!$AI:$AI,"Yes",Fact_Work!$BB:$BB,"No"))
D15: =IF($A15="","",COUNTIF(Dim_Fund!$U:$U,$A15)) | E15: =IF($A15="","",IF($D15=0,"",_xlfn.MINIFS(Dim_Fund!$AH:$AH,Dim_Fund!$U:$U,$A15,Dim_Fund!$AH:$AH,">0"))) | F15: =IF($A15="","",IF($D15=0,"",_xlfn.MAXIFS(Dim_Fund!$AH:$AH,Dim_Fund!$U:$U,$A15,Dim_Fund!$AH:$AH,">0"))) | G15: =IF($A15="","",IF($D15=0,"",ROUND(($F15-$E15)*60,0))) | H15: =IF($A15="","",$E15) | I15: =IF($A15="","",IF($D15>=4,"HIGH — "&$D15&" funds share this feed",IF($D15>=2,"Medium — "&$D15&" funds","Single fund"))) | J15: =IF($A15="","",COUNTIFS(Dim_Fund!$U:$U,$A15,Dim_Fund!$BC:$BC,1)) | K15: =IF($A15="","",IF(COUNTA(Dim_Fund!$A:$A)<=1,"",$D15/(COUNTA(Dim_Fund!$A:$A)-1))) | L15: =IF($A15="","",COUNTIFS(Fact_Milestone!$B:$B,$A15,Fact_Milestone!$I:$I,"?*")) | M15: =IF($A15="","",COUNTIFS(Fact_Milestone!$B:$B,$A15,Fact_Milestone!$I:$I,"No")) | N15: =IF($A15="","",ROUND(SUMIFS(Fact_Milestone!$L:$L,Fact_Milestone!$B:$B,$A15)/60,2)) | O15: =IF($A15="","",COUNTIFS(Fact_Work!$AL:$AL,$A15,Fact_Work!$AI:$AI,"Yes",Fact_Work!$BB:$BB,"No"))
D16: =IF($A16="","",COUNTIF(Dim_Fund!$U:$U,$A16)) | E16: =IF($A16="","",IF($D16=0,"",_xlfn.MINIFS(Dim_Fund!$AH:$AH,Dim_Fund!$U:$U,$A16,Dim_Fund!$AH:$AH,">0"))) | F16: =IF($A16="","",IF($D16=0,"",_xlfn.MAXIFS(Dim_Fund!$AH:$AH,Dim_Fund!$U:$U,$A16,Dim_Fund!$AH:$AH,">0"))) | G16: =IF($A16="","",IF($D16=0,"",ROUND(($F16-$E16)*60,0))) | H16: =IF($A16="","",$E16) | I16: =IF($A16="","",IF($D16>=4,"HIGH — "&$D16&" funds share this feed",IF($D16>=2,"Medium — "&$D16&" funds","Single fund"))) | J16: =IF($A16="","",COUNTIFS(Dim_Fund!$U:$U,$A16,Dim_Fund!$BC:$BC,1)) | K16: =IF($A16="","",IF(COUNTA(Dim_Fund!$A:$A)<=1,"",$D16/(COUNTA(Dim_Fund!$A:$A)-1))) | L16: =IF($A16="","",COUNTIFS(Fact_Milestone!$B:$B,$A16,Fact_Milestone!$I:$I,"?*")) | M16: =IF($A16="","",COUNTIFS(Fact_Milestone!$B:$B,$A16,Fact_Milestone!$I:$I,"No")) | N16: =IF($A16="","",ROUND(SUMIFS(Fact_Milestone!$L:$L,Fact_Milestone!$B:$B,$A16)/60,2)) | O16: =IF($A16="","",COUNTIFS(Fact_Work!$AL:$AL,$A16,Fact_Work!$AI:$AI,"Yes",Fact_Work!$BB:$BB,"No"))
D17: =IF($A17="","",COUNTIF(Dim_Fund!$U:$U,$A17)) | E17: =IF($A17="","",IF($D17=0,"",_xlfn.MINIFS(Dim_Fund!$AH:$AH,Dim_Fund!$U:$U,$A17,Dim_Fund!$AH:$AH,">0"))) | F17: =IF($A17="","",IF($D17=0,"",_xlfn.MAXIFS(Dim_Fund!$AH:$AH,Dim_Fund!$U:$U,$A17,Dim_Fund!$AH:$AH,">0"))) | G17: =IF($A17="","",IF($D17=0,"",ROUND(($F17-$E17)*60,0))) | H17: =IF($A17="","",$E17) | I17: =IF($A17="","",IF($D17>=4,"HIGH — "&$D17&" funds share this feed",IF($D17>=2,"Medium — "&$D17&" funds","Single fund"))) | J17: =IF($A17="","",COUNTIFS(Dim_Fund!$U:$U,$A17,Dim_Fund!$BC:$BC,1)) | K17: =IF($A17="","",IF(COUNTA(Dim_Fund!$A:$A)<=1,"",$D17/(COUNTA(Dim_Fund!$A:$A)-1))) | L17: =IF($A17="","",COUNTIFS(Fact_Milestone!$B:$B,$A17,Fact_Milestone!$I:$I,"?*")) | M17: =IF($A17="","",COUNTIFS(Fact_Milestone!$B:$B,$A17,Fact_Milestone!$I:$I,"No")) | N17: =IF($A17="","",ROUND(SUMIFS(Fact_Milestone!$L:$L,Fact_Milestone!$B:$B,$A17)/60,2)) | O17: =IF($A17="","",COUNTIFS(Fact_Work!$AL:$AL,$A17,Fact_Work!$AI:$AI,"Yes",Fact_Work!$BB:$BB,"No"))
... D200: =IF($A200="","",COUNTIF(Dim_Fund!$U:$U,$A200)) | E200: =IF($A200="","",IF($D200=0,"",_xlfn.MINIFS(Dim_Fund!$AH:$AH,Dim_Fund!$U:$U,$A200,Dim_Fund!$AH:$AH,">0"))) | F200: =IF($A200="","",IF($D200=0,"",_xlfn.MAXIFS(Dim_Fund!$AH:$AH,Dim_Fund!$U:$U,$A200,Dim_Fund!$AH:$AH,">0"))) | G200: =IF($A200="","",IF($D200=0,"",ROUND(($F200-$E200)*60,0))) | H200: =IF($A200="","",$E200) | I200: =IF($A200="","",IF($D200>=4,"HIGH — "&$D200&" funds share this feed",IF($D200>=2,"Medium — "&$D200&" funds","Single fund"))) | J200: =IF($A200="","",COUNTIFS(Dim_Fund!$U:$U,$A200,Dim_Fund!$BC:$BC,1)) | K200: =IF($A200="","",IF(COUNTA(Dim_Fund!$A:$A)<=1,"",$D200/(COUNTA(Dim_Fund!$A:$A)-1))) | L200: =IF($A200="","",COUNTIFS(Fact_Milestone!$B:$B,$A200,Fact_Milestone!$I:$I,"?*")) | M200: =IF($A200="","",COUNTIFS(Fact_Milestone!$B:$B,$A200,Fact_Milestone!$I:$I,"No")) | N200: =IF($A200="","",ROUND(SUMIFS(Fact_Milestone!$L:$L,Fact_Milestone!$B:$B,$A200)/60,2)) | O200: =IF($A200="","",COUNTIFS(Fact_Work!$AL:$AL,$A200,Fact_Work!$AI:$AI,"Yes",Fact_Work!$BB:$BB,"No"))

Sheet Fact_Milestone
A1: Process_Date | B1: TOP_ID | C1: Actual_Arrival_DT | D1: TOP_Name | E1: Funds_In_TOP | F1: Binding_Cutoff_Hr | G1: Binding_Cutoff_DT | H1: Delay_Mins | I1: SLA_Met | J1: Fund_Days_Impacted | K1: Due_Slot_Hr | L1: Late_Mins | M1: Breached_Fund_Days
A2: 46265 | B2: TOP-EQ1 | C2: 46265.46 | D2: =IF($A2="","",IFERROR(VLOOKUP($B2,Dim_TOP!$A:$B,2,0),"")) -> Equity pricing group | E2: =IF($A2="","",COUNTIFS(Fact_Work!$B:$B,$A2,Fact_Work!$AL:$AL,$B2)) -> 2 | F2: =IF($A2="","",IF(COUNTIFS(Fact_Work!$B:$B,$A2,Fact_Work!$AL:$AL,$B2,Fact_Work!$AN:$AN,">0")=0,"",_xlfn.MINIFS(Fact_Work!$AN:$AN,Fact_Work!$B:$B,$A2,Fact_Work!$AL:$AL,$B2,Fact_Work!$AN:$AN,">0"))) -> 12.483333 | G2: =IF($A2="","",IF($F2="","",$A2+$F2/24)) -> 46265.52 | H2: =IF($A2="","",IF($G2="","",ROUND(($C2-$G2)*1440,0))) -> -86 | I2: =IF($A2="","",IF($H2="","",IF($H2<=0,"Yes","No"))) -> Yes | J2: =IF($A2="","",IF($I2="No",$E2,0)) -> 0 | K2: =IF($A2="","",IF($F2="","",FLOOR($F2,0.5))) -> 12 | L2: =IF($A2="","",IF($H2="","",MAX(0,$H2))) -> 0 | M2: =IF($A2="","",IF($F2="","",COUNTIFS(Fact_Work!$B:$B,$A2,Fact_Work!$AL:$AL,$B2,Fact_Work!$AI:$AI,"Yes"))) -> 1
A3: 46265 | B3: TOP-FI1 | C3: 46265.484 | D3: =IF($A3="","",IFERROR(VLOOKUP($B3,Dim_TOP!$A:$B,2,0),"")) -> Fixed income pricing group | E3: =IF($A3="","",COUNTIFS(Fact_Work!$B:$B,$A3,Fact_Work!$AL:$AL,$B3)) -> 2 | F3: =IF($A3="","",IF(COUNTIFS(Fact_Work!$B:$B,$A3,Fact_Work!$AL:$AL,$B3,Fact_Work!$AN:$AN,">0")=0,"",_xlfn.MINIFS(Fact_Work!$AN:$AN,Fact_Work!$B:$B,$A3,Fact_Work!$AL:$AL,$B3,Fact_Work!$AN:$AN,">0"))) -> 12.45 | G3: =IF($A3="","",IF($F3="","",$A3+$F3/24)) -> 46265.519 | H3: =IF($A3="","",IF($G3="","",ROUND(($C3-$G3)*1440,0))) -> -50 | I3: =IF($A3="","",IF($H3="","",IF($H3<=0,"Yes","No"))) -> Yes | J3: =IF($A3="","",IF($I3="No",$E3,0)) -> 0 | K3: =IF($A3="","",IF($F3="","",FLOOR($F3,0.5))) -> 12 | L3: =IF($A3="","",IF($H3="","",MAX(0,$H3))) -> 0 | M3: =IF($A3="","",IF($F3="","",COUNTIFS(Fact_Work!$B:$B,$A3,Fact_Work!$AL:$AL,$B3,Fact_Work!$AI:$AI,"Yes"))) -> 0
A4: 46265 | B4: TOP-MA1 | C4: 46265.499 | D4: =IF($A4="","",IFERROR(VLOOKUP($B4,Dim_TOP!$A:$B,2,0),"")) -> Multi-asset pricing group | E4: =IF($A4="","",COUNTIFS(Fact_Work!$B:$B,$A4,Fact_Work!$AL:$AL,$B4)) -> 3 | F4: =IF($A4="","",IF(COUNTIFS(Fact_Work!$B:$B,$A4,Fact_Work!$AL:$AL,$B4,Fact_Work!$AN:$AN,">0")=0,"",_xlfn.MINIFS(Fact_Work!$AN:$AN,Fact_Work!$B:$B,$A4,Fact_Work!$AL:$AL,$B4,Fact_Work!$AN:$AN,">0"))) -> 11.716667 | G4: =IF($A4="","",IF($F4="","",$A4+$F4/24)) -> 46265.488 | H4: =IF($A4="","",IF($G4="","",ROUND(($C4-$G4)*1440,0))) -> 15 | I4: =IF($A4="","",IF($H4="","",IF($H4<=0,"Yes","No"))) -> No | J4: =IF($A4="","",IF($I4="No",$E4,0)) -> 3 | K4: =IF($A4="","",IF($F4="","",FLOOR($F4,0.5))) -> 11.5 | L4: =IF($A4="","",IF($H4="","",MAX(0,$H4))) -> 15 | M4: =IF($A4="","",IF($F4="","",COUNTIFS(Fact_Work!$B:$B,$A4,Fact_Work!$AL:$AL,$B4,Fact_Work!$AI:$AI,"Yes"))) -> 0
A5: 46265 | B5: TOP-ALT | C5: 46265.472 | D5: =IF($A5="","",IFERROR(VLOOKUP($B5,Dim_TOP!$A:$B,2,0),"")) -> Alternatives pricing group | E5: =IF($A5="","",COUNTIFS(Fact_Work!$B:$B,$A5,Fact_Work!$AL:$AL,$B5)) -> 2 | F5: =IF($A5="","",IF(COUNTIFS(Fact_Work!$B:$B,$A5,Fact_Work!$AL:$AL,$B5,Fact_Work!$AN:$AN,">0")=0,"",_xlfn.MINIFS(Fact_Work!$AN:$AN,Fact_Work!$B:$B,$A5,Fact_Work!$AL:$AL,$B5,Fact_Work!$AN:$AN,">0"))) -> 11.633333 | G5: =IF($A5="","",IF($F5="","",$A5+$F5/24)) -> 46265.485 | H5: =IF($A5="","",IF($G5="","",ROUND(($C5-$G5)*1440,0))) -> -19 | I5: =IF($A5="","",IF($H5="","",IF($H5<=0,"Yes","No"))) -> Yes | J5: =IF($A5="","",IF($I5="No",$E5,0)) -> 0 | K5: =IF($A5="","",IF($F5="","",FLOOR($F5,0.5))) -> 11.5 | L5: =IF($A5="","",IF($H5="","",MAX(0,$H5))) -> 0 | M5: =IF($A5="","",IF($F5="","",COUNTIFS(Fact_Work!$B:$B,$A5,Fact_Work!$AL:$AL,$B5,Fact_Work!$AI:$AI,"Yes"))) -> 0
A6: 46266 | B6: TOP-EQ1 | C6: 46266.463 | D6: =IF($A6="","",IFERROR(VLOOKUP($B6,Dim_TOP!$A:$B,2,0),"")) -> Equity pricing group | E6: =IF($A6="","",COUNTIFS(Fact_Work!$B:$B,$A6,Fact_Work!$AL:$AL,$B6)) -> 3 | F6: =IF($A6="","",IF(COUNTIFS(Fact_Work!$B:$B,$A6,Fact_Work!$AL:$AL,$B6,Fact_Work!$AN:$AN,">0")=0,"",_xlfn.MINIFS(Fact_Work!$AN:$AN,Fact_Work!$B:$B,$A6,Fact_Work!$AL:$AL,$B6,Fact_Work!$AN:$AN,">0"))) -> 11.65 | G6: =IF($A6="","",IF($F6="","",$A6+$F6/24)) -> 46266.485 | H6: =IF($A6="","",IF($G6="","",ROUND(($C6-$G6)*1440,0))) -> -32 | I6: =IF($A6="","",IF($H6="","",IF($H6<=0,"Yes","No"))) -> Yes | J6: =IF($A6="","",IF($I6="No",$E6,0)) -> 0 | K6: =IF($A6="","",IF($F6="","",FLOOR($F6,0.5))) -> 11.5 | L6: =IF($A6="","",IF($H6="","",MAX(0,$H6))) -> 0 | M6: =IF($A6="","",IF($F6="","",COUNTIFS(Fact_Work!$B:$B,$A6,Fact_Work!$AL:$AL,$B6,Fact_Work!$AI:$AI,"Yes"))) -> 2
A7: 46266 | B7: TOP-FI1 | C7: 46266.486 | D7: =IF($A7="","",IFERROR(VLOOKUP($B7,Dim_TOP!$A:$B,2,0),"")) -> Fixed income pricing group | E7: =IF($A7="","",COUNTIFS(Fact_Work!$B:$B,$A7,Fact_Work!$AL:$AL,$B7)) -> 3 | F7: =IF($A7="","",IF(COUNTIFS(Fact_Work!$B:$B,$A7,Fact_Work!$AL:$AL,$B7,Fact_Work!$AN:$AN,">0")=0,"",_xlfn.MINIFS(Fact_Work!$AN:$AN,Fact_Work!$B:$B,$A7,Fact_Work!$AL:$AL,$B7,Fact_Work!$AN:$AN,">0"))) -> 12.45 | G7: =IF($A7="","",IF($F7="","",$A7+$F7/24)) -> 46266.519 | H7: =IF($A7="","",IF($G7="","",ROUND(($C7-$G7)*1440,0))) -> -47 | I7: =IF($A7="","",IF($H7="","",IF($H7<=0,"Yes","No"))) -> Yes | J7: =IF($A7="","",IF($I7="No",$E7,0)) -> 0 | K7: =IF($A7="","",IF($F7="","",FLOOR($F7,0.5))) -> 12 | L7: =IF($A7="","",IF($H7="","",MAX(0,$H7))) -> 0 | M7: =IF($A7="","",IF($F7="","",COUNTIFS(Fact_Work!$B:$B,$A7,Fact_Work!$AL:$AL,$B7,Fact_Work!$AI:$AI,"Yes"))) -> 0
A8: 46266 | B8: TOP-MA1 | C8: 46266.463 | D8: =IF($A8="","",IFERROR(VLOOKUP($B8,Dim_TOP!$A:$B,2,0),"")) -> Multi-asset pricing group | E8: =IF($A8="","",COUNTIFS(Fact_Work!$B:$B,$A8,Fact_Work!$AL:$AL,$B8)) -> 2 | F8: =IF($A8="","",IF(COUNTIFS(Fact_Work!$B:$B,$A8,Fact_Work!$AL:$AL,$B8,Fact_Work!$AN:$AN,">0")=0,"",_xlfn.MINIFS(Fact_Work!$AN:$AN,Fact_Work!$B:$B,$A8,Fact_Work!$AL:$AL,$B8,Fact_Work!$AN:$AN,">0"))) -> 11.716667 | G8: =IF($A8="","",IF($F8="","",$A8+$F8/24)) -> 46266.488 | H8: =IF($A8="","",IF($G8="","",ROUND(($C8-$G8)*1440,0))) -> -36 | I8: =IF($A8="","",IF($H8="","",IF($H8<=0,"Yes","No"))) -> Yes | J8: =IF($A8="","",IF($I8="No",$E8,0)) -> 0 | K8: =IF($A8="","",IF($F8="","",FLOOR($F8,0.5))) -> 11.5 | L8: =IF($A8="","",IF($H8="","",MAX(0,$H8))) -> 0 | M8: =IF($A8="","",IF($F8="","",COUNTIFS(Fact_Work!$B:$B,$A8,Fact_Work!$AL:$AL,$B8,Fact_Work!$AI:$AI,"Yes"))) -> 0
A9: 46266 | B9: TOP-ALT | C9: 46266.531 | D9: =IF($A9="","",IFERROR(VLOOKUP($B9,Dim_TOP!$A:$B,2,0),"")) -> Alternatives pricing group | E9: =IF($A9="","",COUNTIFS(Fact_Work!$B:$B,$A9,Fact_Work!$AL:$AL,$B9)) -> 2 | F9: =IF($A9="","",IF(COUNTIFS(Fact_Work!$B:$B,$A9,Fact_Work!$AL:$AL,$B9,Fact_Work!$AN:$AN,">0")=0,"",_xlfn.MINIFS(Fact_Work!$AN:$AN,Fact_Work!$B:$B,$A9,Fact_Work!$AL:$AL,$B9,Fact_Work!$AN:$AN,">0"))) -> 11.816667 | G9: =IF($A9="","",IF($F9="","",$A9+$F9/24)) -> 46266.492 | H9: =IF($A9="","",IF($G9="","",ROUND(($C9-$G9)*1440,0))) -> 55 | I9: =IF($A9="","",IF($H9="","",IF($H9<=0,"Yes","No"))) -> No | J9: =IF($A9="","",IF($I9="No",$E9,0)) -> 2 | K9: =IF($A9="","",IF($F9="","",FLOOR($F9,0.5))) -> 11.5 | L9: =IF($A9="","",IF($H9="","",MAX(0,$H9))) -> 55 | M9: =IF($A9="","",IF($F9="","",COUNTIFS(Fact_Work!$B:$B,$A9,Fact_Work!$AL:$AL,$B9,Fact_Work!$AI:$AI,"Yes"))) -> 1
A10: 46267 | B10: TOP-EQ1 | C10: 46267.453 | D10: =IF($A10="","",IFERROR(VLOOKUP($B10,Dim_TOP!$A:$B,2,0),"")) -> Equity pricing group | E10: =IF($A10="","",COUNTIFS(Fact_Work!$B:$B,$A10,Fact_Work!$AL:$AL,$B10)) -> 2 | F10: =IF($A10="","",IF(COUNTIFS(Fact_Work!$B:$B,$A10,Fact_Work!$AL:$AL,$B10,Fact_Work!$AN:$AN,">0")=0,"",_xlfn.MINIFS(Fact_Work!$AN:$AN,Fact_Work!$B:$B,$A10,Fact_Work!$AL:$AL,$B10,Fact_Work!$AN:$AN,">0"))) -> 12.483333 | G10: =IF($A10="","",IF($F10="","",$A10+$F10/24)) -> 46267.52 | H10: =IF($A10="","",IF($G10="","",ROUND(($C10-$G10)*1440,0))) -> -96 | I10: =IF($A10="","",IF($H10="","",IF($H10<=0,"Yes","No"))) -> Yes | J10: =IF($A10="","",IF($I10="No",$E10,0)) -> 0 | K10: =IF($A10="","",IF($F10="","",FLOOR($F10,0.5))) -> 12 | L10: =IF($A10="","",IF($H10="","",MAX(0,$H10))) -> 0 | M10: =IF($A10="","",IF($F10="","",COUNTIFS(Fact_Work!$B:$B,$A10,Fact_Work!$AL:$AL,$B10,Fact_Work!$AI:$AI,"Yes"))) -> 1
A11: 46267 | B11: TOP-FI1 | C11: 46267.497 | D11: =IF($A11="","",IFERROR(VLOOKUP($B11,Dim_TOP!$A:$B,2,0),"")) -> Fixed income pricing group | E11: =IF($A11="","",COUNTIFS(Fact_Work!$B:$B,$A11,Fact_Work!$AL:$AL,$B11)) -> 2 | F11: =IF($A11="","",IF(COUNTIFS(Fact_Work!$B:$B,$A11,Fact_Work!$AL:$AL,$B11,Fact_Work!$AN:$AN,">0")=0,"",_xlfn.MINIFS(Fact_Work!$AN:$AN,Fact_Work!$B:$B,$A11,Fact_Work!$AL:$AL,$B11,Fact_Work!$AN:$AN,">0"))) -> 12.45 | G11: =IF($A11="","",IF($F11="","",$A11+$F11/24)) -> 46267.519 | H11: =IF($A11="","",IF($G11="","",ROUND(($C11-$G11)*1440,0))) -> -31 | I11: =IF($A11="","",IF($H11="","",IF($H11<=0,"Yes","No"))) -> Yes | J11: =IF($A11="","",IF($I11="No",$E11,0)) -> 0 | K11: =IF($A11="","",IF($F11="","",FLOOR($F11,0.5))) -> 12 | L11: =IF($A11="","",IF($H11="","",MAX(0,$H11))) -> 0 | M11: =IF($A11="","",IF($F11="","",COUNTIFS(Fact_Work!$B:$B,$A11,Fact_Work!$AL:$AL,$B11,Fact_Work!$AI:$AI,"Yes"))) -> 0
A12: 46267 | B12: TOP-MA1 | C12: 46267.447 | D12: =IF($A12="","",IFERROR(VLOOKUP($B12,Dim_TOP!$A:$B,2,0),"")) -> Multi-asset pricing group | E12: =IF($A12="","",COUNTIFS(Fact_Work!$B:$B,$A12,Fact_Work!$AL:$AL,$B12)) -> 2 | F12: =IF($A12="","",IF(COUNTIFS(Fact_Work!$B:$B,$A12,Fact_Work!$AL:$AL,$B12,Fact_Work!$AN:$AN,">0")=0,"",_xlfn.MINIFS(Fact_Work!$AN:$AN,Fact_Work!$B:$B,$A12,Fact_Work!$AL:$AL,$B12,Fact_Work!$AN:$AN,">0"))) -> 11.716667 | G12: =IF($A12="","",IF($F12="","",$A12+$F12/24)) -> 46267.488 | H12: =IF($A12="","",IF($G12="","",ROUND(($C12-$G12)*1440,0))) -> -60 | I12: =IF($A12="","",IF($H12="","",IF($H12<=0,"Yes","No"))) -> Yes | J12: =IF($A12="","",IF($I12="No",$E12,0)) -> 0 | K12: =IF($A12="","",IF($F12="","",FLOOR($F12,0.5))) -> 11.5 | L12: =IF($A12="","",IF($H12="","",MAX(0,$H12))) -> 0 | M12: =IF($A12="","",IF($F12="","",COUNTIFS(Fact_Work!$B:$B,$A12,Fact_Work!$AL:$AL,$B12,Fact_Work!$AI:$AI,"Yes"))) -> 0
A13: 46267 | B13: TOP-ALT | C13: 46267.469 | D13: =IF($A13="","",IFERROR(VLOOKUP($B13,Dim_TOP!$A:$B,2,0),"")) -> Alternatives pricing group | E13: =IF($A13="","",COUNTIFS(Fact_Work!$B:$B,$A13,Fact_Work!$AL:$AL,$B13)) -> 1 | F13: =IF($A13="","",IF(COUNTIFS(Fact_Work!$B:$B,$A13,Fact_Work!$AL:$AL,$B13,Fact_Work!$AN:$AN,">0")=0,"",_xlfn.MINIFS(Fact_Work!$AN:$AN,Fact_Work!$B:$B,$A13,Fact_Work!$AL:$AL,$B13,Fact_Work!$AN:$AN,">0"))) -> 12.666667 | G13: =IF($A13="","",IF($F13="","",$A13+$F13/24)) -> 46267.528 | H13: =IF($A13="","",IF($G13="","",ROUND(($C13-$G13)*1440,0))) -> -85 | I13: =IF($A13="","",IF($H13="","",IF($H13<=0,"Yes","No"))) -> Yes | J13: =IF($A13="","",IF($I13="No",$E13,0)) -> 0 | K13: =IF($A13="","",IF($F13="","",FLOOR($F13,0.5))) -> 12.5 | L13: =IF($A13="","",IF($H13="","",MAX(0,$H13))) -> 0 | M13: =IF($A13="","",IF($F13="","",COUNTIFS(Fact_Work!$B:$B,$A13,Fact_Work!$AL:$AL,$B13,Fact_Work!$AI:$AI,"Yes"))) -> 1
D14: =IF($A14="","",IFERROR(VLOOKUP($B14,Dim_TOP!$A:$B,2,0),"")) | E14: =IF($A14="","",COUNTIFS(Fact_Work!$B:$B,$A14,Fact_Work!$AL:$AL,$B14)) | F14: =IF($A14="","",IF(COUNTIFS(Fact_Work!$B:$B,$A14,Fact_Work!$AL:$AL,$B14,Fact_Work!$AN:$AN,">0")=0,"",_xlfn.MINIFS(Fact_Work!$AN:$AN,Fact_Work!$B:$B,$A14,Fact_Work!$AL:$AL,$B14,Fact_Work!$AN:$AN,">0"))) | G14: =IF($A14="","",IF($F14="","",$A14+$F14/24)) | H14: =IF($A14="","",IF($G14="","",ROUND(($C14-$G14)*1440,0))) | I14: =IF($A14="","",IF($H14="","",IF($H14<=0,"Yes","No"))) | J14: =IF($A14="","",IF($I14="No",$E14,0)) | K14: =IF($A14="","",IF($F14="","",FLOOR($F14,0.5))) | L14: =IF($A14="","",IF($H14="","",MAX(0,$H14))) | M14: =IF($A14="","",IF($F14="","",COUNTIFS(Fact_Work!$B:$B,$A14,Fact_Work!$AL:$AL,$B14,Fact_Work!$AI:$AI,"Yes")))
D15: =IF($A15="","",IFERROR(VLOOKUP($B15,Dim_TOP!$A:$B,2,0),"")) | E15: =IF($A15="","",COUNTIFS(Fact_Work!$B:$B,$A15,Fact_Work!$AL:$AL,$B15)) | F15: =IF($A15="","",IF(COUNTIFS(Fact_Work!$B:$B,$A15,Fact_Work!$AL:$AL,$B15,Fact_Work!$AN:$AN,">0")=0,"",_xlfn.MINIFS(Fact_Work!$AN:$AN,Fact_Work!$B:$B,$A15,Fact_Work!$AL:$AL,$B15,Fact_Work!$AN:$AN,">0"))) | G15: =IF($A15="","",IF($F15="","",$A15+$F15/24)) | H15: =IF($A15="","",IF($G15="","",ROUND(($C15-$G15)*1440,0))) | I15: =IF($A15="","",IF($H15="","",IF($H15<=0,"Yes","No"))) | J15: =IF($A15="","",IF($I15="No",$E15,0)) | K15: =IF($A15="","",IF($F15="","",FLOOR($F15,0.5))) | L15: =IF($A15="","",IF($H15="","",MAX(0,$H15))) | M15: =IF($A15="","",IF($F15="","",COUNTIFS(Fact_Work!$B:$B,$A15,Fact_Work!$AL:$AL,$B15,Fact_Work!$AI:$AI,"Yes")))
D16: =IF($A16="","",IFERROR(VLOOKUP($B16,Dim_TOP!$A:$B,2,0),"")) | E16: =IF($A16="","",COUNTIFS(Fact_Work!$B:$B,$A16,Fact_Work!$AL:$AL,$B16)) | F16: =IF($A16="","",IF(COUNTIFS(Fact_Work!$B:$B,$A16,Fact_Work!$AL:$AL,$B16,Fact_Work!$AN:$AN,">0")=0,"",_xlfn.MINIFS(Fact_Work!$AN:$AN,Fact_Work!$B:$B,$A16,Fact_Work!$AL:$AL,$B16,Fact_Work!$AN:$AN,">0"))) | G16: =IF($A16="","",IF($F16="","",$A16+$F16/24)) | H16: =IF($A16="","",IF($G16="","",ROUND(($C16-$G16)*1440,0))) | I16: =IF($A16="","",IF($H16="","",IF($H16<=0,"Yes","No"))) | J16: =IF($A16="","",IF($I16="No",$E16,0)) | K16: =IF($A16="","",IF($F16="","",FLOOR($F16,0.5))) | L16: =IF($A16="","",IF($H16="","",MAX(0,$H16))) | M16: =IF($A16="","",IF($F16="","",COUNTIFS(Fact_Work!$B:$B,$A16,Fact_Work!$AL:$AL,$B16,Fact_Work!$AI:$AI,"Yes")))
D17: =IF($A17="","",IFERROR(VLOOKUP($B17,Dim_TOP!$A:$B,2,0),"")) | E17: =IF($A17="","",COUNTIFS(Fact_Work!$B:$B,$A17,Fact_Work!$AL:$AL,$B17)) | F17: =IF($A17="","",IF(COUNTIFS(Fact_Work!$B:$B,$A17,Fact_Work!$AL:$AL,$B17,Fact_Work!$AN:$AN,">0")=0,"",_xlfn.MINIFS(Fact_Work!$AN:$AN,Fact_Work!$B:$B,$A17,Fact_Work!$AL:$AL,$B17,Fact_Work!$AN:$AN,">0"))) | G17: =IF($A17="","",IF($F17="","",$A17+$F17/24)) | H17: =IF($A17="","",IF($G17="","",ROUND(($C17-$G17)*1440,0))) | I17: =IF($A17="","",IF($H17="","",IF($H17<=0,"Yes","No"))) | J17: =IF($A17="","",IF($I17="No",$E17,0)) | K17: =IF($A17="","",IF($F17="","",FLOOR($F17,0.5))) | L17: =IF($A17="","",IF($H17="","",MAX(0,$H17))) | M17: =IF($A17="","",IF($F17="","",COUNTIFS(Fact_Work!$B:$B,$A17,Fact_Work!$AL:$AL,$B17,Fact_Work!$AI:$AI,"Yes")))
D18: =IF($A18="","",IFERROR(VLOOKUP($B18,Dim_TOP!$A:$B,2,0),"")) | E18: =IF($A18="","",COUNTIFS(Fact_Work!$B:$B,$A18,Fact_Work!$AL:$AL,$B18)) | F18: =IF($A18="","",IF(COUNTIFS(Fact_Work!$B:$B,$A18,Fact_Work!$AL:$AL,$B18,Fact_Work!$AN:$AN,">0")=0,"",_xlfn.MINIFS(Fact_Work!$AN:$AN,Fact_Work!$B:$B,$A18,Fact_Work!$AL:$AL,$B18,Fact_Work!$AN:$AN,">0"))) | G18: =IF($A18="","",IF($F18="","",$A18+$F18/24)) | H18: =IF($A18="","",IF($G18="","",ROUND(($C18-$G18)*1440,0))) | I18: =IF($A18="","",IF($H18="","",IF($H18<=0,"Yes","No"))) | J18: =IF($A18="","",IF($I18="No",$E18,0)) | K18: =IF($A18="","",IF($F18="","",FLOOR($F18,0.5))) | L18: =IF($A18="","",IF($H18="","",MAX(0,$H18))) | M18: =IF($A18="","",IF($F18="","",COUNTIFS(Fact_Work!$B:$B,$A18,Fact_Work!$AL:$AL,$B18,Fact_Work!$AI:$AI,"Yes")))
D19: =IF($A19="","",IFERROR(VLOOKUP($B19,Dim_TOP!$A:$B,2,0),"")) | E19: =IF($A19="","",COUNTIFS(Fact_Work!$B:$B,$A19,Fact_Work!$AL:$AL,$B19)) | F19: =IF($A19="","",IF(COUNTIFS(Fact_Work!$B:$B,$A19,Fact_Work!$AL:$AL,$B19,Fact_Work!$AN:$AN,">0")=0,"",_xlfn.MINIFS(Fact_Work!$AN:$AN,Fact_Work!$B:$B,$A19,Fact_Work!$AL:$AL,$B19,Fact_Work!$AN:$AN,">0"))) | G19: =IF($A19="","",IF($F19="","",$A19+$F19/24)) | H19: =IF($A19="","",IF($G19="","",ROUND(($C19-$G19)*1440,0))) | I19: =IF($A19="","",IF($H19="","",IF($H19<=0,"Yes","No"))) | J19: =IF($A19="","",IF($I19="No",$E19,0)) | K19: =IF($A19="","",IF($F19="","",FLOOR($F19,0.5))) | L19: =IF($A19="","",IF($H19="","",MAX(0,$H19))) | M19: =IF($A19="","",IF($F19="","",COUNTIFS(Fact_Work!$B:$B,$A19,Fact_Work!$AL:$AL,$B19,Fact_Work!$AI:$AI,"Yes")))
D20: =IF($A20="","",IFERROR(VLOOKUP($B20,Dim_TOP!$A:$B,2,0),"")) | E20: =IF($A20="","",COUNTIFS(Fact_Work!$B:$B,$A20,Fact_Work!$AL:$AL,$B20)) | F20: =IF($A20="","",IF(COUNTIFS(Fact_Work!$B:$B,$A20,Fact_Work!$AL:$AL,$B20,Fact_Work!$AN:$AN,">0")=0,"",_xlfn.MINIFS(Fact_Work!$AN:$AN,Fact_Work!$B:$B,$A20,Fact_Work!$AL:$AL,$B20,Fact_Work!$AN:$AN,">0"))) | G20: =IF($A20="","",IF($F20="","",$A20+$F20/24)) | H20: =IF($A20="","",IF($G20="","",ROUND(($C20-$G20)*1440,0))) | I20: =IF($A20="","",IF($H20="","",IF($H20<=0,"Yes","No"))) | J20: =IF($A20="","",IF($I20="No",$E20,0)) | K20: =IF($A20="","",IF($F20="","",FLOOR($F20,0.5))) | L20: =IF($A20="","",IF($H20="","",MAX(0,$H20))) | M20: =IF($A20="","",IF($F20="","",COUNTIFS(Fact_Work!$B:$B,$A20,Fact_Work!$AL:$AL,$B20,Fact_Work!$AI:$AI,"Yes")))
D21: =IF($A21="","",IFERROR(VLOOKUP($B21,Dim_TOP!$A:$B,2,0),"")) | E21: =IF($A21="","",COUNTIFS(Fact_Work!$B:$B,$A21,Fact_Work!$AL:$AL,$B21)) | F21: =IF($A21="","",IF(COUNTIFS(Fact_Work!$B:$B,$A21,Fact_Work!$AL:$AL,$B21,Fact_Work!$AN:$AN,">0")=0,"",_xlfn.MINIFS(Fact_Work!$AN:$AN,Fact_Work!$B:$B,$A21,Fact_Work!$AL:$AL,$B21,Fact_Work!$AN:$AN,">0"))) | G21: =IF($A21="","",IF($F21="","",$A21+$F21/24)) | H21: =IF($A21="","",IF($G21="","",ROUND(($C21-$G21)*1440,0))) | I21: =IF($A21="","",IF($H21="","",IF($H21<=0,"Yes","No"))) | J21: =IF($A21="","",IF($I21="No",$E21,0)) | K21: =IF($A21="","",IF($F21="","",FLOOR($F21,0.5))) | L21: =IF($A21="","",IF($H21="","",MAX(0,$H21))) | M21: =IF($A21="","",IF($F21="","",COUNTIFS(Fact_Work!$B:$B,$A21,Fact_Work!$AL:$AL,$B21,Fact_Work!$AI:$AI,"Yes")))
D22: =IF($A22="","",IFERROR(VLOOKUP($B22,Dim_TOP!$A:$B,2,0),"")) | E22: =IF($A22="","",COUNTIFS(Fact_Work!$B:$B,$A22,Fact_Work!$AL:$AL,$B22)) | F22: =IF($A22="","",IF(COUNTIFS(Fact_Work!$B:$B,$A22,Fact_Work!$AL:$AL,$B22,Fact_Work!$AN:$AN,">0")=0,"",_xlfn.MINIFS(Fact_Work!$AN:$AN,Fact_Work!$B:$B,$A22,Fact_Work!$AL:$AL,$B22,Fact_Work!$AN:$AN,">0"))) | G22: =IF($A22="","",IF($F22="","",$A22+$F22/24)) | H22: =IF($A22="","",IF($G22="","",ROUND(($C22-$G22)*1440,0))) | I22: =IF($A22="","",IF($H22="","",IF($H22<=0,"Yes","No"))) | J22: =IF($A22="","",IF($I22="No",$E22,0)) | K22: =IF($A22="","",IF($F22="","",FLOOR($F22,0.5))) | L22: =IF($A22="","",IF($H22="","",MAX(0,$H22))) | M22: =IF($A22="","",IF($F22="","",COUNTIFS(Fact_Work!$B:$B,$A22,Fact_Work!$AL:$AL,$B22,Fact_Work!$AI:$AI,"Yes")))
D23: =IF($A23="","",IFERROR(VLOOKUP($B23,Dim_TOP!$A:$B,2,0),"")) | E23: =IF($A23="","",COUNTIFS(Fact_Work!$B:$B,$A23,Fact_Work!$AL:$AL,$B23)) | F23: =IF($A23="","",IF(COUNTIFS(Fact_Work!$B:$B,$A23,Fact_Work!$AL:$AL,$B23,Fact_Work!$AN:$AN,">0")=0,"",_xlfn.MINIFS(Fact_Work!$AN:$AN,Fact_Work!$B:$B,$A23,Fact_Work!$AL:$AL,$B23,Fact_Work!$AN:$AN,">0"))) | G23: =IF($A23="","",IF($F23="","",$A23+$F23/24)) | H23: =IF($A23="","",IF($G23="","",ROUND(($C23-$G23)*1440,0))) | I23: =IF($A23="","",IF($H23="","",IF($H23<=0,"Yes","No"))) | J23: =IF($A23="","",IF($I23="No",$E23,0)) | K23: =IF($A23="","",IF($F23="","",FLOOR($F23,0.5))) | L23: =IF($A23="","",IF($H23="","",MAX(0,$H23))) | M23: =IF($A23="","",IF($F23="","",COUNTIFS(Fact_Work!$B:$B,$A23,Fact_Work!$AL:$AL,$B23,Fact_Work!$AI:$AI,"Yes")))
D24: =IF($A24="","",IFERROR(VLOOKUP($B24,Dim_TOP!$A:$B,2,0),"")) | E24: =IF($A24="","",COUNTIFS(Fact_Work!$B:$B,$A24,Fact_Work!$AL:$AL,$B24)) | F24: =IF($A24="","",IF(COUNTIFS(Fact_Work!$B:$B,$A24,Fact_Work!$AL:$AL,$B24,Fact_Work!$AN:$AN,">0")=0,"",_xlfn.MINIFS(Fact_Work!$AN:$AN,Fact_Work!$B:$B,$A24,Fact_Work!$AL:$AL,$B24,Fact_Work!$AN:$AN,">0"))) | G24: =IF($A24="","",IF($F24="","",$A24+$F24/24)) | H24: =IF($A24="","",IF($G24="","",ROUND(($C24-$G24)*1440,0))) | I24: =IF($A24="","",IF($H24="","",IF($H24<=0,"Yes","No"))) | J24: =IF($A24="","",IF($I24="No",$E24,0)) | K24: =IF($A24="","",IF($F24="","",FLOOR($F24,0.5))) | L24: =IF($A24="","",IF($H24="","",MAX(0,$H24))) | M24: =IF($A24="","",IF($F24="","",COUNTIFS(Fact_Work!$B:$B,$A24,Fact_Work!$AL:$AL,$B24,Fact_Work!$AI:$AI,"Yes")))
D25: =IF($A25="","",IFERROR(VLOOKUP($B25,Dim_TOP!$A:$B,2,0),"")) | E25: =IF($A25="","",COUNTIFS(Fact_Work!$B:$B,$A25,Fact_Work!$AL:$AL,$B25)) | F25: =IF($A25="","",IF(COUNTIFS(Fact_Work!$B:$B,$A25,Fact_Work!$AL:$AL,$B25,Fact_Work!$AN:$AN,">0")=0,"",_xlfn.MINIFS(Fact_Work!$AN:$AN,Fact_Work!$B:$B,$A25,Fact_Work!$AL:$AL,$B25,Fact_Work!$AN:$AN,">0"))) | G25: =IF($A25="","",IF($F25="","",$A25+$F25/24)) | H25: =IF($A25="","",IF($G25="","",ROUND(($C25-$G25)*1440,0))) | I25: =IF($A25="","",IF($H25="","",IF($H25<=0,"Yes","No"))) | J25: =IF($A25="","",IF($I25="No",$E25,0)) | K25: =IF($A25="","",IF($F25="","",FLOOR($F25,0.5))) | L25: =IF($A25="","",IF($H25="","",MAX(0,$H25))) | M25: =IF($A25="","",IF($F25="","",COUNTIFS(Fact_Work!$B:$B,$A25,Fact_Work!$AL:$AL,$B25,Fact_Work!$AI:$AI,"Yes")))
... D401: =IF($A401="","",IFERROR(VLOOKUP($B401,Dim_TOP!$A:$B,2,0),"")) | E401: =IF($A401="","",COUNTIFS(Fact_Work!$B:$B,$A401,Fact_Work!$AL:$AL,$B401)) | F401: =IF($A401="","",IF(COUNTIFS(Fact_Work!$B:$B,$A401,Fact_Work!$AL:$AL,$B401,Fact_Work!$AN:$AN,">0")=0,"",_xlfn.MINIFS(Fact_Work!$AN:$AN,Fact_Work!$B:$B,$A401,Fact_Work!$AL:$AL,$B401,Fact_Work!$AN:$AN,">0"))) | G401: =IF($A401="","",IF($F401="","",$A401+$F401/24)) | H401: =IF($A401="","",IF($G401="","",ROUND(($C401-$G401)*1440,0))) | I401: =IF($A401="","",IF($H401="","",IF($H401<=0,"Yes","No"))) | J401: =IF($A401="","",IF($I401="No",$E401,0)) | K401: =IF($A401="","",IF($F401="","",FLOOR($F401,0.5))) | L401: =IF($A401="","",IF($H401="","",MAX(0,$H401))) | M401: =IF($A401="","",IF($F401="","",COUNTIFS(Fact_Work!$B:$B,$A401,Fact_Work!$AL:$AL,$B401,Fact_Work!$AI:$AI,"Yes")))

Sheet Raw_Fund_Import
A1: FUND_CODE | B1: FUND_LONG_NAME | C1: PORTFOLIO_MGR | D1: CLIENT_CODE | E1: CLIENT_LONG_NAME | F1: STRATEGIC_FLAG | G1: OPS_TEAM | H1: PRIMARY_ANALYST | I1: FUND_WEIGHT | J1: HAS_ETD | K1: HAS_OTC_NONCFD | L1: HAS_OTC_CFD | M1: HAS_PFC | N1: CUST_CUTOFF_HHMM | O1: TA_CUTOFF_HHMM | P1: BROKER_ETA_HHMM | Q1: PSA_CUTOFF_HHMM | R1: CLIENT_DEADLINE_HHMM | S1: NAV_DEADLINE_HHMM | T1: SIGNOFF_TYPE | U1: CCY | V1: DOMICILE | W1: CUSTODY_FLAG | X1: TA_FLAG | Y1: BROKER_FLAG | Z1: HAS_EUC
A2: FD-1001 | B2: Sample Fund 1001 | C2: PM Desk 3 | D2: CL01 | E2: Meridian Pensions | F2: Y | G2: TM01 | H2: TM01-A1 | I2: 2.152 | J2: Y | K2: N | L2: N | M2: Y | N2: 451 | O2: 1230 | P2: 1230 | Q2: 1230 | R2: 1644 | S2: 1719 | T2: FA | U2: EUR | V2: LU | W2: Yes | X2: No | Y2: No | Z2: N
A3: FD-1002 | B3: Sample Fund 1002 | C3: PM Desk 1 | D3: CL02 | E3: Northgate Insurance | F3: Y | G3: TM01 | H3: TM01-A2 | I3: 1.213 | J3: N | K3: N | L3: N | M3: N | N3: 442 | O3: 338 | P3: 824 | Q3: 1228 | R3: 1625 | S3: 1703 | T3: FA | U3: EUR | V3: LU | W3: Yes | X3: Yes | Y3: Yes | Z3: Y
A4: FD-1003 | B4: Sample Fund 1003 | C4: PM Desk 2 | D4: CL03 | E4: Halvern Wealth | F4: N | G4: TM02 | H4: TM02-A1 | I4: 2.073 | J4: N | K4: N | L4: N | M4: N | N4: 432 | O4: 436 | P4: 737 | Q4: 1144 | R4: 1555 | S4: 1641 | T4: FA | U4: EUR | V4: LU | W4: Yes | X4: Yes | Y4: Yes | Z4: N
A5: FD-1004 | B5: Sample Fund 1004 | C5: PM Desk 3 | D5: CL01 | E5: Meridian Pensions | F5: Y | G5: TM03 | H5: TM03-A1 | I5: 2.099 | J5: N | K5: N | L5: N | M5: N | N5: 428 | O5: 352 | P5: 737 | Q5: 1241 | R5: 1658 | S5: 1736 | T5: Oversight | U5: EUR | V5: LU | W5: Yes | X5: Yes | Y5: Yes | Z5: N
A6: FD-1005 | B6: Sample Fund 1005 | C6: PM Desk 1 | D6: CL02 | E6: Northgate Insurance | F6: Y | G6: TM03 | H6: TM03-A2 | I6: 1.597 | J6: N | K6: N | L6: N | M6: N | N6: 435 | O6: 1302 | P6: 703 | Q6: 1302 | R6: 1625 | S6: 1713 | T6: Client | U6: EUR | V6: LU | W6: Yes | X6: No | Y6: Yes | Z6: Y
A7: FD-1006 | B7: Sample Fund 1006 | C7: PM Desk 2 | D7: CL03 | E7: Halvern Wealth | F7: N | G7: TM04 | H7: TM04-A1 | I7: 1.147 | J7: Y | K7: N | L7: N | M7: Y | N7: 444 | O7: 354 | P7: 1153 | Q7: 1317 | R7: 1745 | S7: 1823 | T7: FA | U7: EUR | V7: LU | W7: Yes | X7: Yes | Y7: Yes | Z7: N
A8: FD-1007 | B8: Sample Fund 1007 | C8: PM Desk 3 | D8: CL01 | E8: Meridian Pensions | F8: Y | G8: TM01 | H8: TM01-A1 | I8: 1.347 | J8: N | K8: Y | L8: Y | M8: Y | N8: 334 | O8: 441 | P8: 1307 | Q8: 1307 | R8: 1722 | S8: 1818 | T8: FA | U8: EUR | V8: LU | W8: Yes | X8: Yes | Y8: No | Z8: N
A9: FD-1008 | B9: Sample Fund 1008 | C9: PM Desk 1 | D9: CL02 | E9: Northgate Insurance | F9: Y | G9: TM01 | H9: TM01-A2 | I9: 1.769 | J9: N | K9: N | L9: Y | M9: N | N9: 430 | O9: 402 | P9: 757 | Q9: 1150 | R9: 1609 | S9: 1647 | T9: FA | U9: EUR | V9: LU | W9: Yes | X9: Yes | Y9: Yes | Z9: Y
A10: FD-1009 | B10: Sample Fund 1009 | C10: PM Desk 2 | D10: CL03 | E10: Halvern Wealth | F10: N | G10: TM02 | H10: TM02-A1 | I10: 1.487 | J10: N | K10: Y | L10: N | M10: N | N10: 418 | O10: 1139 | P10: 726 | Q10: 1139 | R10: 1511 | S10: 1602 | T10: Oversight | U10: EUR | V10: LU | W10: Yes | X10: No | Y10: Yes | Z10: N
A11: FD-1010 | B11: Sample Fund 1010 | C11: PM Desk 3 | D11: CL01 | E11: Meridian Pensions | F11: Y | G11: TM03 | H11: TM03-A1 | I11: 1.091 | J11: N | K11: N | L11: N | M11: N | N11: 358 | O11: 342 | P11: 829 | Q11: 1351 | R11: 1731 | S11: 1818 | T11: Client | U11: EUR | V11: LU | W11: Yes | X11: Yes | Y11: Yes | Z11: N
A12: FD-1011 | B12: Sample Fund 1011 | C12: PM Desk 1 | D12: CL02 | E12: Northgate Insurance | F12: Y | G12: TM03 | H12: TM03-A2 | I12: 1.958 | J12: Y | K12: N | L12: Y | M12: N | N12: 345 | O12: 457 | P12: 1142 | Q12: 1214 | R12: 1646 | S12: 1739 | T12: FA | U12: EUR | V12: LU | W12: Yes | X12: Yes | Y12: Yes | Z12: Y
A13: FD-1012 | B13: Sample Fund 1012 | C13: PM Desk 2 | D13: CL03 | E13: Halvern Wealth | F13: N | G13: TM04 | H13: TM04-A1 | I13: 2.148 | J13: N | K13: N | L13: N | M13: N | N13: 343 | O13: 527 | P13: 753 | Q13: 1138 | R13: 1503 | S13: 1553 | T13: FA | U13: EUR | V13: LU | W13: Yes | X13: Yes | Y13: Yes | Z13: N

Sheet Mapping
A1: Target_Field | B1: Your_Column_Header | C1: Transform | D1: Default_If_Missing | E1: Status
A2: Fund_ID | B2: FUND_CODE | E2: =IF($B2="","Using default",IFERROR(IF(MATCH($B2,Raw_Fund_Import!$1:$1,0)>0,"FOUND"),"NOT FOUND")) -> FOUND
A3: Fund_Name | B3: FUND_LONG_NAME | E3: =IF($B3="","Using default",IFERROR(IF(MATCH($B3,Raw_Fund_Import!$1:$1,0)>0,"FOUND"),"NOT FOUND")) -> FOUND
A4: Client_ID | B4: CLIENT_CODE | E4: =IF($B4="","Using default",IFERROR(IF(MATCH($B4,Raw_Fund_Import!$1:$1,0)>0,"FOUND"),"NOT FOUND")) -> FOUND
A5: Client_Name | B5: CLIENT_LONG_NAME | E5: =IF($B5="","Using default",IFERROR(IF(MATCH($B5,Raw_Fund_Import!$1:$1,0)>0,"FOUND"),"NOT FOUND")) -> FOUND
A6: Strategic_Client | B6: STRATEGIC_FLAG | C6: YESNO | D6: No | E6: =IF($B6="","Using default",IFERROR(IF(MATCH($B6,Raw_Fund_Import!$1:$1,0)>0,"FOUND"),"NOT FOUND")) -> FOUND
A7: Team_ID | B7: OPS_TEAM | E7: =IF($B7="","Using default",IFERROR(IF(MATCH($B7,Raw_Fund_Import!$1:$1,0)>0,"FOUND"),"NOT FOUND")) -> FOUND
A8: Default_Analyst_Name | B8: PRIMARY_ANALYST | E8: =IF($B8="","Using default",IFERROR(IF(MATCH($B8,Raw_Fund_Import!$1:$1,0)>0,"FOUND"),"NOT FOUND")) -> FOUND
A9: Weightage | B9: FUND_WEIGHT | E9: =IF($B9="","Using default",IFERROR(IF(MATCH($B9,Raw_Fund_Import!$1:$1,0)>0,"FOUND"),"NOT FOUND")) -> FOUND
A10: ETD | B10: HAS_ETD | C10: YN | E10: =IF($B10="","Using default",IFERROR(IF(MATCH($B10,Raw_Fund_Import!$1:$1,0)>0,"FOUND"),"NOT FOUND")) -> FOUND
A11: OTC_nonCFD | B11: HAS_OTC_NONCFD | C11: YN | E11: =IF($B11="","Using default",IFERROR(IF(MATCH($B11,Raw_Fund_Import!$1:$1,0)>0,"FOUND"),"NOT FOUND")) -> FOUND
A12: OTC_CFD | B12: HAS_OTC_CFD | C12: YN | E12: =IF($B12="","Using default",IFERROR(IF(MATCH($B12,Raw_Fund_Import!$1:$1,0)>0,"FOUND"),"NOT FOUND")) -> FOUND
A13: PFC | B13: HAS_PFC | C13: YN | E13: =IF($B13="","Using default",IFERROR(IF(MATCH($B13,Raw_Fund_Import!$1:$1,0)>0,"FOUND"),"NOT FOUND")) -> FOUND
A14: EUC | B14: HAS_EUC | C14: YN | E14: =IF($B14="","Using default",IFERROR(IF(MATCH($B14,Raw_Fund_Import!$1:$1,0)>0,"FOUND"),"NOT FOUND")) -> FOUND
A15: Has_Custody_Process | B15: CUSTODY_FLAG | D15: Yes | E15: =IF($B15="","Using default",IFERROR(IF(MATCH($B15,Raw_Fund_Import!$1:$1,0)>0,"FOUND"),"NOT FOUND")) -> FOUND
A16: Has_TA_Process | B16: TA_FLAG | D16: Yes | E16: =IF($B16="","Using default",IFERROR(IF(MATCH($B16,Raw_Fund_Import!$1:$1,0)>0,"FOUND"),"NOT FOUND")) -> FOUND
A17: Has_Broker_Process | B17: BROKER_FLAG | D17: Yes | E17: =IF($B17="","Using default",IFERROR(IF(MATCH($B17,Raw_Fund_Import!$1:$1,0)>0,"FOUND"),"NOT FOUND")) -> FOUND
A18: Custody_Cutoff | B18: CUST_CUTOFF_HHMM | C18: HHMM | E18: =IF($B18="","Using default",IFERROR(IF(MATCH($B18,Raw_Fund_Import!$1:$1,0)>0,"FOUND"),"NOT FOUND")) -> FOUND
A19: TA_Cutoff | B19: TA_CUTOFF_HHMM | C19: HHMM | E19: =IF($B19="","Using default",IFERROR(IF(MATCH($B19,Raw_Fund_Import!$1:$1,0)>0,"FOUND"),"NOT FOUND")) -> FOUND
A20: Broker_ETA | B20: BROKER_ETA_HHMM | C20: HHMM | E20: =IF($B20="","Using default",IFERROR(IF(MATCH($B20,Raw_Fund_Import!$1:$1,0)>0,"FOUND"),"NOT FOUND")) -> FOUND
A21: Pricing_Cutoff | B21: PSA_CUTOFF_HHMM | C21: HHMM | E21: =IF($B21="","Using default",IFERROR(IF(MATCH($B21,Raw_Fund_Import!$1:$1,0)>0,"FOUND"),"NOT FOUND")) -> FOUND
A22: Client_Cutoff | B22: CLIENT_DEADLINE_HHMM | C22: HHMM | E22: =IF($B22="","Using default",IFERROR(IF(MATCH($B22,Raw_Fund_Import!$1:$1,0)>0,"FOUND"),"NOT FOUND")) -> FOUND
A23: NAV_Deadline | B23: NAV_DEADLINE_HHMM | C23: HHMM | E23: =IF($B23="","Using default",IFERROR(IF(MATCH($B23,Raw_Fund_Import!$1:$1,0)>0,"FOUND"),"NOT FOUND")) -> FOUND
A24: Signoff_Model | B24: SIGNOFF_TYPE | E24: =IF($B24="","Using default",IFERROR(IF(MATCH($B24,Raw_Fund_Import!$1:$1,0)>0,"FOUND"),"NOT FOUND")) -> FOUND
A25: Cutoff_Data_Quality | D25: Confirmed | E25: =IF($B25="","Using default",IFERROR(IF(MATCH($B25,Raw_Fund_Import!$1:$1,0)>0,"FOUND"),"NOT FOUND")) -> Using default
A28: TRANSFORM CODES
A29: (blank) | B29: Copy the value as-is.
A30: HHMM | B30: Whole number like 430 or 1230 becomes a real time. Use for cut-offs held as integers.
A31: TIME_TEXT | B31: Text like "04:30" becomes a real time.
A32: DEC_HR | B32: Decimal hours like 4.5 becomes a real time.
A33: YN | B33: Y/N/Yes/True becomes 1, anything else 0. Use for the four product flags.
A34: YESNO | B34: Y/N/Yes/True becomes the text "Yes", anything else "No". Use for Strategic_Client and the three Has_*_Process flags.

Sheet Dim_Fund_Staging
A1: Fund_ID | B1: Fund_Name | C1: Client_ID | D1: Client_Name | E1: Strategic_Client | F1: Team_ID | G1: Default_Analyst_Name | H1: Weightage | I1: ETD | J1: OTC_nonCFD | K1: OTC_CFD | L1: PFC | M1: EUC | N1: Has_Custody_Process | O1: Has_TA_Process | P1: Has_Broker_Process | Q1: Custody_Cutoff | R1: TA_Cutoff | S1: Broker_ETA | T1: Pricing_Cutoff | U1: Client_Cutoff | V1: NAV_Deadline | W1: Signoff_Model | X1: Cutoff_Data_Quality | Y1: Row_OK | AA1: Check every row reads OK, then copy A2:X201 and Paste Special > Values into Dim_Fund cell A2.
A2: =IF(Raw_Fund_Import!$A2="","",IF(Mapping!$B$2="",Mapping!$D$2,IF(OR(UPPER(INDEX(Raw_Fund_Import!$A:$BZ,ROW(),MATCH(Mapping!$B$2,Raw_Fund_Import!$1:$1,0))&"")="NA",UPPER(INDEX(Raw_Fund_Import!$A:$BZ,ROW(),MATCH(Mapping!$B$2,Raw_Fund_Import!$1:$1,0))&"")="N/A",INDEX(Raw_Fund_Import!$A:$BZ,ROW(),MATCH(Mapping!$B$2,Raw_Fund_Import!$1:$1,0))&""="-",INDEX(Raw_Fund_Import!$A:$BZ,ROW(),MATCH(Mapping!$B$2,Raw_Fund_Import!$1:$1,0))&""=""),Mapping!$D$2,IFERROR(IF(Mapping!$C$2="HHMM",TIME(INT(INDEX(Raw_Fund_Import!$A:$BZ,ROW(),MATCH(Mapping!$B$2,Raw_Fund_Import!$1:$1,0))/100),MOD(INDEX(Raw_Fund_Import!$A:$BZ,ROW(),MATCH(Mapping!$B$2,Raw_Fund_Import!$1:$1,0)),100),0),IF(Mapping!$C$2="TIME_TEXT",TIMEVALUE(INDEX(Raw_Fund_Import!$A:$BZ,ROW(),MATCH(Mapping!$B$2,Raw_Fund_Import!$1:$1,0))),IF(Mapping!$C$2="DEC_HR",INDEX(Raw_Fund_Import!$A:$BZ,ROW(),MATCH(Mapping!$B$2,Raw_Fund_Import!$1:$1,0))/24,IF(Mapping!$C$2="YN",IF(OR(UPPER(LEFT(INDEX(Raw_Fund_Import!$A:$BZ,ROW(),MATCH(Mapping!$B$2,Raw_Fund_Import!$1:$1,0))&"",1))="Y",INDEX(Raw_Fund_Import!$A:$BZ,ROW(),MATCH(Mapping!$B$2,Raw_Fund_Import!$1:$1,0))&""="1",UPPER(INDEX(Raw_Fund_Import!$A:$BZ,ROW(),MATCH(Mapping!$B$2,Raw_Fund_Import!$1:$1,0))&"")="TRUE"),1,0),IF(Mapping!$C$2="YESNO",IF(OR(UPPER(LEFT(INDEX(Raw_Fund_Import!$A:$BZ,ROW(),MATCH(Mapping!$B$2,Raw_Fund_Import!$1:$1,0))&"",1))="Y",INDEX(Raw_Fund_Import!$A:$BZ,ROW(),MATCH(Mapping!$B$2,Raw_Fund_Import!$1:$1,0))&""="1",UPPER(INDEX(Raw_Fund_Import!$A:$BZ,ROW(),MATCH(Mapping!$B$2,Raw_Fund_Import!$1:$1,0))&"")="TRUE"),"Yes","No"),INDEX(Raw_Fund_Import!$A:$BZ,ROW(),MATCH(Mapping!$B$2,Raw_Fund_Import!$1:$1,0))))))),Mapping!$D$2)))) -> FD-1001 | B2: =IF(Raw_Fund_Import!$A2="","",IF(Mapping!$B$3="",Mapping!$D$3,IF(OR(UPPER(INDEX(Raw_Fund_Import!$A:$BZ,ROW(),MATCH(Mapping!$B$3,Raw_Fund_Import!$1:$1,0))&"")="NA",UPPER(INDEX(Raw_Fund_Import!$A:$BZ,ROW(),MATCH(Mapping!$B$3,Raw_Fund_Import!$1:$1,0))&"")="N/A",INDEX(Raw_Fund_Import!$A:$BZ,ROW(),MATCH(Mapping!$B$3,Raw_Fund_Import!$1:$1,0))&""="-",INDEX(Raw_Fund_Import!$A:$BZ,ROW(),MATCH(Mapping!$B$3,Raw_Fund_Import!$1:$1,0))&""=""),Mapping!$D$3,IFERROR(IF(Mapping!$C$3="HHMM",TIME(INT(INDEX(Raw_Fund_Import!$A:$BZ,ROW(),MATCH(Mapping!$B$3,Raw_Fund_Import!$1:$1,0))/100),MOD(INDEX(Raw_Fund_Import!$A:$BZ,ROW(),MATCH(Mapping!$B$3,Raw_Fund_Import!$1:$1,0)),100),0),IF(Mapping!$C$3="TIME_TEXT",TIMEVALUE(INDEX(Raw_Fund_Import!$A:$BZ,ROW(),MATCH(Mapping!$B$3,Raw_Fund_Import!$1:$1,0))),IF(Mapping!$C$3="DEC_HR",INDEX(Raw_Fund_Import!$A:$BZ,ROW(),MATCH(Mapping!$B$3,Raw_Fund_Import!$1:$1,0))/24,IF(Mapping!$C$3="YN",IF(OR(UPPER(LEFT(INDEX(Raw_Fund_Import!$A:$BZ,ROW(),MATCH(Mapping!$B$3,Raw_Fund_Import!$1:$1,0))&"",1))="Y",INDEX(Raw_Fund_Import!$A:$BZ,ROW(),MATCH(Mapping!$B$3,Raw_Fund_Import!$1:$1,0))&""="1",UPPER(INDEX(Raw_Fund_Import!$A:$BZ,ROW(),MATCH(Mapping!$B$3,Raw_Fund_Import!$1:$1,0))&"")="TRUE"),1,0),IF(Mapping!$C$3="YESNO",IF(OR(UPPER(LEFT(INDEX(Raw_Fund_Import!$A:$BZ,ROW(),MATCH(Mapping!$B$3,Raw_Fund_Import!$1:$1,0))&"",1))="Y",INDEX(Raw_Fund_Import!$A:$BZ,ROW(),MATCH(Mapping!$B$3,Raw_Fund_Import!$1:$1,0))&""="1",UPPER(INDEX(Raw_Fund_Import!$A:$BZ,ROW(),MATCH(Mapping!$B$3,Raw_Fund_Import!$1:$1,0))&"")="TRUE"),"Yes","No"),INDEX(Raw_Fund_Import!$A:$BZ,ROW(),MATCH(Mapping!$B$3,Raw_Fund_Import!$1:$1,0))))))),Mapping!$D$3)))) -> Sample Fund 1001 | C2: =IF(Raw_Fund_Import!$A2="","",IF(Mapping!$B$4="",Mapping!$D$4,IF(OR(UPPER(INDEX(Raw_Fund_Import!$A:$BZ,ROW(),MATCH(Mapping!$B$4,Raw_Fund_Import!$1:$1,0))&"")="NA",UPPER(INDEX(Raw_Fund_Import!$A:$BZ,ROW(),MATCH(Mapping!$B$4,Raw_Fund_Import!$1:$1,0))&"")="N/A",INDEX(Raw_Fund_Import!$A:$BZ,ROW(),MATCH(Mapping!$B$4,Raw_Fund_Import!$1:$1,0))&""="-",INDEX(Raw_Fund_Import!$A:$BZ,ROW(),MATCH(Mapping!$B$4,Raw_Fund_Import!$1:$1,0))&""=""),Mapping!$D$4,IFERROR(IF(Mapping!$C$4="HHMM",TIME(INT(INDEX(Raw_Fund_Import!$A:$BZ,ROW(),MATCH(Mapping!$B$4,Raw_Fund_Import!$1:$1,0))/100),MOD(INDEX(Raw_Fund_Import!$A:$BZ,ROW(),MATCH(Mapping!$B$4,Raw_Fund_Import!$1:$1,0)),100),0),IF(Mapping!$C$4="TIME_TEXT",TIMEVALUE(INDEX(Raw_Fund_Import!$A:$BZ,ROW(),MATCH(Mapping!$B$4,Raw_Fund_Import!$1:$1,0))),IF(Mapping!$C$4="DEC_HR",INDEX(Raw_Fund_Import!$A:$BZ,ROW(),MATCH(Mapping!$B$4,Raw_Fund_Import!$1:$1,0))/24,IF(Mapping!$C$4="YN",IF(OR(UPPER(LEFT(INDEX(Raw_Fund_Import!$A:$BZ,ROW(),MATCH(Mapping!$B$4,Raw_Fund_Import!$1:$1,0))&"",1))="Y",INDEX(Raw_Fund_Import!$A:$BZ,ROW(),MATCH(Mapping!$B$4,Raw_Fund_Import!$1:$1,0))&""="1",UPPER(INDEX(Raw_Fund_Import!$A:$BZ,ROW(),MATCH(Mapping!$B$4,Raw_Fund_Import!$1:$1,0))&"")="TRUE"),1,0),IF(Mapping!$C$4="YESNO",IF(OR(UPPER(LEFT(INDEX(Raw_Fund_Import!$A:$BZ,ROW(),MATCH(Mapping!$B$4,Raw_Fund_Import!$1:$1,0))&"",1))="Y",INDEX(Raw_Fund_Import!$A:$BZ,ROW(),MATCH(Mapping!$B$4,Raw_Fund_Import!$1:$1,0))&""="1",UPPER(INDEX(Raw_Fund_Import!$A:$BZ,ROW(),MATCH(Mapping!$B$4,Raw_Fund_Import!$1:$1,0))&"")="TRUE"),"Yes","No"),INDEX(Raw_Fund_Import!$A:$BZ,ROW(),MATCH(Mapping!$B$4,Raw_Fund_Import!$1:$1,0))))))),Mapping!$D$4)))) -> CL01 | D2: =IF(Raw_Fund_Import!$A2="","",IF(Mapping!$B$5="",Mapping!$D$5,IF(OR(UPPER(INDEX(Raw_Fund_Import!$A:$BZ,ROW(),MATCH(Mapping!$B$5,Raw_Fund_Import!$1:$1,0))&"")="NA",UPPER(INDEX(Raw_Fund_Import!$A:$BZ,ROW(),MATCH(Mapping!$B$5,Raw_Fund_Import!$1:$1,0))&"")="N/A",INDEX(Raw_Fund_Import!$A:$BZ,ROW(),MATCH(Mapping!$B$5,Raw_Fund_Import!$1:$1,0))&""="-",INDEX(Raw_Fund_Import!$A:$BZ,ROW(),MATCH(Mapping!$B$5,Raw_Fund_Import!$1:$1,0))&""=""),Mapping!$D$5,IFERROR(IF(Mapping!$C$5="HHMM",TIME(INT(INDEX(Raw_Fund_Import!$A:$BZ,ROW(),MATCH(Mapping!$B$5,Raw_Fund_Import!$1:$1,0))/100),MOD(INDEX(Raw_Fund_Import!$A:$BZ,ROW(),MATCH(Mapping!$B$5,Raw_Fund_Import!$1:$1,0)),100),0),IF(Mapping!$C$5="TIME_TEXT",TIMEVALUE(INDEX(Raw_Fund_Import!$A:$BZ,ROW(),MATCH(Mapping!$B$5,Raw_Fund_Import!$1:$1,0))),IF(Mapping!$C$5="DEC_HR",INDEX(Raw_Fund_Import!$A:$BZ,ROW(),MATCH(Mapping!$B$5,Raw_Fund_Import!$1:$1,0))/24,IF(Mapping!$C$5="YN",IF(OR(UPPER(LEFT(INDEX(Raw_Fund_Import!$A:$BZ,ROW(),MATCH(Mapping!$B$5,Raw_Fund_Import!$1:$1,0))&"",1))="Y",INDEX(Raw_Fund_Import!$A:$BZ,ROW(),MATCH(Mapping!$B$5,Raw_Fund_Import!$1:$1,0))&""="1",UPPER(INDEX(Raw_Fund_Import!$A:$BZ,ROW(),MATCH(Mapping!$B$5,Raw_Fund_Import!$1:$1,0))&"")="TRUE"),1,0),IF(Mapping!$C$5="YESNO",IF(OR(UPPER(LEFT(INDEX(Raw_Fund_Import!$A:$BZ,ROW(),MATCH(Mapping!$B$5,Raw_Fund_Import!$1:$1,0))&"",1))="Y",INDEX(Raw_Fund_Import!$A:$BZ,ROW(),MATCH(Mapping!$B$5,Raw_Fund_Import!$1:$1,0))&""="1",UPPER(INDEX(Raw_Fund_Import!$A:$BZ,ROW(),MATCH(Mapping!$B$5,Raw_Fund_Import!$1:$1,0))&"")="TRUE"),"Yes","No"),INDEX(Raw_Fund_Import!$A:$BZ,ROW(),MATCH(Mapping!$B$5,Raw_Fund_Import!$1:$1,0))))))),Mapping!$D$5)))) -> Meridian Pensions | E2: =IF(Raw_Fund_Import!$A2="","",IF(Mapping!$B$6="",Mapping!$D$6,IF(OR(UPPER(INDEX(Raw_Fund_Import!$A:$BZ,ROW(),MATCH(Mapping!$B$6,Raw_Fund_Import!$1:$1,0))&"")="NA",UPPER(INDEX(Raw_Fund_Import!$A:$BZ,ROW(),MATCH(Mapping!$B$6,Raw_Fund_Import!$1:$1,0))&"")="N/A",INDEX(Raw_Fund_Import!$A:$BZ,ROW(),MATCH(Mapping!$B$6,Raw_Fund_Import!$1:$1,0))&""="-",INDEX(Raw_Fund_Import!$A:$BZ,ROW(),MATCH(Mapping!$B$6,Raw_Fund_Import!$1:$1,0))&""=""),Mapping!$D$6,IFERROR(IF(Mapping!$C$6="HHMM",TIME(INT(INDEX(Raw_Fund_Import!$A:$BZ,ROW(),MATCH(Mapping!$B$6,Raw_Fund_Import!$1:$1,0))/100),MOD(INDEX(Raw_Fund_Import!$A:$BZ,ROW(),MATCH(Mapping!$B$6,Raw_Fund_Import!$1:$1,0)),100),0),IF(Mapping!$C$6="TIME_TEXT",TIMEVALUE(INDEX(Raw_Fund_Import!$A:$BZ,ROW(),MATCH(Mapping!$B$6,Raw_Fund_Import!$1:$1,0))),IF(Mapping!$C$6="DEC_HR",INDEX(Raw_Fund_Import!$A:$BZ,ROW(),MATCH(Mapping!$B$6,Raw_Fund_Import!$1:$1,0))/24,IF(Mapping!$C$6="YN",IF(OR(UPPER(LEFT(INDEX(Raw_Fund_Import!$A:$BZ,ROW(),MATCH(Mapping!$B$6,Raw_Fund_Import!$1:$1,0))&"",1))="Y",INDEX(Raw_Fund_Import!$A:$BZ,ROW(),MATCH(Mapping!$B$6,Raw_Fund_Import!$1:$1,0))&""="1",UPPER(INDEX(Raw_Fund_Import!$A:$BZ,ROW(),MATCH(Mapping!$B$6,Raw_Fund_Import!$1:$1,0))&"")="TRUE"),1,0),IF(Mapping!$C$6="YESNO",IF(OR(UPPER(LEFT(INDEX(Raw_Fund_Import!$A:$BZ,ROW(),MATCH(Mapping!$B$6,Raw_Fund_Import!$1:$1,0))&"",1))="Y",INDEX(Raw_Fund_Import!$A:$BZ,ROW(),MATCH(Mapping!$B$6,Raw_Fund_Import!$1:$1,0))&""="1",UPPER(INDEX(Raw_Fund_Import!$A:$BZ,ROW(),MATCH(Mapping!$B$6,Raw_Fund_Import!$1:$1,0))&"")="TRUE"),"Yes","No"),INDEX(Raw_Fund_Import!$A:$BZ,ROW(),MATCH(Mapping!$B$6,Raw_Fund_Import!$1:$1,0))))))),Mapping!$D$6)))) -> Yes | F2: =IF(Raw_Fund_Import!$A2="","",IF(Mapping!$B$7="",Mapping!$D$7,IF(OR(UPPER(INDEX(Raw_Fund_Import!$A:$BZ,ROW(),MATCH(Mapping!$B$7,Raw_Fund_Import!$1:$1,0))&"")="NA",UPPER(INDEX(Raw_Fund_Import!$A:$BZ,ROW(),MATCH(Mapping!$B$7,Raw_Fund_Import!$1:$1,0))&"")="N/A",INDEX(Raw_Fund_Import!$A:$BZ,ROW(),MATCH(Mapping!$B$7,Raw_Fund_Import!$1:$1,0))&""="-",INDEX(Raw_Fund_Import!$A:$BZ,ROW(),MATCH(Mapping!$B$7,Raw_Fund_Import!$1:$1,0))&""=""),Mapping!$D$7,IFERROR(IF(Mapping!$C$7="HHMM",TIME(INT(INDEX(Raw_Fund_Import!$A:$BZ,ROW(),MATCH(Mapping!$B$7,Raw_Fund_Import!$1:$1,0))/100),MOD(INDEX(Raw_Fund_Import!$A:$BZ,ROW(),MATCH(Mapping!$B$7,Raw_Fund_Import!$1:$1,0)),100),0),IF(Mapping!$C$7="TIME_TEXT",TIMEVALUE(INDEX(Raw_Fund_Import!$A:$BZ,ROW(),MATCH(Mapping!$B$7,Raw_Fund_Import!$1:$1,0))),IF(Mapping!$C$7="DEC_HR",INDEX(Raw_Fund_Import!$A:$BZ,ROW(),MATCH(Mapping!$B$7,Raw_Fund_Import!$1:$1,0))/24,IF(Mapping!$C$7="YN",IF(OR(UPPER(LEFT(INDEX(Raw_Fund_Import!$A:$BZ,ROW(),MATCH(Mapping!$B$7,Raw_Fund_Import!$1:$1,0))&"",1))="Y",INDEX(Raw_Fund_Import!$A:$BZ,ROW(),MATCH(Mapping!$B$7,Raw_Fund_Import!$1:$1,0))&""="1",UPPER(INDEX(Raw_Fund_Import!$A:$BZ,ROW(),MATCH(Mapping!$B$7,Raw_Fund_Import!$1:$1,0))&"")="TRUE"),1,0),IF(Mapping!$C$7="YESNO",IF(OR(UPPER(LEFT(INDEX(Raw_Fund_Import!$A:$BZ,ROW(),MATCH(Mapping!$B$7,Raw_Fund_Import!$1:$1,0))&"",1))="Y",INDEX(Raw_Fund_Import!$A:$BZ,ROW(),MATCH(Mapping!$B$7,Raw_Fund_Import!$1:$1,0))&""="1",UPPER(INDEX(Raw_Fund_Import!$A:$BZ,ROW(),MATCH(Mapping!$B$7,Raw_Fund_Import!$1:$1,0))&"")="TRUE"),"Yes","No"),INDEX(Raw_Fund_Import!$A:$BZ,ROW(),MATCH(Mapping!$B$7,Raw_Fund_Import!$1:$1,0))))))),Mapping!$D$7)))) -> TM01 | G2: =IF(Raw_Fund_Import!$A2="","",IF(Mapping!$B$8="",Mapping!$D$8,IF(OR(UPPER(INDEX(Raw_Fund_Import!$A:$BZ,ROW(),MATCH(Mapping!$B$8,Raw_Fund_Import!$1:$1,0))&"")="NA",UPPER(INDEX(Raw_Fund_Import!$A:$BZ,ROW(),MATCH(Mapping!$B$8,Raw_Fund_Import!$1:$1,0))&"")="N/A",INDEX(Raw_Fund_Import!$A:$BZ,ROW(),MATCH(Mapping!$B$8,Raw_Fund_Import!$1:$1,0))&""="-",INDEX(Raw_Fund_Import!$A:$BZ,ROW(),MATCH(Mapping!$B$8,Raw_Fund_Import!$1:$1,0))&""=""),Mapping!$D$8,IFERROR(IF(Mapping!$C$8="HHMM",TIME(INT(INDEX(Raw_Fund_Import!$A:$BZ,ROW(),MATCH(Mapping!$B$8,Raw_Fund_Import!$1:$1,0))/100),MOD(INDEX(Raw_Fund_Import!$A:$BZ,ROW(),MATCH(Mapping!$B$8,Raw_Fund_Import!$1:$1,0)),100),0),IF(Mapping!$C$8="TIME_TEXT",TIMEVALUE(INDEX(Raw_Fund_Import!$A:$BZ,ROW(),MATCH(Mapping!$B$8,Raw_Fund_Import!$1:$1,0))),IF(Mapping!$C$8="DEC_HR",INDEX(Raw_Fund_Import!$A:$BZ,ROW(),MATCH(Mapping!$B$8,Raw_Fund_Import!$1:$1,0))/24,IF(Mapping!$C$8="YN",IF(OR(UPPER(LEFT(INDEX(Raw_Fund_Import!$A:$BZ,ROW(),MATCH(Mapping!$B$8,Raw_Fund_Import!$1:$1,0))&"",1))="Y",INDEX(Raw_Fund_Import!$A:$BZ,ROW(),MATCH(Mapping!$B$8,Raw_Fund_Import!$1:$1,0))&""="1",UPPER(INDEX(Raw_Fund_Import!$A:$BZ,ROW(),MATCH(Mapping!$B$8,Raw_Fund_Import!$1:$1,0))&"")="TRUE"),1,0),IF(Mapping!$C$8="YESNO",IF(OR(UPPER(LEFT(INDEX(Raw_Fund_Import!$A:$BZ,ROW(),MATCH(Mapping!$B$8,Raw_Fund_Import!$1:$1,0))&"",1))="Y",INDEX(Raw_Fund_Import!$A:$BZ,ROW(),MATCH(Mapping!$B$8,Raw_Fund_Import!$1:$1,0))&""="1",UPPER(INDEX(Raw_Fund_Import!$A:$BZ,ROW(),MATCH(Mapping!$B$8,Raw_Fund_Import!$1:$1,0))&"")="TRUE"),"Yes","No"),INDEX(Raw_Fund_Import!$A:$BZ,ROW(),MATCH(Mapping!$B$8,Raw_Fund_Import!$1:$1,0))))))),Mapping!$D$8)))) -> TM01-A1 | H2: =IF(Raw_Fund_Import!$A2="","",IF(Mapping!$B$9="",Mapping!$D$9,IF(OR(UPPER(INDEX(Raw_Fund_Import!$A:$BZ,ROW(),MATCH(Mapping!$B$9,Raw_Fund_Import!$1:$1,0))&"")="NA",UPPER(INDEX(Raw_Fund_Import!$A:$BZ,ROW(),MATCH(Mapping!$B$9,Raw_Fund_Import!$1:$1,0))&"")="N/A",INDEX(Raw_Fund_Import!$A:$BZ,ROW(),MATCH(Mapping!$B$9,Raw_Fund_Import!$1:$1,0))&""="-",INDEX(Raw_Fund_Import!$A:$BZ,ROW(),MATCH(Mapping!$B$9,Raw_Fund_Import!$1:$1,0))&""=""),Mapping!$D$9,IFERROR(IF(Mapping!$C$9="HHMM",TIME(INT(INDEX(Raw_Fund_Import!$A:$BZ,ROW(),MATCH(Mapping!$B$9,Raw_Fund_Import!$1:$1,0))/100),MOD(INDEX(Raw_Fund_Import!$A:$BZ,ROW(),MATCH(Mapping!$B$9,Raw_Fund_Import!$1:$1,0)),100),0),IF(Mapping!$C$9="TIME_TEXT",TIMEVALUE(INDEX(Raw_Fund_Import!$A:$BZ,ROW(),MATCH(Mapping!$B$9,Raw_Fund_Import!$1:$1,0))),IF(Mapping!$C$9="DEC_HR",INDEX(Raw_Fund_Import!$A:$BZ,ROW(),MATCH(Mapping!$B$9,Raw_Fund_Import!$1:$1,0))/24,IF(Mapping!$C$9="YN",IF(OR(UPPER(LEFT(INDEX(Raw_Fund_Import!$A:$BZ,ROW(),MATCH(Mapping!$B$9,Raw_Fund_Import!$1:$1,0))&"",1))="Y",INDEX(Raw_Fund_Import!$A:$BZ,ROW(),MATCH(Mapping!$B$9,Raw_Fund_Import!$1:$1,0))&""="1",UPPER(INDEX(Raw_Fund_Import!$A:$BZ,ROW(),MATCH(Mapping!$B$9,Raw_Fund_Import!$1:$1,0))&"")="TRUE"),1,0),IF(Mapping!$C$9="YESNO",IF(OR(UPPER(LEFT(INDEX(Raw_Fund_Import!$A:$BZ,ROW(),MATCH(Mapping!$B$9,Raw_Fund_Import!$1:$1,0))&"",1))="Y",INDEX(Raw_Fund_Import!$A:$BZ,ROW(),MATCH(Mapping!$B$9,Raw_Fund_Import!$1:$1,0))&""="1",UPPER(INDEX(Raw_Fund_Import!$A:$BZ,ROW(),MATCH(Mapping!$B$9,Raw_Fund_Import!$1:$1,0))&"")="TRUE"),"Yes","No"),INDEX(Raw_Fund_Import!$A:$BZ,ROW(),MATCH(Mapping!$B$9,Raw_Fund_Import!$1:$1,0))))))),Mapping!$D$9)))) -> 2.152 | I2: =IF(Raw_Fund_Import!$A2="","",IF(Mapping!$B$10="",Mapping!$D$10,IF(OR(UPPER(INDEX(Raw_Fund_Import!$A:$BZ,ROW(),MATCH(Mapping!$B$10,Raw_Fund_Import!$1:$1,0))&"")="NA",UPPER(INDEX(Raw_Fund_Import!$A:$BZ,ROW(),MATCH(Mapping!$B$10,Raw_Fund_Import!$1:$1,0))&"")="N/A",INDEX(Raw_Fund_Import!$A:$BZ,ROW(),MATCH(Mapping!$B$10,Raw_Fund_Import!$1:$1,0))&""="-",INDEX(Raw_Fund_Import!$A:$BZ,ROW(),MATCH(Mapping!$B$10,Raw_Fund_Import!$1:$1,0))&""=""),Mapping!$D$10,IFERROR(IF(Mapping!$C$10="HHMM",TIME(INT(INDEX(Raw_Fund_Import!$A:$BZ,ROW(),MATCH(Mapping!$B$10,Raw_Fund_Import!$1:$1,0))/100),MOD(INDEX(Raw_Fund_Import!$A:$BZ,ROW(),MATCH(Mapping!$B$10,Raw_Fund_Import!$1:$1,0)),100),0),IF(Mapping!$C$10="TIME_TEXT",TIMEVALUE(INDEX(Raw_Fund_Import!$A:$BZ,ROW(),MATCH(Mapping!$B$10,Raw_Fund_Import!$1:$1,0))),IF(Mapping!$C$10="DEC_HR",INDEX(Raw_Fund_Import!$A:$BZ,ROW(),MATCH(Mapping!$B$10,Raw_Fund_Import!$1:$1,0))/24,IF(Mapping!$C$10="YN",IF(OR(UPPER(LEFT(INDEX(Raw_Fund_Import!$A:$BZ,ROW(),MATCH(Mapping!$B$10,Raw_Fund_Import!$1:$1,0))&"",1))="Y",INDEX(Raw_Fund_Import!$A:$BZ,ROW(),MATCH(Mapping!$B$10,Raw_Fund_Import!$1:$1,0))&""="1",UPPER(INDEX(Raw_Fund_Import!$A:$BZ,ROW(),MATCH(Mapping!$B$10,Raw_Fund_Import!$1:$1,0))&"")="TRUE"),1,0),IF(Mapping!$C$10="YESNO",IF(OR(UPPER(LEFT(INDEX(Raw_Fund_Import!$A:$BZ,ROW(),MATCH(Mapping!$B$10,Raw_Fund_Import!$1:$1,0))&"",1))="Y",INDEX(Raw_Fund_Import!$A:$BZ,ROW(),MATCH(Mapping!$B$10,Raw_Fund_Import!$1:$1,0))&""="1",UPPER(INDEX(Raw_Fund_Import!$A:$BZ,ROW(),MATCH(Mapping!$B$10,Raw_Fund_Import!$1:$1,0))&"")="TRUE"),"Yes","No"),INDEX(Raw_Fund_Import!$A:$BZ,ROW(),MATCH(Mapping!$B$10,Raw_Fund_Import!$1:$1,0))))))),Mapping!$D$10)))) -> 1 | J2: =IF(Raw_Fund_Import!$A2="","",IF(Mapping!$B$11="",Mapping!$D$11,IF(OR(UPPER(INDEX(Raw_Fund_Import!$A:$BZ,ROW(),MATCH(Mapping!$B$11,Raw_Fund_Import!$1:$1,0))&"")="NA",UPPER(INDEX(Raw_Fund_Import!$A:$BZ,ROW(),MATCH(Mapping!$B$11,Raw_Fund_Import!$1:$1,0))&"")="N/A",INDEX(Raw_Fund_Import!$A:$BZ,ROW(),MATCH(Mapping!$B$11,Raw_Fund_Import!$1:$1,0))&""="-",INDEX(Raw_Fund_Import!$A:$BZ,ROW(),MATCH(Mapping!$B$11,Raw_Fund_Import!$1:$1,0))&""=""),Mapping!$D$11,IFERROR(IF(Mapping!$C$11="HHMM",TIME(INT(INDEX(Raw_Fund_Import!$A:$BZ,ROW(),MATCH(Mapping!$B$11,Raw_Fund_Import!$1:$1,0))/100),MOD(INDEX(Raw_Fund_Import!$A:$BZ,ROW(),MATCH(Mapping!$B$11,Raw_Fund_Import!$1:$1,0)),100),0),IF(Mapping!$C$11="TIME_TEXT",TIMEVALUE(INDEX(Raw_Fund_Import!$A:$BZ,ROW(),MATCH(Mapping!$B$11,Raw_Fund_Import!$1:$1,0))),IF(Mapping!$C$11="DEC_HR",INDEX(Raw_Fund_Import!$A:$BZ,ROW(),MATCH(Mapping!$B$11,Raw_Fund_Import!$1:$1,0))/24,IF(Mapping!$C$11="YN",IF(OR(UPPER(LEFT(INDEX(Raw_Fund_Import!$A:$BZ,ROW(),MATCH(Mapping!$B$11,Raw_Fund_Import!$1:$1,0))&"",1))="Y",INDEX(Raw_Fund_Import!$A:$BZ,ROW(),MATCH(Mapping!$B$11,Raw_Fund_Import!$1:$1,0))&""="1",UPPER(INDEX(Raw_Fund_Import!$A:$BZ,ROW(),MATCH(Mapping!$B$11,Raw_Fund_Import!$1:$1,0))&"")="TRUE"),1,0),IF(Mapping!$C$11="YESNO",IF(OR(UPPER(LEFT(INDEX(Raw_Fund_Import!$A:$BZ,ROW(),MATCH(Mapping!$B$11,Raw_Fund_Import!$1:$1,0))&"",1))="Y",INDEX(Raw_Fund_Import!$A:$BZ,ROW(),MATCH(Mapping!$B$11,Raw_Fund_Import!$1:$1,0))&""="1",UPPER(INDEX(Raw_Fund_Import!$A:$BZ,ROW(),MATCH(Mapping!$B$11,Raw_Fund_Import!$1:$1,0))&"")="TRUE"),"Yes","No"),INDEX(Raw_Fund_Import!$A:$BZ,ROW(),MATCH(Mapping!$B$11,Raw_Fund_Import!$1:$1,0))))))),Mapping!$D$11)))) -> 0 | K2: =IF(Raw_Fund_Import!$A2="","",IF(Mapping!$B$12="",Mapping!$D$12,IF(OR(UPPER(INDEX(Raw_Fund_Import!$A:$BZ,ROW(),MATCH(Mapping!$B$12,Raw_Fund_Import!$1:$1,0))&"")="NA",UPPER(INDEX(Raw_Fund_Import!$A:$BZ,ROW(),MATCH(Mapping!$B$12,Raw_Fund_Import!$1:$1,0))&"")="N/A",INDEX(Raw_Fund_Import!$A:$BZ,ROW(),MATCH(Mapping!$B$12,Raw_Fund_Import!$1:$1,0))&""="-",INDEX(Raw_Fund_Import!$A:$BZ,ROW(),MATCH(Mapping!$B$12,Raw_Fund_Import!$1:$1,0))&""=""),Mapping!$D$12,IFERROR(IF(Mapping!$C$12="HHMM",TIME(INT(INDEX(Raw_Fund_Import!$A:$BZ,ROW(),MATCH(Mapping!$B$12,Raw_Fund_Import!$1:$1,0))/100),MOD(INDEX(Raw_Fund_Import!$A:$BZ,ROW(),MATCH(Mapping!$B$12,Raw_Fund_Import!$1:$1,0)),100),0),IF(Mapping!$C$12="TIME_TEXT",TIMEVALUE(INDEX(Raw_Fund_Import!$A:$BZ,ROW(),MATCH(Mapping!$B$12,Raw_Fund_Import!$1:$1,0))),IF(Mapping!$C$12="DEC_HR",INDEX(Raw_Fund_Import!$A:$BZ,ROW(),MATCH(Mapping!$B$12,Raw_Fund_Import!$1:$1,0))/24,IF(Mapping!$C$12="YN",IF(OR(UPPER(LEFT(INDEX(Raw_Fund_Import!$A:$BZ,ROW(),MATCH(Mapping!$B$12,Raw_Fund_Import!$1:$1,0))&"",1))="Y",INDEX(Raw_Fund_Import!$A:$BZ,ROW(),MATCH(Mapping!$B$12,Raw_Fund_Import!$1:$1,0))&""="1",UPPER(INDEX(Raw_Fund_Import!$A:$BZ,ROW(),MATCH(Mapping!$B$12,Raw_Fund_Import!$1:$1,0))&"")="TRUE"),1,0),IF(Mapping!$C$12="YESNO",IF(OR(UPPER(LEFT(INDEX(Raw_Fund_Import!$A:$BZ,ROW(),MATCH(Mapping!$B$12,Raw_Fund_Import!$1:$1,0))&"",1))="Y",INDEX(Raw_Fund_Import!$A:$BZ,ROW(),MATCH(Mapping!$B$12,Raw_Fund_Import!$1:$1,0))&""="1",UPPER(INDEX(Raw_Fund_Import!$A:$BZ,ROW(),MATCH(Mapping!$B$12,Raw_Fund_Import!$1:$1,0))&"")="TRUE"),"Yes","No"),INDEX(Raw_Fund_Import!$A:$BZ,ROW(),MATCH(Mapping!$B$12,Raw_Fund_Import!$1:$1,0))))))),Mapping!$D$12)))) -> 0 | L2: =IF(Raw_Fund_Import!$A2="","",IF(Mapping!$B$13="",Mapping!$D$13,IF(OR(UPPER(INDEX(Raw_Fund_Import!$A:$BZ,ROW(),MATCH(Mapping!$B$13,Raw_Fund_Import!$1:$1,0))&"")="NA",UPPER(INDEX(Raw_Fund_Import!$A:$BZ,ROW(),MATCH(Mapping!$B$13,Raw_Fund_Import!$1:$1,0))&"")="N/A",INDEX(Raw_Fund_Import!$A:$BZ,ROW(),MATCH(Mapping!$B$13,Raw_Fund_Import!$1:$1,0))&""="-",INDEX(Raw_Fund_Import!$A:$BZ,ROW(),MATCH(Mapping!$B$13,Raw_Fund_Import!$1:$1,0))&""=""),Mapping!$D$13,IFERROR(IF(Mapping!$C$13="HHMM",TIME(INT(INDEX(Raw_Fund_Import!$A:$BZ,ROW(),MATCH(Mapping!$B$13,Raw_Fund_Import!$1:$1,0))/100),MOD(INDEX(Raw_Fund_Import!$A:$BZ,ROW(),MATCH(Mapping!$B$13,Raw_Fund_Import!$1:$1,0)),100),0),IF(Mapping!$C$13="TIME_TEXT",TIMEVALUE(INDEX(Raw_Fund_Import!$A:$BZ,ROW(),MATCH(Mapping!$B$13,Raw_Fund_Import!$1:$1,0))),IF(Mapping!$C$13="DEC_HR",INDEX(Raw_Fund_Import!$A:$BZ,ROW(),MATCH(Mapping!$B$13,Raw_Fund_Import!$1:$1,0))/24,IF(Mapping!$C$13="YN",IF(OR(UPPER(LEFT(INDEX(Raw_Fund_Import!$A:$BZ,ROW(),MATCH(Mapping!$B$13,Raw_Fund_Import!$1:$1,0))&"",1))="Y",INDEX(Raw_Fund_Import!$A:$BZ,ROW(),MATCH(Mapping!$B$13,Raw_Fund_Import!$1:$1,0))&""="1",UPPER(INDEX(Raw_Fund_Import!$A:$BZ,ROW(),MATCH(Mapping!$B$13,Raw_Fund_Import!$1:$1,0))&"")="TRUE"),1,0),IF(Mapping!$C$13="YESNO",IF(OR(UPPER(LEFT(INDEX(Raw_Fund_Import!$A:$BZ,ROW(),MATCH(Mapping!$B$13,Raw_Fund_Import!$1:$1,0))&"",1))="Y",INDEX(Raw_Fund_Import!$A:$BZ,ROW(),MATCH(Mapping!$B$13,Raw_Fund_Import!$1:$1,0))&""="1",UPPER(INDEX(Raw_Fund_Import!$A:$BZ,ROW(),MATCH(Mapping!$B$13,Raw_Fund_Import!$1:$1,0))&"")="TRUE"),"Yes","No"),INDEX(Raw_Fund_Import!$A:$BZ,ROW(),MATCH(Mapping!$B$13,Raw_Fund_Import!$1:$1,0))))))),Mapping!$D$13)))) -> 1 | M2: =IF(Raw_Fund_Import!$A2="","",IF(Mapping!$B$14="",Mapping!$D$14,IF(OR(UPPER(INDEX(Raw_Fund_Import!$A:$BZ,ROW(),MATCH(Mapping!$B$14,Raw_Fund_Import!$1:$1,0))&"")="NA",UPPER(INDEX(Raw_Fund_Import!$A:$BZ,ROW(),MATCH(Mapping!$B$14,Raw_Fund_Import!$1:$1,0))&"")="N/A",INDEX(Raw_Fund_Import!$A:$BZ,ROW(),MATCH(Mapping!$B$14,Raw_Fund_Import!$1:$1,0))&""="-",INDEX(Raw_Fund_Import!$A:$BZ,ROW(),MATCH(Mapping!$B$14,Raw_Fund_Import!$1:$1,0))&""=""),Mapping!$D$14,IFERROR(IF(Mapping!$C$14="HHMM",TIME(INT(INDEX(Raw_Fund_Import!$A:$BZ,ROW(),MATCH(Mapping!$B$14,Raw_Fund_Import!$1:$1,0))/100),MOD(INDEX(Raw_Fund_Import!$A:$BZ,ROW(),MATCH(Mapping!$B$14,Raw_Fund_Import!$1:$1,0)),100),0),IF(Mapping!$C$14="TIME_TEXT",TIMEVALUE(INDEX(Raw_Fund_Import!$A:$BZ,ROW(),MATCH(Mapping!$B$14,Raw_Fund_Import!$1:$1,0))),IF(Mapping!$C$14="DEC_HR",INDEX(Raw_Fund_Import!$A:$BZ,ROW(),MATCH(Mapping!$B$14,Raw_Fund_Import!$1:$1,0))/24,IF(Mapping!$C$14="YN",IF(OR(UPPER(LEFT(INDEX(Raw_Fund_Import!$A:$BZ,ROW(),MATCH(Mapping!$B$14,Raw_Fund_Import!$1:$1,0))&"",1))="Y",INDEX(Raw_Fund_Import!$A:$BZ,ROW(),MATCH(Mapping!$B$14,Raw_Fund_Import!$1:$1,0))&""="1",UPPER(INDEX(Raw_Fund_Import!$A:$BZ,ROW(),MATCH(Mapping!$B$14,Raw_Fund_Import!$1:$1,0))&"")="TRUE"),1,0),IF(Mapping!$C$14="YESNO",IF(OR(UPPER(LEFT(INDEX(Raw_Fund_Import!$A:$BZ,ROW(),MATCH(Mapping!$B$14,Raw_Fund_Import!$1:$1,0))&"",1))="Y",INDEX(Raw_Fund_Import!$A:$BZ,ROW(),MATCH(Mapping!$B$14,Raw_Fund_Import!$1:$1,0))&""="1",UPPER(INDEX(Raw_Fund_Import!$A:$BZ,ROW(),MATCH(Mapping!$B$14,Raw_Fund_Import!$1:$1,0))&"")="TRUE"),"Yes","No"),INDEX(Raw_Fund_Import!$A:$BZ,ROW(),MATCH(Mapping!$B$14,Raw_Fund_Import!$1:$1,0))))))),Mapping!$D$14)))) -> 0 | N2: =IF(Raw_Fund_Import!$A2="","",IF(Mapping!$B$15="",Mapping!$D$15,IF(OR(UPPER(INDEX(Raw_Fund_Import!$A:$BZ,ROW(),MATCH(Mapping!$B$15,Raw_Fund_Import!$1:$1,0))&"")="NA",UPPER(INDEX(Raw_Fund_Import!$A:$BZ,ROW(),MATCH(Mapping!$B$15,Raw_Fund_Import!$1:$1,0))&"")="N/A",INDEX(Raw_Fund_Import!$A:$BZ,ROW(),MATCH(Mapping!$B$15,Raw_Fund_Import!$1:$1,0))&""="-",INDEX(Raw_Fund_Import!$A:$BZ,ROW(),MATCH(Mapping!$B$15,Raw_Fund_Import!$1:$1,0))&""=""),Mapping!$D$15,IFERROR(IF(Mapping!$C$15="HHMM",TIME(INT(INDEX(Raw_Fund_Import!$A:$BZ,ROW(),MATCH(Mapping!$B$15,Raw_Fund_Import!$1:$1,0))/100),MOD(INDEX(Raw_Fund_Import!$A:$BZ,ROW(),MATCH(Mapping!$B$15,Raw_Fund_Import!$1:$1,0)),100),0),IF(Mapping!$C$15="TIME_TEXT",TIMEVALUE(INDEX(Raw_Fund_Import!$A:$BZ,ROW(),MATCH(Mapping!$B$15,Raw_Fund_Import!$1:$1,0))),IF(Mapping!$C$15="DEC_HR",INDEX(Raw_Fund_Import!$A:$BZ,ROW(),MATCH(Mapping!$B$15,Raw_Fund_Import!$1:$1,0))/24,IF(Mapping!$C$15="YN",IF(OR(UPPER(LEFT(INDEX(Raw_Fund_Import!$A:$BZ,ROW(),MATCH(Mapping!$B$15,Raw_Fund_Import!$1:$1,0))&"",1))="Y",INDEX(Raw_Fund_Import!$A:$BZ,ROW(),MATCH(Mapping!$B$15,Raw_Fund_Import!$1:$1,0))&""="1",UPPER(INDEX(Raw_Fund_Import!$A:$BZ,ROW(),MATCH(Mapping!$B$15,Raw_Fund_Import!$1:$1,0))&"")="TRUE"),1,0),IF(Mapping!$C$15="YESNO",IF(OR(UPPER(LEFT(INDEX(Raw_Fund_Import!$A:$BZ,ROW(),MATCH(Mapping!$B$15,Raw_Fund_Import!$1:$1,0))&"",1))="Y",INDEX(Raw_Fund_Import!$A:$BZ,ROW(),MATCH(Mapping!$B$15,Raw_Fund_Import!$1:$1,0))&""="1",UPPER(INDEX(Raw_Fund_Import!$A:$BZ,ROW(),MATCH(Mapping!$B$15,Raw_Fund_Import!$1:$1,0))&"")="TRUE"),"Yes","No"),INDEX(Raw_Fund_Import!$A:$BZ,ROW(),MATCH(Mapping!$B$15,Raw_Fund_Import!$1:$1,0))))))),Mapping!$D$15)))) -> Yes | O2: =IF(Raw_Fund_Import!$A2="","",IF(Mapping!$B$16="",Mapping!$D$16,IF(OR(UPPER(INDEX(Raw_Fund_Import!$A:$BZ,ROW(),MATCH(Mapping!$B$16,Raw_Fund_Import!$1:$1,0))&"")="NA",UPPER(INDEX(Raw_Fund_Import!$A:$BZ,ROW(),MATCH(Mapping!$B$16,Raw_Fund_Import!$1:$1,0))&"")="N/A",INDEX(Raw_Fund_Import!$A:$BZ,ROW(),MATCH(Mapping!$B$16,Raw_Fund_Import!$1:$1,0))&""="-",INDEX(Raw_Fund_Import!$A:$BZ,ROW(),MATCH(Mapping!$B$16,Raw_Fund_Import!$1:$1,0))&""=""),Mapping!$D$16,IFERROR(IF(Mapping!$C$16="HHMM",TIME(INT(INDEX(Raw_Fund_Import!$A:$BZ,ROW(),MATCH(Mapping!$B$16,Raw_Fund_Import!$1:$1,0))/100),MOD(INDEX(Raw_Fund_Import!$A:$BZ,ROW(),MATCH(Mapping!$B$16,Raw_Fund_Import!$1:$1,0)),100),0),IF(Mapping!$C$16="TIME_TEXT",TIMEVALUE(INDEX(Raw_Fund_Import!$A:$BZ,ROW(),MATCH(Mapping!$B$16,Raw_Fund_Import!$1:$1,0))),IF(Mapping!$C$16="DEC_HR",INDEX(Raw_Fund_Import!$A:$BZ,ROW(),MATCH(Mapping!$B$16,Raw_Fund_Import!$1:$1,0))/24,IF(Mapping!$C$16="YN",IF(OR(UPPER(LEFT(INDEX(Raw_Fund_Import!$A:$BZ,ROW(),MATCH(Mapping!$B$16,Raw_Fund_Import!$1:$1,0))&"",1))="Y",INDEX(Raw_Fund_Import!$A:$BZ,ROW(),MATCH(Mapping!$B$16,Raw_Fund_Import!$1:$1,0))&""="1",UPPER(INDEX(Raw_Fund_Import!$A:$BZ,ROW(),MATCH(Mapping!$B$16,Raw_Fund_Import!$1:$1,0))&"")="TRUE"),1,0),IF(Mapping!$C$16="YESNO",IF(OR(UPPER(LEFT(INDEX(Raw_Fund_Import!$A:$BZ,ROW(),MATCH(Mapping!$B$16,Raw_Fund_Import!$1:$1,0))&"",1))="Y",INDEX(Raw_Fund_Import!$A:$BZ,ROW(),MATCH(Mapping!$B$16,Raw_Fund_Import!$1:$1,0))&""="1",UPPER(INDEX(Raw_Fund_Import!$A:$BZ,ROW(),MATCH(Mapping!$B$16,Raw_Fund_Import!$1:$1,0))&"")="TRUE"),"Yes","No"),INDEX(Raw_Fund_Import!$A:$BZ,ROW(),MATCH(Mapping!$B$16,Raw_Fund_Import!$1:$1,0))))))),Mapping!$D$16)))) -> No | P2: =IF(Raw_Fund_Import!$A2="","",IF(Mapping!$B$17="",Mapping!$D$17,IF(OR(UPPER(INDEX(Raw_Fund_Import!$A:$BZ,ROW(),MATCH(Mapping!$B$17,Raw_Fund_Import!$1:$1,0))&"")="NA",UPPER(INDEX(Raw_Fund_Import!$A:$BZ,ROW(),MATCH(Mapping!$B$17,Raw_Fund_Import!$1:$1,0))&"")="N/A",INDEX(Raw_Fund_Import!$A:$BZ,ROW(),MATCH(Mapping!$B$17,Raw_Fund_Import!$1:$1,0))&""="-",INDEX(Raw_Fund_Import!$A:$BZ,ROW(),MATCH(Mapping!$B$17,Raw_Fund_Import!$1:$1,0))&""=""),Mapping!$D$17,IFERROR(IF(Mapping!$C$17="HHMM",TIME(INT(INDEX(Raw_Fund_Import!$A:$BZ,ROW(),MATCH(Mapping!$B$17,Raw_Fund_Import!$1:$1,0))/100),MOD(INDEX(Raw_Fund_Import!$A:$BZ,ROW(),MATCH(Mapping!$B$17,Raw_Fund_Import!$1:$1,0)),100),0),IF(Mapping!$C$17="TIME_TEXT",TIMEVALUE(INDEX(Raw_Fund_Import!$A:$BZ,ROW(),MATCH(Mapping!$B$17,Raw_Fund_Import!$1:$1,0))),IF(Mapping!$C$17="DEC_HR",INDEX(Raw_Fund_Import!$A:$BZ,ROW(),MATCH(Mapping!$B$17,Raw_Fund_Import!$1:$1,0))/24,IF(Mapping!$C$17="YN",IF(OR(UPPER(LEFT(INDEX(Raw_Fund_Import!$A:$BZ,ROW(),MATCH(Mapping!$B$17,Raw_Fund_Import!$1:$1,0))&"",1))="Y",INDEX(Raw_Fund_Import!$A:$BZ,ROW(),MATCH(Mapping!$B$17,Raw_Fund_Import!$1:$1,0))&""="1",UPPER(INDEX(Raw_Fund_Import!$A:$BZ,ROW(),MATCH(Mapping!$B$17,Raw_Fund_Import!$1:$1,0))&"")="TRUE"),1,0),IF(Mapping!$C$17="YESNO",IF(OR(UPPER(LEFT(INDEX(Raw_Fund_Import!$A:$BZ,ROW(),MATCH(Mapping!$B$17,Raw_Fund_Import!$1:$1,0))&"",1))="Y",INDEX(Raw_Fund_Import!$A:$BZ,ROW(),MATCH(Mapping!$B$17,Raw_Fund_Import!$1:$1,0))&""="1",UPPER(INDEX(Raw_Fund_Import!$A:$BZ,ROW(),MATCH(Mapping!$B$17,Raw_Fund_Import!$1:$1,0))&"")="TRUE"),"Yes","No"),INDEX(Raw_Fund_Import!$A:$BZ,ROW(),MATCH(Mapping!$B$17,Raw_Fund_Import!$1:$1,0))))))),Mapping!$D$17)))) -> No | Q2: =IF(Raw_Fund_Import!$A2="","",IF(Mapping!$B$18="",Mapping!$D$18,IF(OR(UPPER(INDEX(Raw_Fund_Import!$A:$BZ,ROW(),MATCH(Mapping!$B$18,Raw_Fund_Import!$1:$1,0))&"")="NA",UPPER(INDEX(Raw_Fund_Import!$A:$BZ,ROW(),MATCH(Mapping!$B$18,Raw_Fund_Import!$1:$1,0))&"")="N/A",INDEX(Raw_Fund_Import!$A:$BZ,ROW(),MATCH(Mapping!$B$18,Raw_Fund_Import!$1:$1,0))&""="-",INDEX(Raw_Fund_Import!$A:$BZ,ROW(),MATCH(Mapping!$B$18,Raw_Fund_Import!$1:$1,0))&""=""),Mapping!$D$18,IFERROR(IF(Mapping!$C$18="HHMM",TIME(INT(INDEX(Raw_Fund_Import!$A:$BZ,ROW(),MATCH(Mapping!$B$18,Raw_Fund_Import!$1:$1,0))/100),MOD(INDEX(Raw_Fund_Import!$A:$BZ,ROW(),MATCH(Mapping!$B$18,Raw_Fund_Import!$1:$1,0)),100),0),IF(Mapping!$C$18="TIME_TEXT",TIMEVALUE(INDEX(Raw_Fund_Import!$A:$BZ,ROW(),MATCH(Mapping!$B$18,Raw_Fund_Import!$1:$1,0))),IF(Mapping!$C$18="DEC_HR",INDEX(Raw_Fund_Import!$A:$BZ,ROW(),MATCH(Mapping!$B$18,Raw_Fund_Import!$1:$1,0))/24,IF(Mapping!$C$18="YN",IF(OR(UPPER(LEFT(INDEX(Raw_Fund_Import!$A:$BZ,ROW(),MATCH(Mapping!$B$18,Raw_Fund_Import!$1:$1,0))&"",1))="Y",INDEX(Raw_Fund_Import!$A:$BZ,ROW(),MATCH(Mapping!$B$18,Raw_Fund_Import!$1:$1,0))&""="1",UPPER(INDEX(Raw_Fund_Import!$A:$BZ,ROW(),MATCH(Mapping!$B$18,Raw_Fund_Import!$1:$1,0))&"")="TRUE"),1,0),IF(Mapping!$C$18="YESNO",IF(OR(UPPER(LEFT(INDEX(Raw_Fund_Import!$A:$BZ,ROW(),MATCH(Mapping!$B$18,Raw_Fund_Import!$1:$1,0))&"",1))="Y",INDEX(Raw_Fund_Import!$A:$BZ,ROW(),MATCH(Mapping!$B$18,Raw_Fund_Import!$1:$1,0))&""="1",UPPER(INDEX(Raw_Fund_Import!$A:$BZ,ROW(),MATCH(Mapping!$B$18,Raw_Fund_Import!$1:$1,0))&"")="TRUE"),"Yes","No"),INDEX(Raw_Fund_Import!$A:$BZ,ROW(),MATCH(Mapping!$B$18,Raw_Fund_Import!$1:$1,0))))))),Mapping!$D$18)))) -> 0.20208333 | R2: =IF(Raw_Fund_Import!$A2="","",IF(Mapping!$B$19="",Mapping!$D$19,IF(OR(UPPER(INDEX(Raw_Fund_Import!$A:$BZ,ROW(),MATCH(Mapping!$B$19,Raw_Fund_Import!$1:$1,0))&"")="NA",UPPER(INDEX(Raw_Fund_Import!$A:$BZ,ROW(),MATCH(Mapping!$B$19,Raw_Fund_Import!$1:$1,0))&"")="N/A",INDEX(Raw_Fund_Import!$A:$BZ,ROW(),MATCH(Mapping!$B$19,Raw_Fund_Import!$1:$1,0))&""="-",INDEX(Raw_Fund_Import!$A:$BZ,ROW(),MATCH(Mapping!$B$19,Raw_Fund_Import!$1:$1,0))&""=""),Mapping!$D$19,IFERROR(IF(Mapping!$C$19="HHMM",TIME(INT(INDEX(Raw_Fund_Import!$A:$BZ,ROW(),MATCH(Mapping!$B$19,Raw_Fund_Import!$1:$1,0))/100),MOD(INDEX(Raw_Fund_Import!$A:$BZ,ROW(),MATCH(Mapping!$B$19,Raw_Fund_Import!$1:$1,0)),100),0),IF(Mapping!$C$19="TIME_TEXT",TIMEVALUE(INDEX(Raw_Fund_Import!$A:$BZ,ROW(),MATCH(Mapping!$B$19,Raw_Fund_Import!$1:$1,0))),IF(Mapping!$C$19="DEC_HR",INDEX(Raw_Fund_Import!$A:$BZ,ROW(),MATCH(Mapping!$B$19,Raw_Fund_Import!$1:$1,0))/24,IF(Mapping!$C$19="YN",IF(OR(UPPER(LEFT(INDEX(Raw_Fund_Import!$A:$BZ,ROW(),MATCH(Mapping!$B$19,Raw_Fund_Import!$1:$1,0))&"",1))="Y",INDEX(Raw_Fund_Import!$A:$BZ,ROW(),MATCH(Mapping!$B$19,Raw_Fund_Import!$1:$1,0))&""="1",UPPER(INDEX(Raw_Fund_Import!$A:$BZ,ROW(),MATCH(Mapping!$B$19,Raw_Fund_Import!$1:$1,0))&"")="TRUE"),1,0),IF(Mapping!$C$19="YESNO",IF(OR(UPPER(LEFT(INDEX(Raw_Fund_Import!$A:$BZ,ROW(),MATCH(Mapping!$B$19,Raw_Fund_Import!$1:$1,0))&"",1))="Y",INDEX(Raw_Fund_Import!$A:$BZ,ROW(),MATCH(Mapping!$B$19,Raw_Fund_Import!$1:$1,0))&""="1",UPPER(INDEX(Raw_Fund_Import!$A:$BZ,ROW(),MATCH(Mapping!$B$19,Raw_Fund_Import!$1:$1,0))&"")="TRUE"),"Yes","No"),INDEX(Raw_Fund_Import!$A:$BZ,ROW(),MATCH(Mapping!$B$19,Raw_Fund_Import!$1:$1,0))))))),Mapping!$D$19)))) -> 0.52083333 | S2: =IF(Raw_Fund_Import!$A2="","",IF(Mapping!$B$20="",Mapping!$D$20,IF(OR(UPPER(INDEX(Raw_Fund_Import!$A:$BZ,ROW(),MATCH(Mapping!$B$20,Raw_Fund_Import!$1:$1,0))&"")="NA",UPPER(INDEX(Raw_Fund_Import!$A:$BZ,ROW(),MATCH(Mapping!$B$20,Raw_Fund_Import!$1:$1,0))&"")="N/A",INDEX(Raw_Fund_Import!$A:$BZ,ROW(),MATCH(Mapping!$B$20,Raw_Fund_Import!$1:$1,0))&""="-",INDEX(Raw_Fund_Import!$A:$BZ,ROW(),MATCH(Mapping!$B$20,Raw_Fund_Import!$1:$1,0))&""=""),Mapping!$D$20,IFERROR(IF(Mapping!$C$20="HHMM",TIME(INT(INDEX(Raw_Fund_Import!$A:$BZ,ROW(),MATCH(Mapping!$B$20,Raw_Fund_Import!$1:$1,0))/100),MOD(INDEX(Raw_Fund_Import!$A:$BZ,ROW(),MATCH(Mapping!$B$20,Raw_Fund_Import!$1:$1,0)),100),0),IF(Mapping!$C$20="TIME_TEXT",TIMEVALUE(INDEX(Raw_Fund_Import!$A:$BZ,ROW(),MATCH(Mapping!$B$20,Raw_Fund_Import!$1:$1,0))),IF(Mapping!$C$20="DEC_HR",INDEX(Raw_Fund_Import!$A:$BZ,ROW(),MATCH(Mapping!$B$20,Raw_Fund_Import!$1:$1,0))/24,IF(Mapping!$C$20="YN",IF(OR(UPPER(LEFT(INDEX(Raw_Fund_Import!$A:$BZ,ROW(),MATCH(Mapping!$B$20,Raw_Fund_Import!$1:$1,0))&"",1))="Y",INDEX(Raw_Fund_Import!$A:$BZ,ROW(),MATCH(Mapping!$B$20,Raw_Fund_Import!$1:$1,0))&""="1",UPPER(INDEX(Raw_Fund_Import!$A:$BZ,ROW(),MATCH(Mapping!$B$20,Raw_Fund_Import!$1:$1,0))&"")="TRUE"),1,0),IF(Mapping!$C$20="YESNO",IF(OR(UPPER(LEFT(INDEX(Raw_Fund_Import!$A:$BZ,ROW(),MATCH(Mapping!$B$20,Raw_Fund_Import!$1:$1,0))&"",1))="Y",INDEX(Raw_Fund_Import!$A:$BZ,ROW(),MATCH(Mapping!$B$20,Raw_Fund_Import!$1:$1,0))&""="1",UPPER(INDEX(Raw_Fund_Import!$A:$BZ,ROW(),MATCH(Mapping!$B$20,Raw_Fund_Import!$1:$1,0))&"")="TRUE"),"Yes","No"),INDEX(Raw_Fund_Import!$A:$BZ,ROW(),MATCH(Mapping!$B$20,Raw_Fund_Import!$1:$1,0))))))),Mapping!$D$20)))) -> 0.52083333 | T2: =IF(Raw_Fund_Import!$A2="","",IF(Mapping!$B$21="",Mapping!$D$21,IF(OR(UPPER(INDEX(Raw_Fund_Import!$A:$BZ,ROW(),MATCH(Mapping!$B$21,Raw_Fund_Import!$1:$1,0))&"")="NA",UPPER(INDEX(Raw_Fund_Import!$A:$BZ,ROW(),MATCH(Mapping!$B$21,Raw_Fund_Import!$1:$1,0))&"")="N/A",INDEX(Raw_Fund_Import!$A:$BZ,ROW(),MATCH(Mapping!$B$21,Raw_Fund_Import!$1:$1,0))&""="-",INDEX(Raw_Fund_Import!$A:$BZ,ROW(),MATCH(Mapping!$B$21,Raw_Fund_Import!$1:$1,0))&""=""),Mapping!$D$21,IFERROR(IF(Mapping!$C$21="HHMM",TIME(INT(INDEX(Raw_Fund_Import!$A:$BZ,ROW(),MATCH(Mapping!$B$21,Raw_Fund_Import!$1:$1,0))/100),MOD(INDEX(Raw_Fund_Import!$A:$BZ,ROW(),MATCH(Mapping!$B$21,Raw_Fund_Import!$1:$1,0)),100),0),IF(Mapping!$C$21="TIME_TEXT",TIMEVALUE(INDEX(Raw_Fund_Import!$A:$BZ,ROW(),MATCH(Mapping!$B$21,Raw_Fund_Import!$1:$1,0))),IF(Mapping!$C$21="DEC_HR",INDEX(Raw_Fund_Import!$A:$BZ,ROW(),MATCH(Mapping!$B$21,Raw_Fund_Import!$1:$1,0))/24,IF(Mapping!$C$21="YN",IF(OR(UPPER(LEFT(INDEX(Raw_Fund_Import!$A:$BZ,ROW(),MATCH(Mapping!$B$21,Raw_Fund_Import!$1:$1,0))&"",1))="Y",INDEX(Raw_Fund_Import!$A:$BZ,ROW(),MATCH(Mapping!$B$21,Raw_Fund_Import!$1:$1,0))&""="1",UPPER(INDEX(Raw_Fund_Import!$A:$BZ,ROW(),MATCH(Mapping!$B$21,Raw_Fund_Import!$1:$1,0))&"")="TRUE"),1,0),IF(Mapping!$C$21="YESNO",IF(OR(UPPER(LEFT(INDEX(Raw_Fund_Import!$A:$BZ,ROW(),MATCH(Mapping!$B$21,Raw_Fund_Import!$1:$1,0))&"",1))="Y",INDEX(Raw_Fund_Import!$A:$BZ,ROW(),MATCH(Mapping!$B$21,Raw_Fund_Import!$1:$1,0))&""="1",UPPER(INDEX(Raw_Fund_Import!$A:$BZ,ROW(),MATCH(Mapping!$B$21,Raw_Fund_Import!$1:$1,0))&"")="TRUE"),"Yes","No"),INDEX(Raw_Fund_Import!$A:$BZ,ROW(),MATCH(Mapping!$B$21,Raw_Fund_Import!$1:$1,0))))))),Mapping!$D$21)))) -> 0.52083333 | U2: =IF(Raw_Fund_Import!$A2="","",IF(Mapping!$B$22="",Mapping!$D$22,IF(OR(UPPER(INDEX(Raw_Fund_Import!$A:$BZ,ROW(),MATCH(Mapping!$B$22,Raw_Fund_Import!$1:$1,0))&"")="NA",UPPER(INDEX(Raw_Fund_Import!$A:$BZ,ROW(),MATCH(Mapping!$B$22,Raw_Fund_Import!$1:$1,0))&"")="N/A",INDEX(Raw_Fund_Import!$A:$BZ,ROW(),MATCH(Mapping!$B$22,Raw_Fund_Import!$1:$1,0))&""="-",INDEX(Raw_Fund_Import!$A:$BZ,ROW(),MATCH(Mapping!$B$22,Raw_Fund_Import!$1:$1,0))&""=""),Mapping!$D$22,IFERROR(IF(Mapping!$C$22="HHMM",TIME(INT(INDEX(Raw_Fund_Import!$A:$BZ,ROW(),MATCH(Mapping!$B$22,Raw_Fund_Import!$1:$1,0))/100),MOD(INDEX(Raw_Fund_Import!$A:$BZ,ROW(),MATCH(Mapping!$B$22,Raw_Fund_Import!$1:$1,0)),100),0),IF(Mapping!$C$22="TIME_TEXT",TIMEVALUE(INDEX(Raw_Fund_Import!$A:$BZ,ROW(),MATCH(Mapping!$B$22,Raw_Fund_Import!$1:$1,0))),IF(Mapping!$C$22="DEC_HR",INDEX(Raw_Fund_Import!$A:$BZ,ROW(),MATCH(Mapping!$B$22,Raw_Fund_Import!$1:$1,0))/24,IF(Mapping!$C$22="YN",IF(OR(UPPER(LEFT(INDEX(Raw_Fund_Import!$A:$BZ,ROW(),MATCH(Mapping!$B$22,Raw_Fund_Import!$1:$1,0))&"",1))="Y",INDEX(Raw_Fund_Import!$A:$BZ,ROW(),MATCH(Mapping!$B$22,Raw_Fund_Import!$1:$1,0))&""="1",UPPER(INDEX(Raw_Fund_Import!$A:$BZ,ROW(),MATCH(Mapping!$B$22,Raw_Fund_Import!$1:$1,0))&"")="TRUE"),1,0),IF(Mapping!$C$22="YESNO",IF(OR(UPPER(LEFT(INDEX(Raw_Fund_Import!$A:$BZ,ROW(),MATCH(Mapping!$B$22,Raw_Fund_Import!$1:$1,0))&"",1))="Y",INDEX(Raw_Fund_Import!$A:$BZ,ROW(),MATCH(Mapping!$B$22,Raw_Fund_Import!$1:$1,0))&""="1",UPPER(INDEX(Raw_Fund_Import!$A:$BZ,ROW(),MATCH(Mapping!$B$22,Raw_Fund_Import!$1:$1,0))&"")="TRUE"),"Yes","No"),INDEX(Raw_Fund_Import!$A:$BZ,ROW(),MATCH(Mapping!$B$22,Raw_Fund_Import!$1:$1,0))))))),Mapping!$D$22)))) -> 0.69722222 | V2: =IF(Raw_Fund_Import!$A2="","",IF(Mapping!$B$23="",Mapping!$D$23,IF(OR(UPPER(INDEX(Raw_Fund_Import!$A:$BZ,ROW(),MATCH(Mapping!$B$23,Raw_Fund_Import!$1:$1,0))&"")="NA",UPPER(INDEX(Raw_Fund_Import!$A:$BZ,ROW(),MATCH(Mapping!$B$23,Raw_Fund_Import!$1:$1,0))&"")="N/A",INDEX(Raw_Fund_Import!$A:$BZ,ROW(),MATCH(Mapping!$B$23,Raw_Fund_Import!$1:$1,0))&""="-",INDEX(Raw_Fund_Import!$A:$BZ,ROW(),MATCH(Mapping!$B$23,Raw_Fund_Import!$1:$1,0))&""=""),Mapping!$D$23,IFERROR(IF(Mapping!$C$23="HHMM",TIME(INT(INDEX(Raw_Fund_Import!$A:$BZ,ROW(),MATCH(Mapping!$B$23,Raw_Fund_Import!$1:$1,0))/100),MOD(INDEX(Raw_Fund_Import!$A:$BZ,ROW(),MATCH(Mapping!$B$23,Raw_Fund_Import!$1:$1,0)),100),0),IF(Mapping!$C$23="TIME_TEXT",TIMEVALUE(INDEX(Raw_Fund_Import!$A:$BZ,ROW(),MATCH(Mapping!$B$23,Raw_Fund_Import!$1:$1,0))),IF(Mapping!$C$23="DEC_HR",INDEX(Raw_Fund_Import!$A:$BZ,ROW(),MATCH(Mapping!$B$23,Raw_Fund_Import!$1:$1,0))/24,IF(Mapping!$C$23="YN",IF(OR(UPPER(LEFT(INDEX(Raw_Fund_Import!$A:$BZ,ROW(),MATCH(Mapping!$B$23,Raw_Fund_Import!$1:$1,0))&"",1))="Y",INDEX(Raw_Fund_Import!$A:$BZ,ROW(),MATCH(Mapping!$B$23,Raw_Fund_Import!$1:$1,0))&""="1",UPPER(INDEX(Raw_Fund_Import!$A:$BZ,ROW(),MATCH(Mapping!$B$23,Raw_Fund_Import!$1:$1,0))&"")="TRUE"),1,0),IF(Mapping!$C$23="YESNO",IF(OR(UPPER(LEFT(INDEX(Raw_Fund_Import!$A:$BZ,ROW(),MATCH(Mapping!$B$23,Raw_Fund_Import!$1:$1,0))&"",1))="Y",INDEX(Raw_Fund_Import!$A:$BZ,ROW(),MATCH(Mapping!$B$23,Raw_Fund_Import!$1:$1,0))&""="1",UPPER(INDEX(Raw_Fund_Import!$A:$BZ,ROW(),MATCH(Mapping!$B$23,Raw_Fund_Import!$1:$1,0))&"")="TRUE"),"Yes","No"),INDEX(Raw_Fund_Import!$A:$BZ,ROW(),MATCH(Mapping!$B$23,Raw_Fund_Import!$1:$1,0))))))),Mapping!$D$23)))) -> 0.72152778 | W2: =IF(Raw_Fund_Import!$A2="","",IF(Mapping!$B$24="",Mapping!$D$24,IF(OR(UPPER(INDEX(Raw_Fund_Import!$A:$BZ,ROW(),MATCH(Mapping!$B$24,Raw_Fund_Import!$1:$1,0))&"")="NA",UPPER(INDEX(Raw_Fund_Import!$A:$BZ,ROW(),MATCH(Mapping!$B$24,Raw_Fund_Import!$1:$1,0))&"")="N/A",INDEX(Raw_Fund_Import!$A:$BZ,ROW(),MATCH(Mapping!$B$24,Raw_Fund_Import!$1:$1,0))&""="-",INDEX(Raw_Fund_Import!$A:$BZ,ROW(),MATCH(Mapping!$B$24,Raw_Fund_Import!$1:$1,0))&""=""),Mapping!$D$24,IFERROR(IF(Mapping!$C$24="HHMM",TIME(INT(INDEX(Raw_Fund_Import!$A:$BZ,ROW(),MATCH(Mapping!$B$24,Raw_Fund_Import!$1:$1,0))/100),MOD(INDEX(Raw_Fund_Import!$A:$BZ,ROW(),MATCH(Mapping!$B$24,Raw_Fund_Import!$1:$1,0)),100),0),IF(Mapping!$C$24="TIME_TEXT",TIMEVALUE(INDEX(Raw_Fund_Import!$A:$BZ,ROW(),MATCH(Mapping!$B$24,Raw_Fund_Import!$1:$1,0))),IF(Mapping!$C$24="DEC_HR",INDEX(Raw_Fund_Import!$A:$BZ,ROW(),MATCH(Mapping!$B$24,Raw_Fund_Import!$1:$1,0))/24,IF(Mapping!$C$24="YN",IF(OR(UPPER(LEFT(INDEX(Raw_Fund_Import!$A:$BZ,ROW(),MATCH(Mapping!$B$24,Raw_Fund_Import!$1:$1,0))&"",1))="Y",INDEX(Raw_Fund_Import!$A:$BZ,ROW(),MATCH(Mapping!$B$24,Raw_Fund_Import!$1:$1,0))&""="1",UPPER(INDEX(Raw_Fund_Import!$A:$BZ,ROW(),MATCH(Mapping!$B$24,Raw_Fund_Import!$1:$1,0))&"")="TRUE"),1,0),IF(Mapping!$C$24="YESNO",IF(OR(UPPER(LEFT(INDEX(Raw_Fund_Import!$A:$BZ,ROW(),MATCH(Mapping!$B$24,Raw_Fund_Import!$1:$1,0))&"",1))="Y",INDEX(Raw_Fund_Import!$A:$BZ,ROW(),MATCH(Mapping!$B$24,Raw_Fund_Import!$1:$1,0))&""="1",UPPER(INDEX(Raw_Fund_Import!$A:$BZ,ROW(),MATCH(Mapping!$B$24,Raw_Fund_Import!$1:$1,0))&"")="TRUE"),"Yes","No"),INDEX(Raw_Fund_Import!$A:$BZ,ROW(),MATCH(Mapping!$B$24,Raw_Fund_Import!$1:$1,0))))))),Mapping!$D$24)))) -> FA | X2: =IF(Raw_Fund_Import!$A2="","",IF(Mapping!$B$25="",Mapping!$D$25,IF(OR(UPPER(INDEX(Raw_Fund_Import!$A:$BZ,ROW(),MATCH(Mapping!$B$25,Raw_Fund_Import!$1:$1,0))&"")="NA",UPPER(INDEX(Raw_Fund_Import!$A:$BZ,ROW(),MATCH(Mapping!$B$25,Raw_Fund_Import!$1:$1,0))&"")="N/A",INDEX(Raw_Fund_Import!$A:$BZ,ROW(),MATCH(Mapping!$B$25,Raw_Fund_Import!$1:$1,0))&""="-",INDEX(Raw_Fund_Import!$A:$BZ,ROW(),MATCH(Mapping!$B$25,Raw_Fund_Import!$1:$1,0))&""=""),Mapping!$D$25,IFERROR(IF(Mapping!$C$25="HHMM",TIME(INT(INDEX(Raw_Fund_Import!$A:$BZ,ROW(),MATCH(Mapping!$B$25,Raw_Fund_Import!$1:$1,0))/100),MOD(INDEX(Raw_Fund_Import!$A:$BZ,ROW(),MATCH(Mapping!$B$25,Raw_Fund_Import!$1:$1,0)),100),0),IF(Mapping!$C$25="TIME_TEXT",TIMEVALUE(INDEX(Raw_Fund_Import!$A:$BZ,ROW(),MATCH(Mapping!$B$25,Raw_Fund_Import!$1:$1,0))),IF(Mapping!$C$25="DEC_HR",INDEX(Raw_Fund_Import!$A:$BZ,ROW(),MATCH(Mapping!$B$25,Raw_Fund_Import!$1:$1,0))/24,IF(Mapping!$C$25="YN",IF(OR(UPPER(LEFT(INDEX(Raw_Fund_Import!$A:$BZ,ROW(),MATCH(Mapping!$B$25,Raw_Fund_Import!$1:$1,0))&"",1))="Y",INDEX(Raw_Fund_Import!$A:$BZ,ROW(),MATCH(Mapping!$B$25,Raw_Fund_Import!$1:$1,0))&""="1",UPPER(INDEX(Raw_Fund_Import!$A:$BZ,ROW(),MATCH(Mapping!$B$25,Raw_Fund_Import!$1:$1,0))&"")="TRUE"),1,0),IF(Mapping!$C$25="YESNO",IF(OR(UPPER(LEFT(INDEX(Raw_Fund_Import!$A:$BZ,ROW(),MATCH(Mapping!$B$25,Raw_Fund_Import!$1:$1,0))&"",1))="Y",INDEX(Raw_Fund_Import!$A:$BZ,ROW(),MATCH(Mapping!$B$25,Raw_Fund_Import!$1:$1,0))&""="1",UPPER(INDEX(Raw_Fund_Import!$A:$BZ,ROW(),MATCH(Mapping!$B$25,Raw_Fund_Import!$1:$1,0))&"")="TRUE"),"Yes","No"),INDEX(Raw_Fund_Import!$A:$BZ,ROW(),MATCH(Mapping!$B$25,Raw_Fund_Import!$1:$1,0))))))),Mapping!$D$25)))) -> Confirmed | Y2: =IF(Raw_Fund_Import!$A2="","",IF(COUNTBLANK($A2:$X2)>0,"CHECK","OK")) -> OK
